Workbook

Sheet GWIND_BS
A1: GALATA WIND ENERJİ A.Ş. — KONSOLİDE BİLANÇO / CONSOLIDATED BALANCE SHEET (BİN TL) | L1: DİKEY ANALİZ (% Toplam Aktifler)
A2: KALEM (BİN TL) | B2: 31.12.2025 (2025 SAG) | C2: 31.12.2024 (2025 SAG) | D2: 31.12.2024 (2024 SAG) | E2: 31.12.2023 (2024 SAG) | F2: 31.12.2023 (2023 SAG) | G2: 31.12.2022 (2023 SAG) | H2: 31.12.2022 (Nominal) | I2: 31.12.2021 (Nominal) | J2: 31.12.2020 (Nominal) | L2: 31.12.2025 (2025 SAG) | M2: 31.12.2024 (2025 SAG) | N2: 31.12.2024 (2024 SAG) | O2: 31.12.2023 (2024 SAG) | P2: 31.12.2023 (2023 SAG) | Q2: 31.12.2022 (2023 SAG) | R2: 31.12.2022 (Nominal) | S2: 31.12.2021 (Nominal) | T2: 31.12.2020 (Nominal)
A3: VARLIKLAR / ASSETS
A4: DÖNEN VARLIKLAR / CURRENT ASSETS
A5: Nakit ve Nakit Benzerleri (Cash & equivalents) | B5: 1187134.7 | C5: 1725691.1 | D5: 1318405.1 | E5: 95293.91 | F5: 66002.716 | G5: 1085983.8 | H5: 659079.07 | I5: 158919.08 | J5: 66124.675 | L5: =IFERROR(B5/B16,"") -> 0.05836851 | M5: =IFERROR(C5/C16,"") -> 0.089024187 | N5: =IFERROR(D5/D16,"") -> 0.089024187 | O5: =IFERROR(E5/E16,"") -> 0.0072058993 | P5: =IFERROR(F5/F16,"") -> 0.0072058993 | Q5: =IFERROR(G5/G16,"") -> 0.12394282 | R5: =IFERROR(H5/H16,"") -> 0.26722762 | S5: =IFERROR(I5/I16,"") -> 0.089907404 | T5: =IFERROR(J5/J16,"") -> 0.040802119
A6: Finansal Yatırımlar KV (ST financial investments) | B6: 653770.19 | C6: 0 | D6: 0 | E6: 127473.44 | F6: 88290.984 | G6: 125720.82 | H6: 76299.442 | I6: 0 | J6: 0 | L6: =IFERROR(B6/B16,"") -> 0.032144282 | M6: =IFERROR(C6/C16,"") -> 0 | N6: =IFERROR(D6/D16,"") -> 0 | O6: =IFERROR(E6/E16,"") -> 0.0096392388 | P6: =IFERROR(F6/F16,"") -> 0.0096392388 | Q6: =IFERROR(G6/G16,"") -> 0.014348458 | R6: =IFERROR(H6/H16,"") -> 0.030936073 | S6: =IFERROR(I6/I16,"") -> 0 | T6: =IFERROR(J6/J16,"") -> 0
A7: Ticari Alacaklar (Trade receivables, net) | B7: 284414.93 | C7: 287927.65 | D7: 219977.91 | E7: 199688.28 | F7: 138308.61 | G7: 138620.85 | H7: 84128.414 | I7: 84322.217 | J7: 34809.442 | L7: =IFERROR(B7/B16,"") -> 0.013983987 | M7: =IFERROR(C7/C16,"") -> 0.014853484 | N7: =IFERROR(D7/D16,"") -> 0.014853822 | O7: =IFERROR(E7/E16,"") -> 0.015099953 | P7: =IFERROR(F7/F16,"") -> 0.015099954 | Q7: =IFERROR(G7/G16,"") -> 0.015820732 | R7: =IFERROR(H7/H16,"") -> 0.034110377 | S7: =IFERROR(I7/I16,"") -> 0.04770473 | T7: =IFERROR(J7/J16,"") -> 0.021479108
A8: Stoklar (Inventories) | B8: 4409.483 | C8: 9281.389 | D8: 7090.857 | E8: 7090.857 | F8: 4911.288 | G8: 4939.75 | H8: 818.695 | I8: 835.022 | J8: 1664.977 | L8: =IFERROR(B8/B16,"") -> 0.0002168035 | M8: =IFERROR(C8/C16,"") -> 0.00047880416 | N8: =IFERROR(D8/D16,"") -> 0.0004788041 | O8: =IFERROR(E8/E16,"") -> 0.00053619377 | P8: =IFERROR(F8/F16,"") -> 0.00053619379 | Q8: =IFERROR(G8/G16,"") -> 0.00056377135 | R8: =IFERROR(H8/H16,"") -> 0.00033194487 | S8: =IFERROR(I8/I16,"") -> 0.00047240811 | T8: =IFERROR(J8/J16,"") -> 0.0010273713
A9: Diğer Dönen Varlıklar (Peşin öd., diğer alacaklar, vb.) | B9: 60201.531 | C9: 94202.658 | D9: 71964.575 | E9: 41725 | F9: 28899.679 | G9: 150499.57 | H9: 87980.426 | I9: 145014.46 | J9: 68896.001 | L9: =IFERROR(B9/B16,"") -> 0.0029599621 | M9: =IFERROR(C9/C16,"") -> 0.0048596848 | N9: =IFERROR(D9/D16,"") -> 0.0048593469 | O9: =IFERROR(E9/E16,"") -> 0.0031551455 | P9: =IFERROR(F9/F16,"") -> 0.0031551456 | Q9: =IFERROR(G9/G16,"") -> 0.017176446 | R9: =IFERROR(H9/H16,"") -> 0.035672199 | S9: =IFERROR(I9/I16,"") -> 0.08204096 | T9: =IFERROR(J9/J16,"") -> 0.042512161
A10: DÖNEN VARLIKLAR TOPLAM (TOTAL CURRENT ASSETS) | B10: =SUM(B5:B9) -> 2189930.8 | C10: =SUM(C5:C9) -> 2117102.8 | D10: =SUM(D5:D9) -> 1617438.5 | E10: =SUM(E5:E9) -> 471271.48 | F10: =SUM(F5:F9) -> 326413.28 | G10: =SUM(G5:G9) -> 1505764.8 | H10: =SUM(H5:H9) -> 908306.05 | I10: =SUM(I5:I9) -> 389090.77 | J10: =SUM(J5:J9) -> 171495.1 | L10: =IFERROR(B10/B16,"") -> 0.10767354 | M10: =IFERROR(C10/C16,"") -> 0.10921616 | N10: =IFERROR(D10/D16,"") -> 0.10921616 | O10: =IFERROR(E10/E16,"") -> 0.035636431 | P10: =IFERROR(F10/F16,"") -> 0.035636431 | Q10: =IFERROR(G10/G16,"") -> 0.17185223 | R10: =IFERROR(H10/H16,"") -> 0.36827821 | S10: =IFERROR(I10/I16,"") -> 0.2201255 | T10: =IFERROR(J10/J16,"") -> 0.10582076
A11: DURAN VARLIKLAR / NON-CURRENT ASSETS
A12: Maddi Duran Varlıklar (Property, plant & equipment) | B12: 11487462 | C12: 11669954 | D12: 8915690.1 | E12: 7429653.2 | F12: 5145945.7 | G12: 4148764.7 | H12: 892677.41 | I12: 880684.72 | J12: 849662 | L12: =IFERROR(B12/B16,"") -> 0.56481041 | M12: =IFERROR(C12/C16,"") -> 0.60202441 | N12: =IFERROR(D12/D16,"") -> 0.60202441 | O12: =IFERROR(E12/E16,"") -> 0.56181274 | P12: =IFERROR(F12/F16,"") -> 0.56181274 | Q12: =IFERROR(G12/G16,"") -> 0.47349657 | R12: =IFERROR(H12/H16,"") -> 0.36194148 | S12: =IFERROR(I12/I16,"") -> 0.49824149 | T12: =IFERROR(J12/J16,"") -> 0.5242825
A13: Maddi Olmayan Duran Varlıklar (Lis., Şerefiye, Haklar) | B13: 6097478.8 | C13: 5025353.2 | D13: 3839303.1 | E13: 3829789.9 | F13: 2652598.3 | G13: 2718735.1 | H13: 341391.08 | I13: 312943.83 | J13: 319686.11 | L13: =IFERROR(B13/B16,"") -> 0.29979812 | M13: =IFERROR(C13/C16,"") -> 0.25924568 | N13: =IFERROR(D13/D16,"") -> 0.25924568 | O13: =IFERROR(E13/E16,"") -> 0.28959962 | P13: =IFERROR(F13/F16,"") -> 0.28959955 | Q13: =IFERROR(G13/G16,"") -> 0.31028796 | R13: =IFERROR(H13/H16,"") -> 0.13841909 | S13: =IFERROR(I13/I16,"") -> 0.17704588 | T13: =IFERROR(J13/J16,"") -> 0.19726178
A14: Diğer Duran Varlıklar (Türev, KHV, Peşin Öd., ETVarlık) | B14: 563744.18 | C14: 572109.77 | D14: 437084.26 | E14: 1493715.4 | F14: 1034581.7 | G14: 388709.53 | H14: 323983.84 | I14: 184866.76 | J14: 279775.44 | L14: =IFERROR(B14/B16,"") -> 0.027717923 | M14: =IFERROR(C14/C16,"") -> 0.029513744 | N14: =IFERROR(D14/D16,"") -> 0.029513744 | O14: =IFERROR(E14/E16,"") -> 0.11295121 | P14: =IFERROR(F14/F16,"") -> 0.11295128 | Q14: =IFERROR(G14/G16,"") -> 0.044363237 | R14: =IFERROR(H14/H16,"") -> 0.13136122 | S14: =IFERROR(I14/I16,"") -> 0.10458713 | T14: =IFERROR(J14/J16,"") -> 0.17263496
A15: DURAN VARLIKLAR TOPLAM (TOTAL NON-CURRENT ASSETS) | B15: =SUM(B12:B14) -> 18148685 | C15: =SUM(C12:C14) -> 17267417 | D15: =SUM(D12:D14) -> 13192077 | E15: =SUM(E12:E14) -> 12753158 | F15: =SUM(F12:F14) -> 8833125.8 | G15: =SUM(G12:G14) -> 7256209.3 | H15: =SUM(H12:H14) -> 1558052.3 | I15: =SUM(I12:I14) -> 1378495.3 | J15: =SUM(J12:J14) -> 1449123.5 | L15: =IFERROR(B15/B16,"") -> 0.89232646 | M15: =IFERROR(C15/C16,"") -> 0.89078384 | N15: =IFERROR(D15/D16,"") -> 0.89078384 | O15: =IFERROR(E15/E16,"") -> 0.96436357 | P15: =IFERROR(F15/F16,"") -> 0.96436357 | Q15: =IFERROR(G15/G16,"") -> 0.82814777 | R15: =IFERROR(H15/H16,"") -> 0.63172179 | S15: =IFERROR(I15/I16,"") -> 0.7798745 | T15: =IFERROR(J15/J16,"") -> 0.89417924
A16: TOPLAM VARLIKLAR (TOTAL ASSETS) | B16: =B10+B15 -> 20338616 | C16: =C10+C15 -> 19384520 | D16: =D10+D15 -> 14809516 | E16: =E10+E15 -> 13224430 | F16: =F10+F15 -> 9159539.1 | G16: =G10+G15 -> 8761974.1 | H16: =H10+H15 -> 2466358.4 | I16: =I10+I15 -> 1767586.1 | J16: =J10+J15 -> 1620618.6 | L16: =IFERROR(B16/B16,"") -> 1 | M16: =IFERROR(C16/C16,"") -> 1 | N16: =IFERROR(D16/D16,"") -> 1 | O16: =IFERROR(E16/E16,"") -> 1 | P16: =IFERROR(F16/F16,"") -> 1 | Q16: =IFERROR(G16/G16,"") -> 1 | R16: =IFERROR(H16/H16,"") -> 1 | S16: =IFERROR(I16/I16,"") -> 1 | T16: =IFERROR(J16/J16,"") -> 1
A17: KAYNAKLAR / LIABILITIES & EQUITY
A18: KISA VADELİ YÜKÜMLÜLÜKLER / CURRENT LIABILITIES
A19: Kısa Vadeli Finansal Borçlar (ST borrowings + lease ST) | B19: 707962.99 | C19: 735797.55 | D19: 562139.55 | E19: 118107.89 | F19: 118108.89 | G19: 112506.03 | H19: 68279.442 | I19: 249449.8 | J19: 123620.11 | L19: =IFERROR(B19/B16,"") -> 0.034808809 | M19: =IFERROR(C19/C16,"") -> 0.037957996 | N19: =IFERROR(D19/D16,"") -> 0.037957996 | O19: =IFERROR(E19/E16,"") -> 0.0089310385 | P19: =IFERROR(F19/F16,"") -> 0.012894633 | Q19: =IFERROR(G19/G16,"") -> 0.01284026 | R19: =IFERROR(H19/H16,"") -> 0.027684315 | S19: =IFERROR(I19/I16,"") -> 0.14112456 | T19: =IFERROR(J19/J16,"") -> 0.07627958
A20: Ticari Borçlar (Trade payables, related + 3rd party) | B20: 61033.761 | C20: 181188.88 | D20: 138425.9 | E20: 101813.21 | F20: 70335.328 | G20: 45170.596 | H20: 17469.688 | I20: 8873.794 | J20: 7050.392 | L20: =IFERROR(B20/B16,"") -> 0.0030008808 | M20: =IFERROR(C20/C16,"") -> 0.0093470912 | N20: =IFERROR(D20/D16,"") -> 0.0093470912 | O20: =IFERROR(E20/E16,"") -> 0.0076988731 | P20: =IFERROR(F20/F16,"") -> 0.0076789157 | Q20: =IFERROR(G20/G16,"") -> 0.005155299 | R20: =IFERROR(H20/H16,"") -> 0.0070831912 | S20: =IFERROR(I20/I16,"") -> 0.0050202896 | T20: =IFERROR(J20/J16,"") -> 0.0043504325
A21: Diğer KV Yükümlülükler (diğer borçlar, karşılıklar, vb.) | B21: 116612.05 | C21: 139222.61 | D21: 106364.23 | E21: 343970.98 | F21: 202120.18 | G21: 19145.416 | H21: 21563.432 | I21: 29723.446 | J21: 171823.45
A22: KV YÜKÜMLÜLÜKLER TOPLAM (TOTAL CURRENT LIABILITIES) | B22: =SUM(B19:B21) -> 885608.8 | C22: =SUM(C19:C21) -> 1056209 | D22: =SUM(D19:D21) -> 806929.67 | E22: =SUM(E19:E21) -> 563892.08 | F22: =SUM(F19:F21) -> 390564.4 | G22: =SUM(G19:G21) -> 176822.04 | H22: =SUM(H19:H21) -> 107312.56 | I22: =SUM(I19:I21) -> 288047.04 | J22: =SUM(J19:J21) -> 302493.95 | L22: =IFERROR(B22/B16,"") -> 0.043543219 | M22: =IFERROR(C22/C16,"") -> 0.054487242 | N22: =IFERROR(D22/D16,"") -> 0.054487242 | O22: =IFERROR(E22/E16,"") -> 0.042640181 | P22: =IFERROR(F22/F16,"") -> 0.042640181 | Q22: =IFERROR(G22/G16,"") -> 0.020180617 | R22: =IFERROR(H22/H16,"") -> 0.043510531 | S22: =IFERROR(I22/I16,"") -> 0.16296069 | T22: =IFERROR(J22/J16,"") -> 0.18665338
A23: UZUN VADELİ YÜKÜMLÜLÜKLER / NON-CURRENT LIABILITIES
A24: Uzun Vadeli Finansal Borçlar (LT borrowings + lease LT) | B24: 2624731 | C24: 2263656.6 | D24: 1729403.6 | E24: 946201.18 | F24: 655437.57 | G24: 755803.87 | H24: 458341.85 | I24: 398374.89 | J24: 292951.92 | L24: =IFERROR(B24/B16,"") -> 0.12905161 | M24: =IFERROR(C24/C16,"") -> 0.11677651 | N24: =IFERROR(D24/D16,"") -> 0.11677651 | O24: =IFERROR(E24/E16,"") -> 0.071549487 | P24: =IFERROR(F24/F16,"") -> 0.071557921 | Q24: =IFERROR(G24/G16,"") -> 0.086259542 | R24: =IFERROR(H24/H16,"") -> 0.18583749 | S24: =IFERROR(I24/I16,"") -> 0.22537793 | T24: =IFERROR(J24/J16,"") -> 0.18076549
A25: Diğer UV Yükümlülükler (ETVergi, uzun vad. karşılıklar) | B25: 2699075.1 | C25: 2377697.3 | D25: 1816529.1 | E25: 1560473.6 | F25: 1080742 | G25: 888643.71 | H25: 10466.605 | I25: 83477.477 | J25: 97935.405
A26: UV YÜKÜMLÜLÜKLER TOPLAM (TOTAL NON-CURRENT LIABILITIES) | B26: =SUM(B24:B25) -> 5323806.1 | C26: =SUM(C24:C25) -> 4641353.9 | D26: =SUM(D24:D25) -> 3545932.7 | E26: =SUM(E24:E25) -> 2506674.7 | F26: =SUM(F24:F25) -> 1736179.6 | G26: =SUM(G24:G25) -> 1644447.6 | H26: =SUM(H24:H25) -> 468808.46 | I26: =SUM(I24:I25) -> 481852.36 | J26: =SUM(J24:J25) -> 390887.33 | L26: =IFERROR(B26/B16,"") -> 0.26175853 | M26: =IFERROR(C26/C16,"") -> 0.2394361 | N26: =IFERROR(D26/D16,"") -> 0.2394361 | O26: =IFERROR(E26/E16,"") -> 0.18954879 | P26: =IFERROR(F26/F16,"") -> 0.18954879 | Q26: =IFERROR(G26/G16,"") -> 0.18768003 | R26: =IFERROR(H26/H16,"") -> 0.19008124 | S26: =IFERROR(I26/I16,"") -> 0.27260475 | T26: =IFERROR(J26/J16,"") -> 0.24119637
A27: TOPLAM YÜKÜMLÜLÜKLER (TOTAL LIABILITIES) | B27: =B22+B26 -> 6209414.9 | C27: =C22+C26 -> 5697562.9 | D27: =D22+D26 -> 4352862.4 | E27: =E22+E26 -> 3070566.8 | F27: =F22+F26 -> 2126744 | G27: =G22+G26 -> 1821269.6 | H27: =H22+H26 -> 576121.02 | I27: =I22+I26 -> 769899.41 | J27: =J22+J26 -> 693381.28 | L27: =IFERROR(B27/B16,"") -> 0.30530175 | M27: =IFERROR(C27/C16,"") -> 0.29392334 | N27: =IFERROR(D27/D16,"") -> 0.29392334 | O27: =IFERROR(E27/E16,"") -> 0.23218897 | P27: =IFERROR(F27/F16,"") -> 0.23218897 | Q27: =IFERROR(G27/G16,"") -> 0.20786065 | R27: =IFERROR(H27/H16,"") -> 0.23359177 | S27: =IFERROR(I27/I16,"") -> 0.43556544 | T27: =IFERROR(J27/J16,"") -> 0.42784975
A28: ÖZKAYNAKLAR / EQUITY
A29: Ödenmiş Sermaye (Paid-in capital) | B29: 540000 | C29: 540000 | D29: 540000 | E29: 540000 | F29: 540000 | G29: 534791.46 | H29: 534791.46 | I29: 534791.46 | J29: 534791.46 | L29: =IFERROR(B29/B16,"") -> 0.02655048 | M29: =IFERROR(C29/C16,"") -> 0.02785728 | N29: =IFERROR(D29/D16,"") -> 0.036463042 | O29: =IFERROR(E29/E16,"") -> 0.040833518 | P29: =IFERROR(F29/F16,"") -> 0.058954932 | Q29: =IFERROR(G29/G16,"") -> 0.061035499 | R29: =IFERROR(H29/H16,"") -> 0.21683445 | S29: =IFERROR(I29/I16,"") -> 0.30255469 | T29: =IFERROR(J29/J16,"") -> 0.32999217
A30: Sermaye Düzeltme Farkları / SAG (Capital adj. differences) | B30: 4891623.8 | C30: 4891623.8 | D30: 3609688.4 | E30: 3609688.4 | F30: 2334168 | G30: 2332832.1 | H30: 0 | I30: 0 | J30: 0 | L30: =IFERROR(B30/B16,"") -> 0.24050918 | M30: =IFERROR(C30/C16,"") -> 0.25234691 | N30: =IFERROR(D30/D16,"") -> 0.24374115 | O30: =IFERROR(E30/E16,"") -> 0.27295607 | P30: =IFERROR(F30/F16,"") -> 0.25483466 | Q30: =IFERROR(G30/G16,"") -> 0.26624504 | R30: =IFERROR(H30/H16,"") -> 0 | S30: =IFERROR(I30/I16,"") -> 0 | T30: =IFERROR(J30/J16,"") -> 0
A31: Diğer Özkaynak (Primler, OCI, Yedekler) | B31: 592655.15 | C31: 532059.72 | D31: 406486.56 | E31: 165439.94 | F31: 114586.75 | G31: 170048.53 | H31: 44966.711 | I31: 29794.936 | J31: 19975.93
A32: Geçmiş Yıl + Net Dönem Karı (Retained + Net profit) | B32: 8104921.7 | C32: 7723273.7 | D32: 5900478.5 | E32: 5838734.8 | F32: 4044040.3 | G32: 3903032.4 | H32: 1310479.2 | I32: 433100.29 | J32: 372469.97
A33: ÖZKAYNAKLAR TOPLAM (TOTAL EQUITY) | B33: =SUM(B29:B32) -> 14129201 | C33: =SUM(C29:C32) -> 13686957 | D33: =SUM(D29:D32) -> 10456654 | E33: =SUM(E29:E32) -> 10153863 | F33: =SUM(F29:F32) -> 7032795.1 | G33: =SUM(G29:G32) -> 6940704.5 | H33: =SUM(H29:H32) -> 1890237.4 | I33: =SUM(I29:I32) -> 997686.69 | J33: =SUM(J29:J32) -> 927237.36 | L33: =IFERROR(B33/B16,"") -> 0.69469825 | M33: =IFERROR(C33/C16,"") -> 0.70607666 | N33: =IFERROR(D33/D16,"") -> 0.70607666 | O33: =IFERROR(E33/E16,"") -> 0.76781103 | P33: =IFERROR(F33/F16,"") -> 0.76781103 | Q33: =IFERROR(G33/G16,"") -> 0.79213935 | R33: =IFERROR(H33/H16,"") -> 0.76640823 | S33: =IFERROR(I33/I16,"") -> 0.56443456 | T33: =IFERROR(J33/J16,"") -> 0.57215025
A34: TOPLAM KAYNAKLAR (TOTAL LIAB. + EQUITY) | B34: =B27+B33 -> 20338616 | C34: =C27+C33 -> 19384520 | D34: =D27+D33 -> 14809516 | E34: =E27+E33 -> 13224430 | F34: =F27+F33 -> 9159539.1 | G34: =G27+G33 -> 8761974.1 | H34: =H27+H33 -> 2466358.4 | I34: =I27+I33 -> 1767586.1 | J34: =J27+J33 -> 1620618.6 | L34: =IFERROR(B34/B16,"") -> 1 | M34: =IFERROR(C34/C16,"") -> 1 | N34: =IFERROR(D34/D16,"") -> 1 | O34: =IFERROR(E34/E16,"") -> 1 | P34: =IFERROR(F34/F16,"") -> 1 | Q34: =IFERROR(G34/G16,"") -> 1 | R34: =IFERROR(H34/H16,"") -> 1 | S34: =IFERROR(I34/I16,"") -> 1 | T34: =IFERROR(J34/J16,"") -> 1
L39: YATAY ANALİZ (Aynı SAG YoY %)
K40: KALEM | L40: 2025/2024(SAG) | M40: 2024/2023(SAG) | N40: 2023/2022(SAG) | O40: 2022/2021(Nom) | P40: 2021/2020(Nom)
K41: Nakit ve Nakit Benzerleri | L41: =IFERROR((B5-C5)/ABS(C5),"-") -> -0.3120816 | M41: =IFERROR((D5-E5)/ABS(E5),"-") -> 12.835146 | N41: =IFERROR((F5-G5)/ABS(G5),"-") -> -0.93922311 | O41: =IFERROR((H5-I5)/ABS(I5),"-") -> 3.1472622 | P41: =IFERROR((I5-J5)/ABS(J5),"-") -> 1.4033249
K42: Finansal Yatırımlar KV | L42: =IFERROR((B6-C6)/ABS(C6),"-") -> - | M42: =IFERROR((D6-E6)/ABS(E6),"-") -> -1 | N42: =IFERROR((F6-G6)/ABS(G6),"-") -> -0.29772185 | O42: =IFERROR((H6-I6)/ABS(I6),"-") -> - | P42: =IFERROR((I6-J6)/ABS(J6),"-") -> -
K43: Ticari Alacaklar | L43: =IFERROR((B7-C7)/ABS(C7),"-") -> -0.012200023 | M43: =IFERROR((D7-E7)/ABS(E7),"-") -> 0.10160652 | N43: =IFERROR((F7-G7)/ABS(G7),"-") -> -0.0022524102 | O43: =IFERROR((H7-I7)/ABS(I7),"-") -> -0.0022983622 | P43: =IFERROR((I7-J7)/ABS(J7),"-") -> 1.422395
K44: Stoklar | L44: =IFERROR((B8-C8)/ABS(C8),"-") -> -0.5249113 | M44: =IFERROR((D8-E8)/ABS(E8),"-") -> 0 | N44: =IFERROR((F8-G8)/ABS(G8),"-") -> -0.0057618301 | O44: =IFERROR((H8-I8)/ABS(I8),"-") -> -0.019552778 | P44: =IFERROR((I8-J8)/ABS(J8),"-") -> -0.49847836
K45: Diğer Dönen Varlıklar | L45: =IFERROR((B9-C9)/ABS(C9),"-") -> -0.36093596 | M45: =IFERROR((D9-E9)/ABS(E9),"-") -> 0.72473517 | N45: =IFERROR((F9-G9)/ABS(G9),"-") -> -0.80797501 | O45: =IFERROR((H9-I9)/ABS(I9),"-") -> -0.39329894 | P45: =IFERROR((I9-J9)/ABS(J9),"-") -> 1.1048313
K46: DÖNEN VARLIKLAR TOPLAM | L46: =IFERROR((B10-C10)/ABS(C10),"-") -> 0.034399833 | M46: =IFERROR((D10-E10)/ABS(E10),"-") -> 2.4320737 | N46: =IFERROR((F10-G10)/ABS(G10),"-") -> -0.78322426 | O46: =IFERROR((H10-I10)/ABS(I10),"-") -> 1.3344322 | P46: =IFERROR((I10-J10)/ABS(J10),"-") -> 1.2688158
K47: Maddi Duran Varlıklar | L47: =IFERROR((B12-C12)/ABS(C12),"-") -> -0.015637817 | M47: =IFERROR((D12-E12)/ABS(E12),"-") -> 0.20001431 | N47: =IFERROR((F12-G12)/ABS(G12),"-") -> 0.24035613 | O47: =IFERROR((H12-I12)/ABS(I12),"-") -> 0.01361745 | P47: =IFERROR((I12-J12)/ABS(J12),"-") -> 0.036511844
K48: Maddi Olmayan Duran Varlıklar | L48: =IFERROR((B13-C13)/ABS(C13),"-") -> 0.21334334 | M48: =IFERROR((D13-E13)/ABS(E13),"-") -> 0.0024839885 | N48: =IFERROR((F13-G13)/ABS(G13),"-") -> -0.024326289 | O48: =IFERROR((H13-I13)/ABS(I13),"-") -> 0.090902079 | P48: =IFERROR((I13-J13)/ABS(J13),"-") -> -0.021090303
K49: Diğer Duran Varlıklar | L49: =IFERROR((B14-C14)/ABS(C14),"-") -> -0.01462235 | M49: =IFERROR((D14-E14)/ABS(E14),"-") -> -0.7073845 | N49: =IFERROR((F14-G14)/ABS(G14),"-") -> 1.6615805 | O49: =IFERROR((H14-I14)/ABS(I14),"-") -> 0.75252622 | P49: =IFERROR((I14-J14)/ABS(J14),"-") -> -0.33923163
K50: DURAN VARLIKLAR TOPLAM | L50: =IFERROR((B15-C15)/ABS(C15),"-") -> 0.051036435 | M50: =IFERROR((D15-E15)/ABS(E15),"-") -> 0.034416493 | N50: =IFERROR((F15-G15)/ABS(G15),"-") -> 0.2173196 | O50: =IFERROR((H15-I15)/ABS(I15),"-") -> 0.1302558 | P50: =IFERROR((I15-J15)/ABS(J15),"-") -> -0.048738584
K51: TOPLAM VARLIKLAR | L51: =IFERROR((B16-C16)/ABS(C16),"-") -> 0.049219449 | M51: =IFERROR((D16-E16)/ABS(E16),"-") -> 0.11986044 | N51: =IFERROR((F16-G16)/ABS(G16),"-") -> 0.045373902 | O51: =IFERROR((H16-I16)/ABS(I16),"-") -> 0.39532574 | P51: =IFERROR((I16-J16)/ABS(J16),"-") -> 0.090686017
K52: KV Finansal Borçlar | L52: =IFERROR((B19-C19)/ABS(C19),"-") -> -0.037829099 | M52: =IFERROR((D19-E19)/ABS(E19),"-") -> 3.7595426 | N52: =IFERROR((F19-G19)/ABS(G19),"-") -> 0.049800567 | O52: =IFERROR((H19-I19)/ABS(I19),"-") -> -0.72627983 | P52: =IFERROR((I19-J19)/ABS(J19),"-") -> 1.017874
K53: Ticari Borçlar | L53: =IFERROR((B20-C20)/ABS(C20),"-") -> -0.66314842 | M53: =IFERROR((D20-E20)/ABS(E20),"-") -> 0.35960647 | N53: =IFERROR((F20-G20)/ABS(G20),"-") -> 0.55710427 | O53: =IFERROR((H20-I20)/ABS(I20),"-") -> 0.96868307 | P53: =IFERROR((I20-J20)/ABS(J20),"-") -> 0.2586242
K54: KV YÜKÜMLÜLÜKLER TOPLAM | L54: =IFERROR((B22-C22)/ABS(C22),"-") -> -0.16152128 | M54: =IFERROR((D22-E22)/ABS(E22),"-") -> 0.43100018 | N54: =IFERROR((F22-G22)/ABS(G22),"-") -> 1.2087993 | O54: =IFERROR((H22-I22)/ABS(I22),"-") -> -0.62744779 | P54: =IFERROR((I22-J22)/ABS(J22),"-") -> -0.047759332
K55: UV Finansal Borçlar | L55: =IFERROR((B24-C24)/ABS(C24),"-") -> 0.15950935 | M55: =IFERROR((D24-E24)/ABS(E24),"-") -> 0.8277335 | N55: =IFERROR((F24-G24)/ABS(G24),"-") -> -0.1327941 | O55: =IFERROR((H24-I24)/ABS(I24),"-") -> 0.15052898 | P55: =IFERROR((I24-J24)/ABS(J24),"-") -> 0.35986439
K56: UV YÜKÜMLÜLÜKLER TOPLAM | L56: =IFERROR((B26-C26)/ABS(C26),"-") -> 0.14703732 | M56: =IFERROR((D26-E26)/ABS(E26),"-") -> 0.41459627 | N56: =IFERROR((F26-G26)/ABS(G26),"-") -> 0.055782857 | O56: =IFERROR((H26-I26)/ABS(I26),"-") -> -0.027070341 | P56: =IFERROR((I26-J26)/ABS(J26),"-") -> 0.23271421
K57: TOPLAM YÜKÜMLÜLÜKLER | L57: =IFERROR((B27-C27)/ABS(C27),"-") -> 0.089837006 | M57: =IFERROR((D27-E27)/ABS(E27),"-") -> 0.41760875 | N57: =IFERROR((F27-G27)/ABS(G27),"-") -> 0.16772604 | O57: =IFERROR((H27-I27)/ABS(I27),"-") -> -0.25169312 | P57: =IFERROR((I27-J27)/ABS(J27),"-") -> 0.11035505
K58: Ödenmiş Sermaye | L58: =IFERROR((B29-C29)/ABS(C29),"-") -> 0 | M58: =IFERROR((D29-E29)/ABS(E29),"-") -> 0 | N58: =IFERROR((F29-G29)/ABS(G29),"-") -> 0.0097393889 | O58: =IFERROR((H29-I29)/ABS(I29),"-") -> 0 | P58: =IFERROR((I29-J29)/ABS(J29),"-") -> 0
K59: Sermaye Düzeltme Farkları | L59: =IFERROR((B30-C30)/ABS(C30),"-") -> 0 | M59: =IFERROR((D30-E30)/ABS(E30),"-") -> 0 | N59: =IFERROR((F30-G30)/ABS(G30),"-") -> 0.00057263186 | O59: =IFERROR((H30-I30)/ABS(I30),"-") -> - | P59: =IFERROR((I30-J30)/ABS(J30),"-") -> -
K60: ÖZKAYNAKLAR TOPLAM | L60: =IFERROR((B33-C33)/ABS(C33),"-") -> 0.032311302 | M60: =IFERROR((D33-E33)/ABS(E33),"-") -> 0.029820215 | N60: =IFERROR((F33-G33)/ABS(G33),"-") -> 0.013268193 | O60: =IFERROR((H33-I33)/ABS(I33),"-") -> 0.89462021 | P60: =IFERROR((I33-J33)/ABS(J33),"-") -> 0.075977657
K61: TOPLAM KAYNAKLAR | L61: =IFERROR((B34-C34)/ABS(C34),"-") -> 0.049219449 | M61: =IFERROR((D34-E34)/ABS(E34),"-") -> 0.11986044 | N61: =IFERROR((F34-G34)/ABS(G34),"-") -> 0.045373902 | O61: =IFERROR((H34-I34)/ABS(I34),"-") -> 0.39532574 | P61: =IFERROR((I34-J34)/ABS(J34),"-") -> 0.090686017

Sheet GWIND_PLS
A1: GALATA WIND ENERJİ A.Ş. — GELİR TABLOSU / INCOME STATEMENT (BİN TL) | L1: DİKEY ANALİZ (% Hasılat)
A2: KALEM (BİN TL) | B2: 31.12.2025 (2025 SAG) | C2: 31.12.2024 (2025 SAG) | D2: 31.12.2024 (2024 SAG) | E2: 31.12.2023 (2024 SAG) | F2: 31.12.2023 (2023 SAG) | G2: 31.12.2022 (2023 SAG) | H2: 31.12.2022 (Nominal) | I2: 31.12.2021 (Nominal) | J2: 31.12.2020 (Nominal) | L2: 31.12.2025 (2025 SAG) | M2: 31.12.2024 (2025 SAG) | N2: 31.12.2024 (2024 SAG) | O2: 31.12.2023 (2024 SAG) | P2: 31.12.2023 (2023 SAG) | Q2: 31.12.2022 (2023 SAG) | R2: 31.12.2022 (Nominal) | S2: 31.12.2021 (Nominal) | T2: 31.12.2020 (Nominal)
A3: GELİR TABLOSU / INCOME STATEMENT (TFRS - TMS29 Satın Alma Gücü Düzeltmeli)
A4: Hasılat (Net Revenue) | B4: 2939691.8 | C4: 3094818.2 | D4: 2364400 | E4: 2684048.7 | F4: 1859032.8 | G4: 2296830 | H4: 1187271.8 | I4: 540226.28 | J4: 335201.95 | L4: =IFERROR(B4/B4,"") -> 1 | M4: =IFERROR(C4/C4,"") -> 1 | N4: =IFERROR(D4/D4,"") -> 1 | O4: =IFERROR(E4/E4,"") -> 1 | P4: =IFERROR(F4/F4,"") -> 1 | Q4: =IFERROR(G4/G4,"") -> 1 | R4: =IFERROR(H4/H4,"") -> 1 | S4: =IFERROR(I4/I4,"") -> 1 | T4: =IFERROR(J4/J4,"") -> 1
A5: Satışların Maliyeti (-) (Cost of sales) | B5: -1593244 | C5: -1470095.7 | D5: -1123133.6 | E5: -1087585.4 | F5: -753286.24 | G5: -652409.85 | H5: -213469.08 | I5: -145366.75 | J5: -88705.657 | L5: =IFERROR(B5/B4,"") -> -0.54197654 | M5: =IFERROR(C5/C4,"") -> -0.47501845 | N5: =IFERROR(D5/D4,"") -> -0.47501845 | O5: =IFERROR(E5/E4,"") -> -0.40520331 | P5: =IFERROR(F5/F4,"") -> -0.40520331 | Q5: =IFERROR(G5/G4,"") -> -0.28404795 | R5: =IFERROR(H5/H4,"") -> -0.17979798 | S5: =IFERROR(I5/I4,"") -> -0.26908493 | T5: =IFERROR(J5/J4,"") -> -0.26463347
A6: BRÜT KAR / GROSS PROFIT | B6: =B4+B5 -> 1346447.8 | C6: =C4+C5 -> 1624722.4 | D6: =D4+D5 -> 1241266.3 | E6: =E4+E5 -> 1596463.3 | F6: =F4+F5 -> 1105746.6 | G6: =G4+G5 -> 1644420.2 | H6: =H4+H5 -> 973802.75 | I6: =I4+I5 -> 394859.53 | J6: =J4+J5 -> 246496.3 | L6: =IFERROR(B6/B4,"") -> 0.45802346 | M6: =IFERROR(C6/C4,"") -> 0.52498155 | N6: =IFERROR(D6/D4,"") -> 0.52498155 | O6: =IFERROR(E6/E4,"") -> 0.59479669 | P6: =IFERROR(F6/F4,"") -> 0.59479669 | Q6: =IFERROR(G6/G4,"") -> 0.71595205 | R6: =IFERROR(H6/H4,"") -> 0.82020202 | S6: =IFERROR(I6/I4,"") -> 0.73091507 | T6: =IFERROR(J6/J4,"") -> 0.73536653
A7: Genel Yönetim Giderleri (-) (G&A expenses) | B7: -277480.55 | C7: -275923.04 | D7: -174481.46 | E7: -91519.475 | F7: -63388.457 | G7: -45956.042 | H7: -24713.014 | I7: -23918.82 | J7: -14143.854 | L7: =IFERROR(B7/B4,"") -> -0.094391037 | M7: =IFERROR(C7/C4,"") -> -0.089156464 | N7: =IFERROR(D7/D4,"") -> -0.073795241 | O7: =IFERROR(E7/E4,"") -> -0.034097546 | P7: =IFERROR(F7/F4,"") -> -0.034097546 | Q7: =IFERROR(G7/G4,"") -> -0.020008464 | R7: =IFERROR(H7/H4,"") -> -0.020814959 | S7: =IFERROR(I7/I4,"") -> -0.044275558 | T7: =IFERROR(J7/J4,"") -> -0.042195023
A8: Pazarlama Giderleri (-) (Marketing expenses) | B8: -21122.877 | C8: -20363.625 | D8: -51877.614 | E8: -37178.785 | F8: -25750.867 | G8: -21280.791 | H8: -10884.445 | I8: -6034.512 | J8: -3100.522 | L8: =IFERROR(B8/B4,"") -> -0.0071854054 | M8: =IFERROR(C8/C4,"") -> -0.00657991 | N8: =IFERROR(D8/D4,"") -> -0.021941133 | O8: =IFERROR(E8/E4,"") -> -0.013851755 | P8: =IFERROR(F8/F4,"") -> -0.013851755 | Q8: =IFERROR(G8/G4,"") -> -0.0092652877 | R8: =IFERROR(H8/H4,"") -> -0.0091676099 | S8: =IFERROR(I8/I4,"") -> -0.011170341 | T8: =IFERROR(J8/J4,"") -> -0.0092497134
A9: Esas Faaliyetlerden Diğer Gelirler (Other op. income) | B9: 531728.09 | C9: 184347.62 | D9: 140839.13 | E9: 661558.64 | F9: 458210.46 | G9: 351011.99 | H9: 181818.13 | I9: 59967.787 | J9: 49577.647 | L9: =IFERROR(B9/B4,"") -> 0.18087886 | M9: =IFERROR(C9/C4,"") -> 0.059566542 | N9: =IFERROR(D9/D4,"") -> 0.059566542 | O9: =IFERROR(E9/E4,"") -> 0.24647788 | P9: =IFERROR(F9/F4,"") -> 0.24647788 | Q9: =IFERROR(G9/G4,"") -> 0.15282454 | R9: =IFERROR(H9/H4,"") -> 0.15313943 | S9: =IFERROR(I9/I4,"") -> 0.11100494 | T9: =IFERROR(J9/J4,"") -> 0.14790381
A10: Esas Faaliyetlerden Diğer Giderler (-) (Other op. exp.) | B10: -40727.291 | C10: -39299.627 | D10: -30024.393 | E10: -3175.88 | F10: -2199.686 | G10: -23441.626 | H10: -13469.879 | I10: -19537.816 | J10: -4522.369 | L10: =IFERROR(B10/B4,"") -> -0.013854273 | M10: =IFERROR(C10/C4,"") -> -0.012698525 | N10: =IFERROR(D10/D4,"") -> -0.012698525 | O10: =IFERROR(E10/E4,"") -> -0.0011832423 | P10: =IFERROR(F10/F4,"") -> -0.0011832422 | Q10: =IFERROR(G10/G4,"") -> -0.010206078 | R10: =IFERROR(H10/H4,"") -> -0.011345236 | S10: =IFERROR(I10/I4,"") -> -0.036165986 | T10: =IFERROR(J10/J4,"") -> -0.013491476
A11: FAALİYET KARI (EBIT) / OPERATING PROFIT | B11: =B6+B7+B8+B9+B10 -> 1538845.2 | C11: =C6+C7+C8+C9+C10 -> 1473483.7 | D11: =D6+D7+D8+D9+D10 -> 1125722 | E11: =E6+E7+E8+E9+E10 -> 2126147.8 | F11: =F6+F7+F8+F9+F10 -> 1472618 | G11: =G6+G7+G8+G9+G10 -> 1904753.7 | H11: =H6+H7+H8+H9+H10 -> 1106553.5 | I11: =I6+I7+I8+I9+I10 -> 405336.17 | J11: =J6+J7+J8+J9+J10 -> 274307.2 | L11: =IFERROR(B11/B4,"") -> 0.52347161 | M11: =IFERROR(C11/C4,"") -> 0.47611319 | N11: =IFERROR(D11/D4,"") -> 0.47611319 | O11: =IFERROR(E11/E4,"") -> 0.79214203 | P11: =IFERROR(F11/F4,"") -> 0.79214203 | Q11: =IFERROR(G11/G4,"") -> 0.82929676 | R11: =IFERROR(H11/H4,"") -> 0.93201364 | S11: =IFERROR(I11/I4,"") -> 0.75030813 | T11: =IFERROR(J11/J4,"") -> 0.81833413
A12: (+) Amortisman ve İtfa (D&A add-back) | B12: 963755.74 | C12: 812716.39 | D12: 620904.52 | E12: 560777.8 | F12: 388407.38 | G12: 380365.88 | H12: 64577.672 | I12: 63161.961 | J12: 34544.685 | L12: =IFERROR(B12/B4,"") -> 0.32784245 | M12: =IFERROR(C12/C4,"") -> 0.26260554 | N12: =IFERROR(D12/D4,"") -> 0.26260554 | O12: =IFERROR(E12/E4,"") -> 0.20892981 | P12: =IFERROR(F12/F4,"") -> 0.20892981 | Q12: =IFERROR(G12/G4,"") -> 0.16560471 | R12: =IFERROR(H12/H4,"") -> 0.054391649 | S12: =IFERROR(I12/I4,"") -> 0.1169176 | T12: =IFERROR(J12/J4,"") -> 0.10305634
A13: FAVÖK / EBITDA | B13: =B11+B12 -> 2502600.9 | C13: =C11+C12 -> 2286200.1 | D13: =D11+D12 -> 1746626.5 | E13: =E11+E12 -> 2686925.6 | F13: =F11+F12 -> 1861025.4 | G13: =G11+G12 -> 2285119.6 | H13: =H11+H12 -> 1171131.2 | I13: =I11+I12 -> 468498.13 | J13: =J11+J12 -> 308851.88 | L13: =IFERROR(B13/B4,"") -> 0.85131405 | M13: =IFERROR(C13/C4,"") -> 0.73871873 | N13: =IFERROR(D13/D4,"") -> 0.73871873 | O13: =IFERROR(E13/E4,"") -> 1.0010718 | P13: =IFERROR(F13/F4,"") -> 1.0010718 | Q13: =IFERROR(G13/G4,"") -> 0.99490148 | R13: =IFERROR(H13/H4,"") -> 0.98640529 | S13: =IFERROR(I13/I4,"") -> 0.86722573 | T13: =IFERROR(J13/J4,"") -> 0.92139046
A14: Finansman Giderleri (-) (Finance expenses, net) | B14: -513747.36 | C14: -259170.25 | D14: -198002.63 | E14: -515294.42 | F14: -356904.56 | G14: -327852.6 | H14: -171205.87 | I14: -208984.41 | J14: -75592.598 | L14: =IFERROR(B14/B4,"") -> -0.17476232 | M14: =IFERROR(C14/C4,"") -> -0.083743289 | N14: =IFERROR(D14/D4,"") -> -0.083743289 | O14: =IFERROR(E14/E4,"") -> -0.191984 | P14: =IFERROR(F14/F4,"") -> -0.191984 | Q14: =IFERROR(G14/G4,"") -> -0.14274134 | R14: =IFERROR(H14/H4,"") -> -0.14420107 | S14: =IFERROR(I14/I4,"") -> -0.38684607 | T14: =IFERROR(J14/J4,"") -> -0.2255136
A15: Net Parasal Pozisyon Kazancı/(Kaybı) (TMS29 Monetary gain/loss) | B15: 335341.09 | C15: 360389.54 | D15: 275332.82 | E15: -159758.03 | F15: -110652.02 | G15: 27868.825 | H15: 0 | I15: 0 | J15: 0 | L15: =IFERROR(B15/B4,"") -> 0.11407355 | M15: =IFERROR(C15/C4,"") -> 0.11644934 | N15: =IFERROR(D15/D4,"") -> 0.11644934 | O15: =IFERROR(E15/E4,"") -> -0.059521287 | P15: =IFERROR(F15/F4,"") -> -0.059521287 | Q15: =IFERROR(G15/G4,"") -> 0.012133604 | R15: =IFERROR(H15/H4,"") -> 0 | S15: =IFERROR(I15/I4,"") -> 0 | T15: =IFERROR(J15/J4,"") -> 0
A16: VERGİ ÖNCESİ KAR / PROFIT BEFORE TAX (PBT) | B16: =B11+B14+B15 -> 1360438.9 | C16: =C11+C14+C15 -> 1574703 | D16: =D11+D14+D15 -> 1203052.2 | E16: =E11+E14+E15 -> 1451095.4 | F16: =F11+F14+F15 -> 1005061.4 | G16: =G11+G14+G15 -> 1604769.9 | H16: =H11+H14+H15 -> 935347.67 | I16: =I11+I14+I15 -> 196351.76 | J16: =J11+J14+J15 -> 198714.6 | L16: =IFERROR(B16/B4,"") -> 0.46278284 | M16: =IFERROR(C16/C4,"") -> 0.50881924 | N16: =IFERROR(D16/D4,"") -> 0.50881924 | O16: =IFERROR(E16/E4,"") -> 0.54063674 | P16: =IFERROR(F16/F4,"") -> 0.54063674 | Q16: =IFERROR(G16/G4,"") -> 0.69868902 | R16: =IFERROR(H16/H4,"") -> 0.78781257 | S16: =IFERROR(I16/I4,"") -> 0.36346206 | T16: =IFERROR(J16/J4,"") -> 0.59282053
A17: Dönem Vergi Gideri (-) (Current tax expense) | B17: -192352.45 | C17: -145137.72 | D17: -110883.29 | E17: -260872.27 | F17: -180686.03 | G17: -233889.62 | H17: -114981.52 | I17: -47052.651 | J17: -27295.599 | L17: =IFERROR(B17/B4,"") -> -0.065432862 | M17: =IFERROR(C17/C4,"") -> -0.046897009 | N17: =IFERROR(D17/D4,"") -> -0.046897009 | O17: =IFERROR(E17/E4,"") -> -0.097193568 | P17: =IFERROR(F17/F4,"") -> -0.097193568 | Q17: =IFERROR(G17/G4,"") -> -0.10183149 | R17: =IFERROR(H17/H4,"") -> -0.096845156 | S17: =IFERROR(I17/I4,"") -> -0.087098042 | T17: =IFERROR(J17/J4,"") -> -0.08143031
A18: Ertelenmiş Vergi Gel./(Gid.) (Deferred tax income/(expense)) | B18: -322658.89 | C18: -337386.54 | D18: -257758.84 | E18: -289952.52 | F18: -200827.67 | G18: 93746.871 | H18: 223589.79 | I18: 21613.755 | J18: -15062.46 | L18: =IFERROR(B18/B4,"") -> -0.10975943 | M18: =IFERROR(C18/C4,"") -> -0.1090166 | N18: =IFERROR(D18/D4,"") -> -0.1090166 | O18: =IFERROR(E18/E4,"") -> -0.10802804 | P18: =IFERROR(F18/F4,"") -> -0.10802804 | Q18: =IFERROR(G18/G4,"") -> 0.040815763 | R18: =IFERROR(H18/H4,"") -> 0.18832232 | S18: =IFERROR(I18/I4,"") -> 0.040008707 | T18: =IFERROR(J18/J4,"") -> -0.044935478
A19: Toplam Vergi (-) / Total Tax Expense | B19: =B17+B18 -> -515011.34 | C19: =C17+C18 -> -482524.26 | D19: =D17+D18 -> -368642.12 | E19: =E17+E18 -> -550824.79 | F19: =F17+F18 -> -381513.7 | G19: =G17+G18 -> -140142.75 | H19: =H17+H18 -> 108608.26 | I19: =I17+I18 -> -25438.896 | J19: =J17+J18 -> -42358.059 | L19: =IFERROR(B19/B4,"") -> -0.17519229 | M19: =IFERROR(C19/C4,"") -> -0.15591361 | N19: =IFERROR(D19/D4,"") -> -0.15591361 | O19: =IFERROR(E19/E4,"") -> -0.20522161 | P19: =IFERROR(F19/F4,"") -> -0.20522161 | Q19: =IFERROR(G19/G4,"") -> -0.061015723 | R19: =IFERROR(H19/H4,"") -> 0.091477166 | S19: =IFERROR(I19/I4,"") -> -0.047089335 | T19: =IFERROR(J19/J4,"") -> -0.12636579
A20: NET DÖNEM KARI / NET PROFIT | B20: =B16+B19 -> 845427.57 | C20: =C16+C19 -> 1092178.8 | D20: =D16+D19 -> 834410.07 | E20: =E16+E19 -> 900270.56 | F20: =F16+F19 -> 623547.74 | G20: =G16+G19 -> 1464627.2 | H20: =H16+H19 -> 1043955.9 | I20: =I16+I19 -> 170912.86 | J20: =J16+J19 -> 156356.54 | L20: =IFERROR(B20/B4,"") -> 0.28759055 | M20: =IFERROR(C20/C4,"") -> 0.35290564 | N20: =IFERROR(D20/D4,"") -> 0.35290564 | O20: =IFERROR(E20/E4,"") -> 0.33541513 | P20: =IFERROR(F20/F4,"") -> 0.33541513 | Q20: =IFERROR(G20/G4,"") -> 0.6376733 | R20: =IFERROR(H20/H4,"") -> 0.87928974 | S20: =IFERROR(I20/I4,"") -> 0.31637272 | T20: =IFERROR(J20/J4,"") -> 0.46645475
A21: Hisse Başına Kazanç / EPS (TL) | B21: =IFERROR(B20/GWIND_BS!B29,0) -> 1.5656066 | C21: =IFERROR(C20/GWIND_BS!C29,0) -> 2.0225533 | D21: =IFERROR(D20/GWIND_BS!D29,0) -> 1.5452038 | E21: =IFERROR(E20/GWIND_BS!E29,0) -> 1.6671677 | F21: =IFERROR(F20/GWIND_BS!F29,0) -> 1.154718 | G21: =IFERROR(G20/GWIND_BS!G29,0) -> 2.7386884 | H21: =IFERROR(H20/GWIND_BS!H29,0) -> 1.9520804 | I21: =IFERROR(I20/GWIND_BS!I29,0) -> 0.31958786 | J21: =IFERROR(J20/GWIND_BS!J29,0) -> 0.29236918
L24: YATAY ANALİZ (Aynı SAG YoY %)
K25: KALEM | L25: 2025/2024(SAG) | M25: 2024/2023(SAG) | N25: 2023/2022(SAG) | O25: 2022/2021(Nom) | P25: 2021/2020(Nom)
K26: Hasılat (Net Revenue) | L26: =IFERROR((B4-C4)/ABS(C4),"-") -> -0.050124557 | M26: =IFERROR((D4-E4)/ABS(E4),"-") -> -0.11909201 | N26: =IFERROR((F4-G4)/ABS(G4),"-") -> -0.19060933 | O26: =IFERROR((H4-I4)/ABS(I4),"-") -> 1.1977306 | P26: =IFERROR((I4-J4)/ABS(J4),"-") -> 0.61164418
K27: Satışların Maliyeti | L27: =IFERROR((B5-C5)/ABS(C5),"-") -> -0.083768847 | M27: =IFERROR((D5-E5)/ABS(E5),"-") -> -0.032685424 | N27: =IFERROR((F5-G5)/ABS(G5),"-") -> -0.1546212 | O27: =IFERROR((H5-I5)/ABS(I5),"-") -> -0.46848629 | P27: =IFERROR((I5-J5)/ABS(J5),"-") -> -0.63875399
K28: BRÜT KAR | L28: =IFERROR((B6-C6)/ABS(C6),"-") -> -0.17127517 | M28: =IFERROR((D6-E6)/ABS(E6),"-") -> -0.2224899 | N28: =IFERROR((F6-G6)/ABS(G6),"-") -> -0.32757663 | O28: =IFERROR((H6-I6)/ABS(I6),"-") -> 1.4662005 | P28: =IFERROR((I6-J6)/ABS(J6),"-") -> 0.60188828
K29: Genel Yönetim Giderleri | L29: =IFERROR((B7-C7)/ABS(C7),"-") -> -0.0056447297 | M29: =IFERROR((D7-E7)/ABS(E7),"-") -> -0.90649548 | N29: =IFERROR((F7-G7)/ABS(G7),"-") -> -0.37932803 | O29: =IFERROR((H7-I7)/ABS(I7),"-") -> -0.033203728 | P29: =IFERROR((I7-J7)/ABS(J7),"-") -> -0.6911105
K30: Pazarlama Giderleri | L30: =IFERROR((B8-C8)/ABS(C8),"-") -> -0.037284717 | M30: =IFERROR((D8-E8)/ABS(E8),"-") -> -0.39535528 | N30: =IFERROR((F8-G8)/ABS(G8),"-") -> -0.21005215 | O30: =IFERROR((H8-I8)/ABS(I8),"-") -> -0.80369929 | P30: =IFERROR((I8-J8)/ABS(J8),"-") -> -0.94628904
K31: Esas Faaliyetlerden Diğer Gelirler | L31: =IFERROR((B9-C9)/ABS(C9),"-") -> 1.8843774 | M31: =IFERROR((D9-E9)/ABS(E9),"-") -> -0.78711013 | N31: =IFERROR((F9-G9)/ABS(G9),"-") -> 0.30539833 | O31: =IFERROR((H9-I9)/ABS(I9),"-") -> 2.03193 | P31: =IFERROR((I9-J9)/ABS(J9),"-") -> 0.20957308
K32: Esas Faaliyetlerden Diğer Giderler | L32: =IFERROR((B10-C10)/ABS(C10),"-") -> -0.036327673 | M32: =IFERROR((D10-E10)/ABS(E10),"-") -> -8.4538814 | N32: =IFERROR((F10-G10)/ABS(G10),"-") -> 0.90616325 | O32: =IFERROR((H10-I10)/ABS(I10),"-") -> 0.31057397 | P32: =IFERROR((I10-J10)/ABS(J10),"-") -> -3.3202613
K33: FAALİYET KARI (EBIT) | L33: =IFERROR((B11-C11)/ABS(C11),"-") -> 0.044358434 | M33: =IFERROR((D11-E11)/ABS(E11),"-") -> -0.47053445 | N33: =IFERROR((F11-G11)/ABS(G11),"-") -> -0.22687221 | O33: =IFERROR((H11-I11)/ABS(I11),"-") -> 1.729965 | P33: =IFERROR((I11-J11)/ABS(J11),"-") -> 0.47767236
K34: (+) Amortisman ve İtfa | L34: =IFERROR((B12-C12)/ABS(C12),"-") -> 0.18584509 | M34: =IFERROR((D12-E12)/ABS(E12),"-") -> 0.10722022 | N34: =IFERROR((F12-G12)/ABS(G12),"-") -> 0.021141486 | O34: =IFERROR((H12-I12)/ABS(I12),"-") -> 0.022413981 | P34: =IFERROR((I12-J12)/ABS(J12),"-") -> 0.82841329
K35: FAVÖK / EBITDA | L35: =IFERROR((B13-C13)/ABS(C13),"-") -> 0.094655223 | M35: =IFERROR((D13-E13)/ABS(E13),"-") -> -0.34995352 | N35: =IFERROR((F13-G13)/ABS(G13),"-") -> -0.1855895 | O35: =IFERROR((H13-I13)/ABS(I13),"-") -> 1.4997564 | P35: =IFERROR((I13-J13)/ABS(J13),"-") -> 0.51690228
K36: Finansman Giderleri (Net) | L36: =IFERROR((B14-C14)/ABS(C14),"-") -> -0.98227751 | M36: =IFERROR((D14-E14)/ABS(E14),"-") -> 0.61574855 | N36: =IFERROR((F14-G14)/ABS(G14),"-") -> -0.088612864 | O36: =IFERROR((H14-I14)/ABS(I14),"-") -> 0.18077206 | P36: =IFERROR((I14-J14)/ABS(J14),"-") -> -1.7646148
K37: Net Parasal Poz. Kazancı (TMS29) | L37: =IFERROR((B15-C15)/ABS(C15),"-") -> -0.06950381 | M37: =IFERROR((D15-E15)/ABS(E15),"-") -> 2.7234364 | N37: =IFERROR((F15-G15)/ABS(G15),"-") -> -4.9704589 | O37: =IFERROR((H15-I15)/ABS(I15),"-") -> - | P37: =IFERROR((I15-J15)/ABS(J15),"-") -> -
... K42: NET DÖNEM KARI | L42: =IFERROR((B20-C20)/ABS(C20),"-") -> -0.22592566 | M42: =IFERROR((D20-E20)/ABS(E20),"-") -> -0.073156328 | N42: =IFERROR((F20-G20)/ABS(G20),"-") -> -0.57426181 | O42: =IFERROR((H20-I20)/ABS(I20),"-") -> 5.1081181 | P42: =IFERROR((I20-J20)/ABS(J20),"-") -> 0.093096949

Sheet GWIND_CFS
A1: GALATA WIND ENERJİ A.Ş. — NAKİT AKIŞ TABLOSU / CASH FLOW (BİN TL) | L1: DİKEY ANALİZ (% İşletme Nakit Akışı)
A2: KALEM (BİN TL) | B2: 31.12.2025 (2025 SAG) | C2: 31.12.2024 (2025 SAG) | D2: 31.12.2024 (2024 SAG) | E2: 31.12.2023 (2024 SAG) | F2: 31.12.2023 (2023 SAG) | G2: 31.12.2022 (2023 SAG) | H2: 31.12.2022 (Nominal) | I2: 31.12.2021 (Nominal) | J2: 31.12.2020 (Nominal) | L2: 31.12.2025 (2025 SAG) | M2: 31.12.2024 (2025 SAG) | N2: 31.12.2024 (2024 SAG) | O2: 31.12.2023 (2024 SAG) | P2: 31.12.2023 (2023 SAG) | Q2: 31.12.2022 (2023 SAG) | R2: 31.12.2022 (Nominal) | S2: 31.12.2021 (Nominal) | T2: 31.12.2020 (Nominal)
A3: NAKİT AKIŞ TABLOSU / CASH FLOW STATEMENT (TFRS)
A4: Dönem Karı / Net profit | B4: 845427.56 | C4: 1092178.8 | D4: 834410.07 | E4: 900270.56 | F4: 623547.73 | G4: 1464627.2 | H4: 1043955.9 | I4: 170912.86 | J4: 156356.54
A5: (+) Amortisman ve İtfa / Depreciation & amortization | B5: 963755.74 | C5: 812716.39 | D5: 620904.52 | E5: 560777.8 | F5: 388407.38 | G5: 380365.88 | H5: 64577.672 | I5: 63161.961 | J5: 34544.685
A6: Karşılıklar ve Düzeltmeler / Provisions & adjustments | B6: 20107.924 | C6: 12896.045 | D6: 9852.408 | E6: 33146.902 | F6: 22958.294 | G6: 13004.747 | H6: 1405.209 | I6: 11677.165 | J6: -110.232
A7: Diğer Düzeltmeler (Faiz, Vergi, GUD, Kur) / Other adj. | B7: 607627.29 | C7: 627006 | D7: 534652.18 | E7: 382028.84 | F7: 262453.58 | G7: 174805.81 | H7: -103795.68 | I7: 101547.09 | J7: 92925.322
A8: Parasal Poz. Düzeltmesi (TMS29) / Monetary adj. | B8: -746356.79 | C8: -313201.42 | D8: -239281.73 | E8: 474745.82 | F8: 323838.87 | G8: -1798306.2 | H8: 0 | I8: 0 | J8: 0
A9: İşletme Sermayesi Değişimleri / Working capital changes | B9: -76683.407 | C9: -250756.5 | D9: -191574.64 | E9: 461741.94 | F9: 319812.9 | G9: 634189.37 | H9: 177579.13 | I9: -10650.368 | J9: 14922.737
A10: Diğer / Other operating adjustments | B10: 33838.034 | C10: -26401.949 | D10: -75841.663 | E10: 55055.779 | F10: 38133.058 | G10: -180477.88 | H10: -110935.93 | I10: -17156.744 | J10: -26462.685
A11: İŞLETME FAALİYETLERİNDEN NAKİT AKIŞI (OCF) | B11: =SUM(B4:B10) -> 1647716.4 | C11: =SUM(C4:C10) -> 1954437.3 | D11: =SUM(D4:D10) -> 1493121.2 | E11: =SUM(E4:E10) -> 2867767.6 | F11: =SUM(F4:F10) -> 1979151.8 | G11: =SUM(G4:G10) -> 688208.92 | H11: =SUM(H4:H10) -> 1072786.3 | I11: =SUM(I4:I10) -> 319491.96 | J11: =SUM(J4:J10) -> 272176.37 | L11: =IFERROR(B11/B11,"") -> 1 | M11: =IFERROR(C11/C11,"") -> 1 | N11: =IFERROR(D11/D11,"") -> 1 | O11: =IFERROR(E11/E11,"") -> 1 | P11: =IFERROR(F11/F11,"") -> 1 | Q11: =IFERROR(G11/G11,"") -> 1 | R11: =IFERROR(H11/H11,"") -> 1 | S11: =IFERROR(I11/I11,"") -> 1 | T11: =IFERROR(J11/J11,"") -> 1
A12: YATIRIM FAALİYETLERİNDEN NAKİT AKIŞLARI / INVESTING
A13: (-) CAPEX — Maddi+Maddi Olmayan Duran Varlık Alımları | B13: -1613690.2 | C13: -2624231.8 | D13: -2004878.2 | E13: -1898584.7 | F13: -1332027.9 | G13: -120188.28 | H13: -140695.98 | I13: -83658.89 | J13: -424660.51 | L13: =IFERROR(B13/B11,"") -> -0.97934949 | M13: =IFERROR(C13/C11,"") -> -1.3427045 | N13: =IFERROR(D13/D11,"") -> -1.3427432 | O13: =IFERROR(E13/E11,"") -> -0.66204271 | P13: =IFERROR(F13/F11,"") -> -0.67302968 | Q13: =IFERROR(G13/G11,"") -> -0.17463924 | R13: =IFERROR(H13/H11,"") -> -0.13115005 | S13: =IFERROR(I13/I11,"") -> -0.26184975 | T13: =IFERROR(J13/J11,"") -> -1.5602402
A14: Diğer Yatırım Faaliyetleri / Other investing activities | B14: -633415.97 | C14: 1375745.1 | D14: 1050861.7 | E14: -1080199.4 | F14: -731145.22 | G14: -369227.89 | H14: -117068.35 | I14: 152.455 | J14: -1050
A15: YATIRIM FAALİYETLERİNDEN NAKİT AKIŞI (ICF) | B15: =B13+B14 -> -2247106.2 | C15: =C13+C14 -> -1248486.7 | D15: =D13+D14 -> -954016.52 | E15: =E13+E14 -> -2978784 | F15: =F13+F14 -> -2063173.1 | G15: =G13+G14 -> -489416.17 | H15: =H13+H14 -> -257764.33 | I15: =I13+I14 -> -83506.435 | J15: =J13+J14 -> -425710.51 | L15: =IFERROR(B15/B11,"") -> -1.36377 | M15: =IFERROR(C15/C11,"") -> -0.63879597 | N15: =IFERROR(D15/D11,"") -> -0.63894113 | O15: =IFERROR(E15/E11,"") -> -1.0387118 | P15: =IFERROR(F15/F11,"") -> -1.0424532 | Q15: =IFERROR(G15/G11,"") -> -0.71114477 | R15: =IFERROR(H15/H11,"") -> -0.24027555 | S15: =IFERROR(I15/I11,"") -> -0.26137257 | T15: =IFERROR(J15/J11,"") -> -1.564098
A16: FİNANSMAN FAALİYETLERİNDEN NAKİT AKIŞLARI / FINANCING
A17: Borçlanmalardan/Ödemelerden Net Nakit / Net borrowings | B17: 473391.15 | C17: 1716838.9 | D17: 1311748.1 | E17: -138604.67 | F17: -96000.726 | G17: -434902.89 | H17: -267579.93 | I17: -58459.47 | J17: 86575.938 | L17: =IFERROR(B17/B11,"") -> 0.28730136 | M17: =IFERROR(C17/C11,"") -> 0.87843131 | N17: =IFERROR(D17/D11,"") -> 0.87852755 | O17: =IFERROR(E17/E11,"") -> -0.048331904 | P17: =IFERROR(F17/F11,"") -> -0.048505994 | Q17: =IFERROR(G17/G11,"") -> -0.63193439 | R17: =IFERROR(H17/H11,"") -> -0.24942519 | S17: =IFERROR(I17/I11,"") -> -0.18297634 | T17: =IFERROR(J17/J11,"") -> 0.31808764
A18: (-) Ödenen Temettüler / Dividends paid | B18: -399509.41 | C18: -695610.96 | D18: -531437.53 | E18: -761888.11 | F18: -527700.93 | G18: -330599.54 | H18: -150000 | I18: -100000 | J18: -10000 | L18: =IFERROR(B18/B11,"") -> -0.24246249 | M18: =IFERROR(C18/C11,"") -> -0.35591367 | N18: =IFERROR(D18/D11,"") -> -0.35592392 | O18: =IFERROR(E18/E11,"") -> -0.26567289 | P18: =IFERROR(F18/F11,"") -> -0.26662984 | Q18: =IFERROR(G18/G11,"") -> -0.48037671 | R18: =IFERROR(H18/H11,"") -> -0.13982281 | S18: =IFERROR(I18/I11,"") -> -0.31299692 | T18: =IFERROR(J18/J11,"") -> -0.036740883
A19: Diğer Finansman (Faiz, Diğer) / Other financing | B19: -169507.79 | C19: -91454.398 | D19: -79869.946 | E19: -28132.368 | F19: -12356.257 | G19: -112400.84 | H19: -47559.886 | I19: -37842.211 | J19: -10090.076
A20: FİNANSMAN FAALİYETLERİNDEN NAKİT AKIŞI (FCF) | B20: =SUM(B17:B19) -> -95626.048 | C20: =SUM(C17:C19) -> 929773.59 | D20: =SUM(D17:D19) -> 700440.59 | E20: =SUM(E17:E19) -> -928625.15 | F20: =SUM(F17:F19) -> -636057.91 | G20: =SUM(G17:G19) -> -877903.27 | H20: =SUM(H17:H19) -> -465139.82 | I20: =SUM(I17:I19) -> -196301.68 | J20: =SUM(J17:J19) -> 66485.862 | L20: =IFERROR(B20/B11,"") -> -0.058035503 | M20: =IFERROR(C20/C11,"") -> 0.47572443 | N20: =IFERROR(D20/D11,"") -> 0.4691117 | O20: =IFERROR(E20/E11,"") -> -0.32381464 | P20: =IFERROR(F20/F11,"") -> -0.32137904 | Q20: =IFERROR(G20/G11,"") -> -1.2756348 | R20: =IFERROR(H20/H11,"") -> -0.43358104 | S20: =IFERROR(I20/I11,"") -> -0.61441822 | T20: =IFERROR(J20/J11,"") -> 0.24427492
A21: Nakit Üzerindeki Enflasyon Etkisi / Inflation effect on cash | B21: -85066.781 | C21: -71183.487 | D21: -54383.239 | E21: -846022.19 | F21: -585974.09 | G21: 1057991.4 | H21: 0 | I21: 0 | J21: 0
A22: Yabancı Para Çevrim Farkları / FX translation differences | B22: 251605.04 | C22: 24996.678 | D22: 19097.131 | E22: 421929.74 | F22: 292238.08 | G22: 270724.79 | H22: 144048.32 | I22: 53124.901 | J22: 20493.323
A23: NAKİT NET ARTIŞ/(AZALIŞ) / Net change in cash | B23: =B11+B15+B20+B21+B22 -> -528477.58 | C23: =C11+C15+C20+C21+C22 -> 1589537.4 | D23: =D11+D15+D20+D21+D22 -> 1204259.1 | E23: =E11+E15+E20+E21+E22 -> -1463734 | F23: =F11+F15+F20+F21+F22 -> -1013815.2 | G23: =G11+G15+G20+G21+G22 -> 649605.66 | H23: =H11+H15+H20+H21+H22 -> 493930.51 | I23: =I11+I15+I20+I21+I22 -> 92808.743 | J23: =J11+J15+J20+J21+J22 -> -66554.955 | L23: =IFERROR(B23/B11,"") -> -0.32073335 | M23: =IFERROR(C23/C11,"") -> 0.81329669 | N23: =IFERROR(D23/D11,"") -> 0.80653811 | O23: =IFERROR(E23/E11,"") -> -0.51040885 | P23: =IFERROR(F23/F11,"") -> -0.51224733 | Q23: =IFERROR(G23/G11,"") -> 0.94390764 | R23: =IFERROR(H23/H11,"") -> 0.46041835 | S23: =IFERROR(I23/I11,"") -> 0.29048851 | T23: =IFERROR(J23/J11,"") -> -0.24452878
A24: Dönem Başı Nakit / Cash at beginning of period | B24: 1714149.1 | C24: 124611.66 | D24: 95201.655 | E24: 1558935.6 | F24: 1079754.1 | G24: 430148.27 | H24: 158918.75 | I24: 66110.01 | J24: 132664.96 | L24: =IFERROR(B24/B11,"") -> 1.0403181 | M24: =IFERROR(C24/C11,"") -> 0.063758332 | N24: =IFERROR(D24/D11,"") -> 0.063760168 | O24: =IFERROR(E24/E11,"") -> 0.54360598 | P24: =IFERROR(F24/F11,"") -> 0.54556404 | Q24: =IFERROR(G24/G11,"") -> 0.6250257 | R24: =IFERROR(H24/H11,"") -> 0.14813644 | S24: =IFERROR(I24/I11,"") -> 0.2069223 | T24: =IFERROR(J24/J11,"") -> 0.48742279
A25: DÖNEM SONU NAKİT / Cash at end of period | B25: =B24+B23 -> 1185671.5 | C25: =C24+C23 -> 1714149.1 | D25: =D24+D23 -> 1299460.8 | E25: =E24+E23 -> 95201.655 | F25: =F24+F23 -> 65938.818 | G25: =G24+G23 -> 1079753.9 | H25: =H24+H23 -> 652849.27 | I25: =I24+I23 -> 158918.75 | J25: =J24+J23 -> 66110.01 | L25: =IFERROR(B25/B11,"") -> 0.71958471 | M25: =IFERROR(C25/C11,"") -> 0.87705502 | N25: =IFERROR(D25/D11,"") -> 0.87029828 | O25: =IFERROR(E25/E11,"") -> 0.03319713 | P25: =IFERROR(F25/F11,"") -> 0.033316705 | Q25: =IFERROR(G25/G11,"") -> 1.5689333 | R25: =IFERROR(H25/H11,"") -> 0.60855479 | S25: =IFERROR(I25/I11,"") -> 0.49741081 | T25: =IFERROR(J25/J11,"") -> 0.24289401
A29: NOT: B/C/D sütunlarındaki küçük farklar PDF'deki Nakit akışı ile Bilanço'daki Nakit kapsamı arasındaki tanım farkından kaynaklanmaktadır (kısa vadeli mevduat ve benzeri kalemler). | L29: YATAY ANALİZ (Aynı SAG YoY %)
K30: KALEM | L30: 2025/2024(SAG) | M30: 2024/2023(SAG) | N30: 2023/2022(SAG) | O30: 2022/2021(Nom) | P30: 2021/2020(Nom)
K31: İŞLETME FAALİYETLERİNDEN NAKİT AKIŞI | L31: =IFERROR((B11-C11)/ABS(C11),"-") -> -0.15693569 | M31: =IFERROR((D11-E11)/ABS(E11),"-") -> -0.47934375 | N31: =IFERROR((F11-G11)/ABS(G11),"-") -> 1.8758009 | O31: =IFERROR((H11-I11)/ABS(I11),"-") -> 2.3577882 | P31: =IFERROR((I11-J11)/ABS(J11),"-") -> 0.17384165
K32: CAPEX (Sabit Sermaye Yatırımları) | L32: =IFERROR((B13-C13)/ABS(C13),"-") -> 0.38508093 | M32: =IFERROR((D13-E13)/ABS(E13),"-") -> -0.055985695 | N32: =IFERROR((F13-G13)/ABS(G13),"-") -> -10.082844 | O32: =IFERROR((H13-I13)/ABS(I13),"-") -> -0.68178158 | P32: =IFERROR((I13-J13)/ABS(J13),"-") -> 0.80299819
K33: YATIRIM FAALİYETLERİNDEN NAKİT AKIŞI | L33: =IFERROR((B15-C15)/ABS(C15),"-") -> -0.79986392 | M33: =IFERROR((D15-E15)/ABS(E15),"-") -> 0.67972954 | N33: =IFERROR((F15-G15)/ABS(G15),"-") -> -3.2155802 | O33: =IFERROR((H15-I15)/ABS(I15),"-") -> -2.0867601 | P33: =IFERROR((I15-J15)/ABS(J15),"-") -> 0.8038422
K34: Borçlanmalar (net) | L34: =IFERROR((B17-C17)/ABS(C17),"-") -> -0.72426584 | M34: =IFERROR((D17-E17)/ABS(E17),"-") -> 10.463953 | N34: =IFERROR((F17-G17)/ABS(G17),"-") -> 0.77925939 | O34: =IFERROR((H17-I17)/ABS(I17),"-") -> -3.5771871 | P34: =IFERROR((I17-J17)/ABS(J17),"-") -> -1.6752392
K35: Ödenen Temettüler | L35: =IFERROR((B18-C18)/ABS(C18),"-") -> 0.42567119 | M35: =IFERROR((D18-E18)/ABS(E18),"-") -> 0.302473 | N35: =IFERROR((F18-G18)/ABS(G18),"-") -> -0.59619377 | O35: =IFERROR((H18-I18)/ABS(I18),"-") -> -0.5 | P35: =IFERROR((I18-J18)/ABS(J18),"-") -> -9
K36: FİNANSMAN FAALİYETLERİNDEN NAKİT AKIŞI | L36: =IFERROR((B20-C20)/ABS(C20),"-") -> -1.1028487 | M36: =IFERROR((D20-E20)/ABS(E20),"-") -> 1.754277 | N36: =IFERROR((F20-G20)/ABS(G20),"-") -> 0.27548064 | O36: =IFERROR((H20-I20)/ABS(I20),"-") -> -1.3695152 | P36: =IFERROR((I20-J20)/ABS(J20),"-") -> -3.9525327
K37: NAKİT NET ARTIŞ/(AZALIŞ) | L37: =IFERROR((B23-C23)/ABS(C23),"-") -> -1.3324726 | M37: =IFERROR((D23-E23)/ABS(E23),"-") -> 1.8227309 | N37: =IFERROR((F23-G23)/ABS(G23),"-") -> -2.5606626 | O37: =IFERROR((H23-I23)/ABS(I23),"-") -> 4.3220257 | P37: =IFERROR((I23-J23)/ABS(J23),"-") -> 2.3944678
K38: Dönem Başı Nakit | L38: =IFERROR((B24-C24)/ABS(C24),"-") -> 12.755928 | M38: =IFERROR((D24-E24)/ABS(E24),"-") -> -0.93893163 | N38: =IFERROR((F24-G24)/ABS(G24),"-") -> 1.5101904 | O38: =IFERROR((H24-I24)/ABS(I24),"-") -> 1.4038531 | P38: =IFERROR((I24-J24)/ABS(J24),"-") -> -0.50167695
K39: DÖNEM SONU NAKİT | L39: =IFERROR((B25-C25)/ABS(C25),"-") -> -0.30830316 | M39: =IFERROR((D25-E25)/ABS(E25),"-") -> 12.649561 | N39: =IFERROR((F25-G25)/ABS(G25),"-") -> -0.93893162 | O39: =IFERROR((H25-I25)/ABS(I25),"-") -> 3.1080694 | P39: =IFERROR((I25-J25)/ABS(J25),"-") -> 1.4038531
A41: NOTLAR / NOTES:
A42: • 9 sütun yapısı: Her SAG dönemi kendi satın alma gücü cinsinden gösterilmektedir (ASTOR/AKSEN/ENJSA ile aynı format).
A43: • TMS29 'Nakit üzerindeki enflasyon etkisi' 2023'ten itibaren; 2022 ve öncesi Nominal TL (TMS29 öncesi dönem).
A44: • BS ve GelirTablosu tüm 9 sütun için denetçi PDF'leriyle tam mutabakatlıdır (Deloitte 2024-2025, PwC 2020-2023).
A45: • Nakit akış tablosu bileşen tutarları PDFlerden alınan tahmini değerler olabilir; BS ve PL tabloları esas referanstır.

Sheet GWIND_Ratios
A1: GALATA WIND ENERJİ A.Ş. — FİNANSAL ORAN ANALİZİ / FINANCIAL RATIO ANALYSIS (2020–2025)
A2: Oran Adı | B2: Formül / Formula | C2: Sektörel Referans | D2: 2025 | E2: 2024 | F2: 2023 | G2: 2022 | H2: 2021 | I2: 2020
A3: LİKİDİTE ORANLARI / LIQUIDITY RATIOS
A4: Cari Oran (Current Ratio) | B4: Dönen Var. / KV Yükümlülükler | C4: 1.50–2.00x | D4: =IFERROR(GWIND_BS!B10/GWIND_BS!B22,"-") -> 2.4727971 | E4: =IFERROR(GWIND_BS!D10/GWIND_BS!D22,"-") -> 2.0044355 | F4: =IFERROR(GWIND_BS!F10/GWIND_BS!F22,"-") -> 0.83574765 | G4: =IFERROR(GWIND_BS!H10/GWIND_BS!H22,"-") -> 8.4641167 | H4: =IFERROR(GWIND_BS!I10/GWIND_BS!I22,"-") -> 1.350789 | I4: =IFERROR(GWIND_BS!J10/GWIND_BS!J22,"-") -> 0.56693727
A5: Asit-Test Oranı (Quick Ratio) | B5: (Dönen Var. - Stoklar) / KV Y. | C5: 0.80–1.50x | D5: =IFERROR((GWIND_BS!B10-GWIND_BS!B8)/GWIND_BS!B22,"-") -> 2.467818 | E5: =IFERROR((GWIND_BS!D10-GWIND_BS!D8)/GWIND_BS!D22,"-") -> 1.995648 | F5: =IFERROR((GWIND_BS!F10-GWIND_BS!F8)/GWIND_BS!F22,"-") -> 0.82317281 | G5: =IFERROR((GWIND_BS!H10-GWIND_BS!H8)/GWIND_BS!H22,"-") -> 8.4564876 | H5: =IFERROR((GWIND_BS!I10-GWIND_BS!I8)/GWIND_BS!I22,"-") -> 1.3478901 | I5: =IFERROR((GWIND_BS!J10-GWIND_BS!J8)/GWIND_BS!J22,"-") -> 0.56143311
A6: Nakit Oranı (Cash Ratio) | B6: (Nakit + Fin.Yatırım KV) / KV Y. | C6: > 0.20x | D6: =IFERROR((GWIND_BS!B5+GWIND_BS!B6)/GWIND_BS!B22,"-") -> 2.0786886 | E6: =IFERROR((GWIND_BS!D5+GWIND_BS!D6)/GWIND_BS!D22,"-") -> 1.6338538 | F6: =IFERROR((GWIND_BS!F5+GWIND_BS!F6)/GWIND_BS!F22,"-") -> 0.39505316 | G6: =IFERROR((GWIND_BS!H5+GWIND_BS!H6)/GWIND_BS!H22,"-") -> 6.8526787 | H6: =IFERROR((GWIND_BS!I5+GWIND_BS!I6)/GWIND_BS!I22,"-") -> 0.55171223 | I6: =IFERROR((GWIND_BS!J5+GWIND_BS!J6)/GWIND_BS!J22,"-") -> 0.21859834
A7: BORÇLULUK / FİNANSAL YAPI ORANLARI / LEVERAGE & SOLVENCY
A8: Kaldıraç Oranı (Debt-to-Assets) | B8: Toplam Yüküm. / Toplam Aktifler | C8: %40–%60 | D8: =IFERROR(GWIND_BS!B27/GWIND_BS!B16,"-") -> 0.30530175 | E8: =IFERROR(GWIND_BS!D27/GWIND_BS!D16,"-") -> 0.29392334 | F8: =IFERROR(GWIND_BS!F27/GWIND_BS!F16,"-") -> 0.23218897 | G8: =IFERROR(GWIND_BS!H27/GWIND_BS!H16,"-") -> 0.23359177 | H8: =IFERROR(GWIND_BS!I27/GWIND_BS!I16,"-") -> 0.43556544 | I8: =IFERROR(GWIND_BS!J27/GWIND_BS!J16,"-") -> 0.42784975
A9: Borç / Özkaynak (D/E) | B9: Toplam Yüküm. / Özkaynak | C9: 0.50–1.50x | D9: =IFERROR(GWIND_BS!B27/GWIND_BS!B33,"-") -> 0.4394739 | E9: =IFERROR(GWIND_BS!D27/GWIND_BS!D33,"-") -> 0.41627681 | F9: =IFERROR(GWIND_BS!F27/GWIND_BS!F33,"-") -> 0.3024038 | G9: =IFERROR(GWIND_BS!H27/GWIND_BS!H33,"-") -> 0.30478766 | H9: =IFERROR(GWIND_BS!I27/GWIND_BS!I33,"-") -> 0.77168455 | I9: =IFERROR(GWIND_BS!J27/GWIND_BS!J33,"-") -> 0.74779264
A10: Fin. Borç / Özkaynak (Net Debt Ratio) | B10: (KV+UV Fin.Borç) / Özkaynak | C10: 0.30–1.00x | D10: =IFERROR((GWIND_BS!B19+GWIND_BS!B24)/GWIND_BS!B33,"-") -> 0.23587279 | E10: =IFERROR((GWIND_BS!D19+GWIND_BS!D24)/GWIND_BS!D33,"-") -> 0.21914689 | F10: =IFERROR((GWIND_BS!F19+GWIND_BS!F24)/GWIND_BS!F33,"-") -> 0.10999133 | G10: =IFERROR((GWIND_BS!H19+GWIND_BS!H24)/GWIND_BS!H33,"-") -> 0.27860062 | H10: =IFERROR((GWIND_BS!I19+GWIND_BS!I24)/GWIND_BS!I33,"-") -> 0.64932679 | I10: =IFERROR((GWIND_BS!J19+GWIND_BS!J24)/GWIND_BS!J33,"-") -> 0.44926148
A11: Net Borç / FAVÖK | B11: (Fin.Borç - Nakit - Fin.Yat.) / FAVÖK | C11: < 2.00x | D11: =IFERROR((GWIND_BS!B19+GWIND_BS!B24-GWIND_BS!B5-GWIND_BS!B6)/GWIND_PLS!B13,"-") -> 0.59609549 | E11: =IFERROR((GWIND_BS!D19+GWIND_BS!D24-GWIND_BS!D5-GWIND_BS!D6)/GWIND_PLS!D13,"-") -> 0.5571529 | F11: =IFERROR((GWIND_BS!F19+GWIND_BS!F24-GWIND_BS!F5-GWIND_BS!F6)/GWIND_PLS!F13,"-") -> 0.33274816 | G11: =IFERROR((GWIND_BS!H19+GWIND_BS!H24-GWIND_BS!H5-GWIND_BS!H6)/GWIND_PLS!H13,"-") -> -0.17825263 | H11: =IFERROR((GWIND_BS!I19+GWIND_BS!I24-GWIND_BS!I5-GWIND_BS!I6)/GWIND_PLS!I13,"-") -> 1.0435594 | I11: =IFERROR((GWIND_BS!J19+GWIND_BS!J24-GWIND_BS!J5-GWIND_BS!J6)/GWIND_PLS!J13,"-") -> 1.1346777
A12: Faiz Karşılama (Interest Coverage) | B12: EBIT / |Finansman Giderleri| | C12: > 4.00x | D12: =IFERROR(GWIND_PLS!B11/ABS(GWIND_PLS!B14),"-") -> 2.9953345 | E12: =IFERROR(GWIND_PLS!D11/ABS(GWIND_PLS!D14),"-") -> 5.6853892 | F12: =IFERROR(GWIND_PLS!F11/ABS(GWIND_PLS!F14),"-") -> 4.1260835 | G12: =IFERROR(GWIND_PLS!H11/ABS(GWIND_PLS!H14),"-") -> 6.4632921 | H12: =IFERROR(GWIND_PLS!I11/ABS(GWIND_PLS!I14),"-") -> 1.9395522 | I12: =IFERROR(GWIND_PLS!J11/ABS(GWIND_PLS!J14),"-") -> 3.6287574
A13: Özkaynak Çarpanı (Equity Multiplier) | B13: Toplam Aktifler / Özkaynak | C13: 1.50–2.50x | D13: =IFERROR(GWIND_BS!B16/GWIND_BS!B33,"-") -> 1.4394739 | E13: =IFERROR(GWIND_BS!D16/GWIND_BS!D33,"-") -> 1.4162768 | F13: =IFERROR(GWIND_BS!F16/GWIND_BS!F33,"-") -> 1.3024038 | G13: =IFERROR(GWIND_BS!H16/GWIND_BS!H33,"-") -> 1.3047877 | H13: =IFERROR(GWIND_BS!I16/GWIND_BS!I33,"-") -> 1.7716846 | I13: =IFERROR(GWIND_BS!J16/GWIND_BS!J33,"-") -> 1.7477926
A14: KARLILIK ORANLARI / PROFITABILITY RATIOS
A15: Brüt Kar Marjı (Gross Margin) | B15: Brüt Kar / Hasılat | C15: %50–%70 (enerji üret.) | D15: =IFERROR(GWIND_PLS!B6/GWIND_PLS!B4,"-") -> 0.45802346 | E15: =IFERROR(GWIND_PLS!D6/GWIND_PLS!D4,"-") -> 0.52498155 | F15: =IFERROR(GWIND_PLS!F6/GWIND_PLS!F4,"-") -> 0.59479669 | G15: =IFERROR(GWIND_PLS!H6/GWIND_PLS!H4,"-") -> 0.82020202 | H15: =IFERROR(GWIND_PLS!I6/GWIND_PLS!I4,"-") -> 0.73091507 | I15: =IFERROR(GWIND_PLS!J6/GWIND_PLS!J4,"-") -> 0.73536653
A16: FAVÖK Marjı (EBITDA Margin) | B16: FAVÖK / Hasılat | C16: %60–%90 (enerji üret.) | D16: =IFERROR(GWIND_PLS!B13/GWIND_PLS!B4,"-") -> 0.85131405 | E16: =IFERROR(GWIND_PLS!D13/GWIND_PLS!D4,"-") -> 0.73871873 | F16: =IFERROR(GWIND_PLS!F13/GWIND_PLS!F4,"-") -> 1.0010718 | G16: =IFERROR(GWIND_PLS!H13/GWIND_PLS!H4,"-") -> 0.98640529 | H16: =IFERROR(GWIND_PLS!I13/GWIND_PLS!I4,"-") -> 0.86722573 | I16: =IFERROR(GWIND_PLS!J13/GWIND_PLS!J4,"-") -> 0.92139046
A17: EBIT Marjı (Operating Margin) | B17: EBIT / Hasılat | C17: %50–%80 (enerji üret.) | D17: =IFERROR(GWIND_PLS!B11/GWIND_PLS!B4,"-") -> 0.52347161 | E17: =IFERROR(GWIND_PLS!D11/GWIND_PLS!D4,"-") -> 0.47611319 | F17: =IFERROR(GWIND_PLS!F11/GWIND_PLS!F4,"-") -> 0.79214203 | G17: =IFERROR(GWIND_PLS!H11/GWIND_PLS!H4,"-") -> 0.93201364 | H17: =IFERROR(GWIND_PLS!I11/GWIND_PLS!I4,"-") -> 0.75030813 | I17: =IFERROR(GWIND_PLS!J11/GWIND_PLS!J4,"-") -> 0.81833413
A18: Net Kar Marjı (Net Margin) | B18: Net Kar / Hasılat | C18: %20–%50 | D18: =IFERROR(GWIND_PLS!B20/GWIND_PLS!B4,"-") -> 0.28759055 | E18: =IFERROR(GWIND_PLS!D20/GWIND_PLS!D4,"-") -> 0.35290564 | F18: =IFERROR(GWIND_PLS!F20/GWIND_PLS!F4,"-") -> 0.33541513 | G18: =IFERROR(GWIND_PLS!H20/GWIND_PLS!H4,"-") -> 0.87928974 | H18: =IFERROR(GWIND_PLS!I20/GWIND_PLS!I4,"-") -> 0.31637272 | I18: =IFERROR(GWIND_PLS!J20/GWIND_PLS!J4,"-") -> 0.46645475
A19: ROA (Aktif Karlılığı) | B19: Net Kar / Toplam Aktifler (YE) | C19: %5–%15 | D19: =IFERROR(GWIND_PLS!B20/GWIND_BS!B16,"-") -> 0.041567606 | E19: =IFERROR(GWIND_PLS!D20/GWIND_BS!D16,"-") -> 0.056342832 | F19: =IFERROR(GWIND_PLS!F20/GWIND_BS!F16,"-") -> 0.068076323 | G19: =IFERROR(GWIND_PLS!H20/GWIND_BS!H16,"-") -> 0.42327828 | H19: =IFERROR(GWIND_PLS!I20/GWIND_BS!I16,"-") -> 0.096692806 | I19: =IFERROR(GWIND_PLS!J20/GWIND_BS!J16,"-") -> 0.096479541
A20: ROE (Özkaynak Karlılığı) | B20: Net Kar / Özkaynak (YE) | C20: %15–%35 | D20: =IFERROR(GWIND_PLS!B20/GWIND_BS!B33,"-") -> 0.059835484 | E20: =IFERROR(GWIND_PLS!D20/GWIND_BS!D33,"-") -> 0.079797047 | F20: =IFERROR(GWIND_PLS!F20/GWIND_BS!F33,"-") -> 0.088662861 | G20: =IFERROR(GWIND_PLS!H20/GWIND_BS!H33,"-") -> 0.55228828 | H20: =IFERROR(GWIND_PLS!I20/GWIND_BS!I33,"-") -> 0.17130915 | I20: =IFERROR(GWIND_PLS!J20/GWIND_BS!J33,"-") -> 0.16862623
A21: Karlılık Kaldıracı (ROE / ROA) | B21: ROE / ROA | C21: — | D21: =IFERROR((GWIND_PLS!B20/GWIND_BS!B33)/(GWIND_PLS!B20/GWIND_BS!B16),"-") -> 1.4394739 | E21: =IFERROR((GWIND_PLS!D20/GWIND_BS!D33)/(GWIND_PLS!D20/GWIND_BS!D16),"-") -> 1.4162768 | F21: =IFERROR((GWIND_PLS!F20/GWIND_BS!F33)/(GWIND_PLS!F20/GWIND_BS!F16),"-") -> 1.3024038 | G21: =IFERROR((GWIND_PLS!H20/GWIND_BS!H33)/(GWIND_PLS!H20/GWIND_BS!H16),"-") -> 1.3047877 | H21: =IFERROR((GWIND_PLS!I20/GWIND_BS!I33)/(GWIND_PLS!I20/GWIND_BS!I16),"-") -> 1.7716846 | I21: =IFERROR((GWIND_PLS!J20/GWIND_BS!J33)/(GWIND_PLS!J20/GWIND_BS!J16),"-") -> 1.7477926
A22: FAALİYET VERİMLİLİĞİ / OPERATING EFFICIENCY
A23: Aktif Devir Hızı (Asset Turnover) | B23: Hasılat / Toplam Aktifler | C23: 0.15–0.40x | D23: =IFERROR(GWIND_PLS!B4/GWIND_BS!B16,"-") -> 0.14453746 | E23: =IFERROR(GWIND_PLS!D4/GWIND_BS!D16,"-") -> 0.1596541 | F23: =IFERROR(GWIND_PLS!F4/GWIND_BS!F16,"-") -> 0.20296139 | G23: =IFERROR(GWIND_PLS!H4/GWIND_BS!H16,"-") -> 0.48138658 | H23: =IFERROR(GWIND_PLS!I4/GWIND_BS!I16,"-") -> 0.3056294 | I23: =IFERROR(GWIND_PLS!J4/GWIND_BS!J16,"-") -> 0.2068358
A24: Tic. Alacak Devir Hızı (T/R Turnover) | B24: Hasılat / Ticari Alacaklar | C24: 5–20x | D24: =IFERROR(GWIND_PLS!B4/GWIND_BS!B7,"-") -> 10.335926 | E24: =IFERROR(GWIND_PLS!D4/GWIND_BS!D7,"-") -> 10.748352 | F24: =IFERROR(GWIND_PLS!F4/GWIND_BS!F7,"-") -> 13.441193 | G24: =IFERROR(GWIND_PLS!H4/GWIND_BS!H7,"-") -> 14.112614 | H24: =IFERROR(GWIND_PLS!I4/GWIND_BS!I7,"-") -> 6.4066897 | I24: =IFERROR(GWIND_PLS!J4/GWIND_BS!J7,"-") -> 9.6296273
A25: Ort. Tahsilat Süresi (DSO, gün) | B25: 365 / Alacak Devir Hızı | C25: 20–80 gün | D25: =IFERROR(365/(GWIND_PLS!B4/GWIND_BS!B7),"-") -> 35.313719 | E25: =IFERROR(365/(GWIND_PLS!D4/GWIND_BS!D7),"-") -> 33.958695 | F25: =IFERROR(365/(GWIND_PLS!F4/GWIND_BS!F7),"-") -> 27.155327 | G25: =IFERROR(365/(GWIND_PLS!H4/GWIND_BS!H7),"-") -> 25.863387 | H25: =IFERROR(365/(GWIND_PLS!I4/GWIND_BS!I7),"-") -> 56.9717 | I25: =IFERROR(365/(GWIND_PLS!J4/GWIND_BS!J7),"-") -> 37.903855
A26: Stok Devir Hızı (Inventory Turnover) | B26: SMM / Stoklar (YE) | C26: 50–300x | D26: =IFERROR(ABS(GWIND_PLS!B5)/GWIND_BS!B8,"-") -> 361.32217 | E26: =IFERROR(ABS(GWIND_PLS!D5)/GWIND_BS!D8,"-") -> 158.3918 | F26: =IFERROR(ABS(GWIND_PLS!F5)/GWIND_BS!F8,"-") -> 153.37855 | G26: =IFERROR(ABS(GWIND_PLS!H5)/GWIND_BS!H8,"-") -> 260.74311 | H26: =IFERROR(ABS(GWIND_PLS!I5)/GWIND_BS!I8,"-") -> 174.08733 | I26: =IFERROR(ABS(GWIND_PLS!J5)/GWIND_BS!J8,"-") -> 53.277407
A27: Ort. Stok Süresi (Days Inventory, gün) | B27: 365 / Stok Devir Hızı | C27: 1–10 gün | D27: =IFERROR(365/(ABS(GWIND_PLS!B5)/GWIND_BS!B8),"-") -> 1.0101788 | E27: =IFERROR(365/(ABS(GWIND_PLS!D5)/GWIND_BS!D8),"-") -> 2.3044122 | F27: =IFERROR(365/(ABS(GWIND_PLS!F5)/GWIND_BS!F8),"-") -> 2.379733 | G27: =IFERROR(365/(ABS(GWIND_PLS!H5)/GWIND_BS!H8),"-") -> 1.3998453 | H27: =IFERROR(365/(ABS(GWIND_PLS!I5)/GWIND_BS!I8),"-") -> 2.0966489 | I27: =IFERROR(365/(ABS(GWIND_PLS!J5)/GWIND_BS!J8),"-") -> 6.850934
A28: Tic. Borç Devir Hızı (Trade Pay. Turnover) | B28: Hasılat / Ticari Borçlar | C28: 10–50x | D28: =IFERROR(GWIND_PLS!B4/GWIND_BS!B20,"-") -> 48.165011 | E28: =IFERROR(GWIND_PLS!D4/GWIND_BS!D20,"-") -> 17.080619 | F28: =IFERROR(GWIND_PLS!F4/GWIND_BS!F20,"-") -> 26.430996 | G28: =IFERROR(GWIND_PLS!H4/GWIND_BS!H20,"-") -> 67.961822 | H28: =IFERROR(GWIND_PLS!I4/GWIND_BS!I20,"-") -> 60.878839 | I28: =IFERROR(GWIND_PLS!J4/GWIND_BS!J20,"-") -> 47.543733
A29: NAKİT AKIŞ ORANLARI / CASH FLOW RATIOS
A30: İşletme Nakdi / Net Kar | B30: OCF / Net Dönem Karı | C30: > 0.80x | D30: =IFERROR(GWIND_CFS!B11/GWIND_PLS!B20,"-") -> 1.948974 | E30: =IFERROR(GWIND_CFS!D11/GWIND_PLS!D20,"-") -> 1.7894333 | F30: =IFERROR(GWIND_CFS!F11/GWIND_PLS!F20,"-") -> 3.1740181 | G30: =IFERROR(GWIND_CFS!H11/GWIND_PLS!H20,"-") -> 1.0276165 | H30: =IFERROR(GWIND_CFS!I11/GWIND_PLS!I20,"-") -> 1.8693266 | I30: =IFERROR(GWIND_CFS!J11/GWIND_PLS!J20,"-") -> 1.7407418
A31: FAVÖK / Faiz Gideri | B31: FAVÖK / |Finansman Gid.| | C31: > 3.00x | D31: =IFERROR(GWIND_PLS!B13/ABS(GWIND_PLS!B14),"-") -> 4.8712677 | E31: =IFERROR(GWIND_PLS!D13/ABS(GWIND_PLS!D14),"-") -> 8.821229 | F31: =IFERROR(GWIND_PLS!F13/ABS(GWIND_PLS!F14),"-") -> 5.2143503 | G31: =IFERROR(GWIND_PLS!H13/ABS(GWIND_PLS!H14),"-") -> 6.8404852 | H31: =IFERROR(GWIND_PLS!I13/ABS(GWIND_PLS!I14),"-") -> 2.241785 | I31: =IFERROR(GWIND_PLS!J13/ABS(GWIND_PLS!J14),"-") -> 4.0857424
A32: Serbest Nakit Akışı / Hasılat | B32: (OCF + CAPEX) / Hasılat | C32: > %5 | D32: =IFERROR((GWIND_CFS!B11+GWIND_CFS!B13)/GWIND_PLS!B4,"-") -> 0.011574742 | E32: =IFERROR((GWIND_CFS!D11+GWIND_CFS!D13)/GWIND_PLS!D4,"-") -> -0.21644269 | F32: =IFERROR((GWIND_CFS!F11+GWIND_CFS!F13)/GWIND_PLS!F4,"-") -> 0.34809709 | G32: =IFERROR((GWIND_CFS!H11+GWIND_CFS!H13)/GWIND_PLS!H4,"-") -> 0.78506904 | H32: =IFERROR((GWIND_CFS!I11+GWIND_CFS!I13)/GWIND_PLS!I4,"-") -> 0.43654498 | I32: =IFERROR((GWIND_CFS!J11+GWIND_CFS!J13)/GWIND_PLS!J4,"-") -> -0.4549023
A33: HİSSE ANALİZİ / EQUITY METRICS
A34: Hisse Adedi (mn) (Shares Outstanding) | B34: Ödenmiş Sermaye / 1000 (mn pay) | C34: — | D34: =IFERROR(GWIND_BS!B29/1000,"-") -> 540 | E34: =IFERROR(GWIND_BS!D29/1000,"-") -> 540 | F34: =IFERROR(GWIND_BS!F29/1000,"-") -> 540 | G34: =IFERROR(GWIND_BS!H29/1000,"-") -> 534.79146 | H34: =IFERROR(GWIND_BS!I29/1000,"-") -> 534.79146 | I34: =IFERROR(GWIND_BS!J29/1000,"-") -> 534.79146
A35: Hisse Başına Kazanç - TL (EPS) | B35: Net Kar / Hisse Adedi (BinTL/BinTL = TL/pay) | C35: — | D35: =IFERROR(GWIND_PLS!B20/GWIND_BS!B29,"-") -> 1.5656066 | E35: =IFERROR(GWIND_PLS!D20/GWIND_BS!D29,"-") -> 1.5452038 | F35: =IFERROR(GWIND_PLS!F20/GWIND_BS!F29,"-") -> 1.154718 | G35: =IFERROR(GWIND_PLS!H20/GWIND_BS!H29,"-") -> 1.9520804 | H35: =IFERROR(GWIND_PLS!I20/GWIND_BS!I29,"-") -> 0.31958786 | I35: =IFERROR(GWIND_PLS!J20/GWIND_BS!J29,"-") -> 0.29236918
A36: Hisse Başına Defter Değeri - TL (BVPS) | B36: Özkaynak / Hisse Adedi | C36: — | D36: =IFERROR(GWIND_BS!B33/GWIND_BS!B29,"-") -> 26.165186 | E36: =IFERROR(GWIND_BS!D33/GWIND_BS!D29,"-") -> 19.364173 | F36: =IFERROR(GWIND_BS!F33/GWIND_BS!F29,"-") -> 13.023695 | G36: =IFERROR(GWIND_BS!H33/GWIND_BS!H29,"-") -> 3.5345317 | H36: =IFERROR(GWIND_BS!I33/GWIND_BS!I29,"-") -> 1.8655621 | I36: =IFERROR(GWIND_BS!J33/GWIND_BS!J29,"-") -> 1.7338298
A37: Hisse Başına Temettü - TL (DPS) | B37: |Ödenen Temettü| / Hisse Adedi | C37: — | D37: =IFERROR(ABS(GWIND_CFS!B18)/GWIND_BS!B29,"-") -> 0.73983224 | E37: =IFERROR(ABS(GWIND_CFS!D18)/GWIND_BS!D29,"-") -> 0.98414358 | F37: =IFERROR(ABS(GWIND_CFS!F18)/GWIND_BS!F29,"-") -> 0.97722394 | G37: =IFERROR(ABS(GWIND_CFS!H18)/GWIND_BS!H29,"-") -> 0.28048316 | H37: =IFERROR(ABS(GWIND_CFS!I18)/GWIND_BS!I29,"-") -> 0.18698878 | I37: =IFERROR(ABS(GWIND_CFS!J18)/GWIND_BS!J29,"-") -> 0.018698878
A38: DEĞERLEME ÇARPANLARI / VALUATION MULTIPLES
A39: Dönem Sonu Hisse Fiyatı - TL (Year-end share price) | B39: BIST son işlem günü kapanışı (Year-end close) | C39: N/A 2020 (halka arz öncesi) | D39: 26.46 | E39: 28.44 | F39: 26.18 | G39: 16.67 | H39: 6.73 | I39: IPO öncesi / Pre-IPO
A40: Piyasa Değeri - Bin TL (Market Cap) | B40: Hisse Fiyatı × Hisse Adedi (BinTL) | C40: — | D40: =IFERROR(D39*GWIND_BS!B29,"-") -> 14288400 | E40: =IFERROR(E39*GWIND_BS!D29,"-") -> 15357600 | F40: =IFERROR(F39*GWIND_BS!F29,"-") -> 14137200 | G40: =IFERROR(G39*GWIND_BS!H29,"-") -> 8914973.6 | H40: =IFERROR(H39*GWIND_BS!I29,"-") -> 3599146.5 | I40: N/A
A41: F/K (P/E - Price/Earnings) | B41: Piyasa Değeri / Net Kar | C41: 8–20x | D41: =IFERROR(D40/GWIND_PLS!B20,"-") -> 16.900797 | E41: =IFERROR(E40/GWIND_PLS!D20,"-") -> 18.405339 | F41: =IFERROR(F40/GWIND_PLS!F20,"-") -> 22.672202 | G41: =IFERROR(G40/GWIND_PLS!H20,"-") -> 8.5396072 | H41: =IFERROR(H40/GWIND_PLS!I20,"-") -> 21.058372 | I41: "N/A"
A42: PD/DD (P/B - Price/Book) | B42: Piyasa Değeri / Özkaynak | C42: 1.0–4.0x | D42: =IFERROR(D40/GWIND_BS!B33,"-") -> 1.0112674 | E42: =IFERROR(E40/GWIND_BS!D33,"-") -> 1.4686917 | F42: =IFERROR(F40/GWIND_BS!F33,"-") -> 2.0101823 | G42: =IFERROR(G40/GWIND_BS!H33,"-") -> 4.716325 | H42: =IFERROR(H40/GWIND_BS!I33,"-") -> 3.6074918 | I42: "N/A"
A43: FD/FAVÖK (EV/EBITDA) | B43: (PD + Net Fin.Borç) / FAVÖK | C43: 5–12x | D43: =IFERROR((D40+GWIND_BS!B19+GWIND_BS!B24-GWIND_BS!B5-GWIND_BS!B6)/GWIND_PLS!B13,"-") -> 6.3055156 | E43: =IFERROR((E40+GWIND_BS!D19+GWIND_BS!D24-GWIND_BS!D5-GWIND_BS!D6)/GWIND_PLS!D13,"-") -> 9.349874 | F43: =IFERROR((F40+GWIND_BS!F19+GWIND_BS!F24-GWIND_BS!F5-GWIND_BS!F6)/GWIND_PLS!F13,"-") -> 7.9292055 | G43: =IFERROR((G40+GWIND_BS!H19+GWIND_BS!H24-GWIND_BS!H5-GWIND_BS!H6)/GWIND_PLS!H13,"-") -> 7.434023 | H43: =IFERROR((H40+GWIND_BS!I19+GWIND_BS!I24-GWIND_BS!I5-GWIND_BS!I6)/GWIND_PLS!I13,"-") -> 8.7258665 | I43: "N/A"
A44: Temettü Verimi (Dividend Yield) | B44: DPS / Hisse Fiyatı | C44: > %1 | D44: =IFERROR(ABS(GWIND_CFS!B18)/GWIND_BS!B29/D39,"-") -> 0.027960402 | E44: =IFERROR(ABS(GWIND_CFS!D18)/GWIND_BS!D29/E39,"-") -> 0.034604204 | F44: =IFERROR(ABS(GWIND_CFS!F18)/GWIND_BS!F29/F39,"-") -> 0.037327117 | G44: =IFERROR(ABS(GWIND_CFS!H18)/GWIND_BS!H29/G39,"-") -> 0.016825625 | H44: =IFERROR(ABS(GWIND_CFS!I18)/GWIND_BS!I29/H39,"-") -> 0.027784365 | I44: "N/A"
A46: NOTLAR / NOTES:
A47: • D(2025)=B, E(2024)=D, F(2023)=F, G(2022)=H, H(2021)=I, I(2020)=J sütunları GWIND_BS/PLS/CFS'den alınmaktadır.
A48: • Her yıl kendi SAG (Satın Alma Gücü) referansında gösterilmektedir: 2023+ TMS29, 2020-2022 Nominal TL.
A49: • Tüm oranlar formül bazlıdır; GWIND_BS, GWIND_PLS veya GWIND_CFS'de değer değişirse otomatik güncellenir.
A50: • Hisse adedi = Ödenmiş Sermaye (GWIND_BS R30, BinTL = bin pay). GWIND nom. pay değeri 1 TL.
A51: • Hisse fiyatları (sarı hücreler) yıl sonu BIST kapanış değerleridir; güncellenebilir.
A52: • 2020 hisse fiyatı boş: GWIND Nisan 2021'de BIST'e kote olmuştur (IPO öncesi N/A).

Sheet ASTOR_BS
A1: ASTOR ENERJİ A.Ş. — KONSOLİDE BİLANÇO / CONSOLIDATED BALANCE SHEET | L1: DİKEY ANALİZ (% TOPLAM AKTİF)
A2: KALEM (BİN TL) | B2: 31.12.2025 (2025 SAG) | C2: 31.12.2024 (2025 SAG) | D2: 31.12.2024 (2024 SAG) | E2: 31.12.2023 (2024 SAG) | F2: 31.12.2023 (2023 SAG) | G2: 31.12.2022 (2023 SAG) | H2: 31.12.2022 (Nominal) | I2: 31.12.2021 (Nominal) | J2: 31.12.2020 (Nominal) | L2: 31.12.2025 (2025 SAG) | M2: 31.12.2024 (2025 SAG) | N2: 31.12.2024 (2024 SAG) | O2: 31.12.2023 (2024 SAG) | P2: 31.12.2023 (2023 SAG) | Q2: 31.12.2022 (2023 SAG) | R2: 31.12.2022 (Nominal) | S2: 31.12.2021 (Nominal) | T2: 31.12.2020 (Nominal)
A3: VARLIKLAR
A4: DÖNEN VARLIKLAR
A5: Nakit ve Nakit Benzerleri (Cash & equivalents) | B5: 1275727 | C5: 6110484 | D5: 4668329 | E5: 2429147 | F5: 1682482 | G5: 235806 | H5: 143101 | I5: 293096 | J5: 224697 | L5: =IFERROR(B5/B22,"") -> 0.025169997 | M5: =IFERROR(C5/C22,"") -> 0.15279982 | N5: =IFERROR(D5/D22,"") -> 0.15279983 | O5: =IFERROR(E5/E22,"") -> 0.089713965 | P5: =IFERROR(F5/F22,"") -> 0.089713957 | Q5: =IFERROR(G5/G22,"") -> 0.019965682 | R5: =IFERROR(H5/H22,"") -> 0.02229696 | S5: =IFERROR(I5/I22,"") -> 0.092025046 | T5: =IFERROR(J5/J22,"") -> 0.13337413
A6: Finansal Yatırımlar (KV) (Short-term financial investments) | B6: 11265802 | C6: 4257948 | D6: 3253016 | E6: 2021164 | F6: 1399904 | G6: 612964 | H6: 371983 | I6: 1129 | J6: 0 | L6: =IFERROR(B6/B22,"") -> 0.22227342 | M6: =IFERROR(C6/C22,"") -> 0.10647498 | N6: =IFERROR(D6/D22,"") -> 0.10647499 | O6: =IFERROR(E6/E22,"") -> 0.074646218 | P6: =IFERROR(F6/F22,"") -> 0.074646223 | Q6: =IFERROR(G6/G22,"") -> 0.05189963 | R6: =IFERROR(H6/H22,"") -> 0.057959694 | S6: =IFERROR(I6/I22,"") -> 0.00035447866 | T6: =IFERROR(J6/J22,"") -> 0
A7: Ticari Alacaklar - İlişkili (Trade rec. - Related parties) | B7: 152253 | C7: 23032 | D7: 17596 | E7: 407164 | F7: 282011 | G7: 46202 | H7: 28038 | I7: 76867 | J7: 58714 | L7: =IFERROR(B7/B22,"") -> 0.0030039401 | M7: =IFERROR(C7/C22,"") -> 0.00057594217 | N7: =IFERROR(D7/D22,"") -> 0.0005759375 | O7: =IFERROR(E7/E22,"") -> 0.0150375 | P7: =IFERROR(F7/F22,"") -> 0.0150375 | Q7: =IFERROR(G7/G22,"") -> 0.0039119209 | R7: =IFERROR(H7/H22,"") -> 0.0043686779 | S7: =IFERROR(I7/I22,"") -> 0.024134377 | T7: =IFERROR(J7/J22,"") -> 0.034851061
A8: Ticari Alacaklar - Üçüncü (Trade rec. - Third parties) | B8: 11605367 | C8: 8543058 | D8: 6526783 | E8: 8152693 | F8: 5646740 | G8: 4202086 | H8: 2550076 | I8: 1308805 | J8: 371132 | L8: =IFERROR(B8/B22,"") -> 0.22897301 | M8: =IFERROR(C8/C22,"") -> 0.21362918 | N8: =IFERROR(D8/D22,"") -> 0.21362918 | O8: =IFERROR(E8/E22,"") -> 0.30109764 | P8: =IFERROR(F8/F22,"") -> 0.30109766 | Q8: =IFERROR(G8/G22,"") -> 0.3557904 | R8: =IFERROR(H8/H22,"") -> 0.39733436 | S8: =IFERROR(I8/I22,"") -> 0.41093308 | T8: =IFERROR(J8/J22,"") -> 0.22029403
A9: Diğer Alacaklar (Other receivables - current) | B9: 451862 | C9: 307716 | D9: 235091 | E9: 112008 | F9: 77580 | G9: 245618 | H9: 149056 | I9: 99807 | J9: 60596 | L9: =IFERROR(B9/B22,"") -> 0.008915203 | M9: =IFERROR(C9/C22,"") -> 0.0076947995 | N9: =IFERROR(D9/D22,"") -> 0.0076948013 | O9: =IFERROR(E9/E22,"") -> 0.0041367121 | P9: =IFERROR(F9/F22,"") -> 0.0041367508 | Q9: =IFERROR(G9/G22,"") -> 0.020796463 | R9: =IFERROR(H9/H22,"") -> 0.023224825 | S9: =IFERROR(I9/I22,"") -> 0.031336981 | T9: =IFERROR(J9/J22,"") -> 0.035968165
A10: Stoklar (Inventories) | B10: 7796698 | C10: 3747056 | D10: 2862701 | E10: 2183348 | F10: 1512236 | G10: 2129120 | H10: 1201417 | I10: 551631 | J10: 344536 | L10: =IFERROR(B10/B22,"") -> 0.15382826 | M10: =IFERROR(C10/C22,"") -> 0.09369953 | N10: =IFERROR(D10/D22,"") -> 0.093699527 | O10: =IFERROR(E10/E22,"") -> 0.080636045 | P10: =IFERROR(F10/F22,"") -> 0.080636034 | Q10: =IFERROR(G10/G22,"") -> 0.18027248 | R10: =IFERROR(H10/H22,"") -> 0.18719609 | S10: =IFERROR(I10/I22,"") -> 0.17319878 | T10: =IFERROR(J10/J22,"") -> 0.20450736
A11: Peşin Ödenmiş Giderler (Prepaid - current) | B11: 3235021 | C11: 4608371 | D11: 3520734 | E11: 3512338 | F11: 2432724 | G11: 1055411 | H11: 584591 | I11: 165965 | J11: 82515 | L11: =IFERROR(B11/B22,"") -> 0.063826719 | M11: =IFERROR(C11/C22,"") -> 0.11523772 | N11: =IFERROR(D11/D22,"") -> 0.11523771 | O11: =IFERROR(E11/E22,"") -> 0.12971869 | P11: =IFERROR(F11/F22,"") -> 0.12971865 | Q11: =IFERROR(G11/G22,"") -> 0.089361594 | R11: =IFERROR(H11/H22,"") -> 0.091086732 | S11: =IFERROR(I11/I22,"") -> 0.052108991 | T11: =IFERROR(J11/J22,"") -> 0.048978698
A12: Diğer Dönen Varlıklar (Other current assets) | B12: 32014 | C12: 42302 | D12: 32318 | E12: 993 | F12: 688 | G12: 1116 | H12: 677 | I12: 1597 | J12: 436 | L12: =IFERROR(B12/B22,"") -> 0.00063163379 | M12: =IFERROR(C12/C22,"") -> 0.0010578111 | N12: =IFERROR(D12/D22,"") -> 0.0010578057 | O12: =IFERROR(E12/E22,"") -> 3.6673766e-05 | P12: =IFERROR(F12/F22,"") -> 3.6685802e-05 | Q12: =IFERROR(G12/G22,"") -> 9.4491661e-05 | R12: =IFERROR(H12/H22,"") -> 0.00010548523 | S12: =IFERROR(I12/I22,"") -> 0.00050141933 | T12: =IFERROR(J12/J22,"") -> 0.00025879794
A13: DÖNEN VARLIKLAR TOPLAM (TOTAL CURRENT ASSETS) | B13: =SUM(B5:B12) -> 35814744 | C13: =SUM(C5:C12) -> 27639967 | D13: =SUM(D5:D12) -> 21116568 | E13: =SUM(E5:E12) -> 18818855 | F13: =SUM(F5:F12) -> 13034365 | G13: =SUM(G5:G12) -> 8528323 | H13: =SUM(H5:H12) -> 5028939 | I13: =SUM(I5:I12) -> 2498897 | J13: =SUM(J5:J12) -> 1142626 | L13: =IFERROR(B13/B22,"") -> 0.70662218 | M13: =IFERROR(C13/C22,"") -> 0.69116979 | N13: =IFERROR(D13/D22,"") -> 0.69116978 | O13: =IFERROR(E13/E22,"") -> 0.69502344 | P13: =IFERROR(F13/F22,"") -> 0.69502346 | Q13: =IFERROR(G13/G22,"") -> 0.72209266 | R13: =IFERROR(H13/H22,"") -> 0.78357282 | S13: =IFERROR(I13/I22,"") -> 0.78459315 | T13: =IFERROR(J13/J22,"") -> 0.67823224
A14: DURAN VARLIKLAR
A15: Diğer Alacaklar (UV) (Other receivables - non-current) | B15: 53787 | C15: 19038 | D15: 14545 | E15: 13453 | F15: 9318 | G15: 14217 | H15: 8628 | I15: 8455 | J15: 1020 | L15: =IFERROR(B15/B22,"") -> 0.0010612134 | M15: =IFERROR(C15/C22,"") -> 0.00047606752 | N15: =IFERROR(D15/D22,"") -> 0.00047607473 | O15: =IFERROR(E15/E22,"") -> 0.00049685012 | P15: =IFERROR(F15/F22,"") -> 0.000496858 | Q15: =IFERROR(G15/G22,"") -> 0.0012037526 | R15: =IFERROR(H15/H22,"") -> 0.0013443524 | S15: =IFERROR(I15/I22,"") -> 0.0026546653 | T15: =IFERROR(J15/J22,"") -> 0.00060544473
A16: Finansal Yatırımlar (UV) (LT financial investments) | B16: 1975807 | C16: 1219952 | D16: 932027 | E16: 374018 | F16: 259053 | G16: 56591 | H16: 34343 | I16: 0 | J16: 16594 | L16: =IFERROR(B16/B22,"") -> 0.038982522 | M16: =IFERROR(C16/C22,"") -> 0.03050633 | N16: =IFERROR(D16/D22,"") -> 0.030506326 | O16: =IFERROR(E16/E22,"") -> 0.013813342 | P16: =IFERROR(F16/F22,"") -> 0.013813324 | Q16: =IFERROR(G16/G22,"") -> 0.004791557 | R16: =IFERROR(H16/H22,"") -> 0.0053510773 | S16: =IFERROR(I16/I22,"") -> 0 | T16: =IFERROR(J16/J22,"") -> 0.0098497547
A17: Maddi Duran Varlıklar (Property, plant & equipment) | B17: 9987391 | C17: 7416747 | D17: 5666296 | E17: 4253379 | F17: 2945987 | G17: 2229485 | H17: 886361 | I17: 521633 | J17: 444798 | L17: =IFERROR(B17/B22,"") -> 0.19705047 | M17: =IFERROR(C17/C22,"") -> 0.18546446 | N17: =IFERROR(D17/D22,"") -> 0.18546445 | O17: =IFERROR(E17/E22,"") -> 0.15708703 | P17: =IFERROR(F17/F22,"") -> 0.15708706 | Q17: =IFERROR(G17/G22,"") -> 0.18877038 | R17: =IFERROR(H17/H22,"") -> 0.13810635 | S17: =IFERROR(I17/I22,"") -> 0.16378013 | T17: =IFERROR(J17/J22,"") -> 0.2640202
A18: Maddi Olmayan Duran Varlıklar (Intangible assets) | B18: 1659111 | C18: 2712272 | D18: 2072140 | E18: 1896818 | F18: 1313779 | G18: 539087 | H18: 194067 | I18: 108519 | J18: 78234 | L18: =IFERROR(B18/B22,"") -> 0.032734134 | M18: =IFERROR(C18/C22,"") -> 0.067823542 | N18: =IFERROR(D18/D22,"") -> 0.067823547 | O18: =IFERROR(E18/E22,"") -> 0.070053835 | P18: =IFERROR(F18/F22,"") -> 0.070053833 | Q18: =IFERROR(G18/G22,"") -> 0.045644468 | R18: =IFERROR(H18/H22,"") -> 0.030238113 | S18: =IFERROR(I18/I22,"") -> 0.034072338 | T18: =IFERROR(J18/J22,"") -> 0.046437611
A19: Peşin Ödenmiş Giderler (UV) (Prepaid - non-current) | B19: 325933 | C19: 137244 | D19: 104853 | E19: 951626 | F19: 659117 | G19: 63095 | H19: 35156 | I19: 1530 | J19: 1440 | L19: =IFERROR(B19/B22,"") -> 0.0064306334 | M19: =IFERROR(C19/C22,"") -> 0.0034319472 | N19: =IFERROR(D19/D22,"") -> 0.0034319604 | O19: =IFERROR(E19/E22,"") -> 0.035145729 | P19: =IFERROR(F19/F22,"") -> 0.035145692 | Q19: =IFERROR(G19/G22,"") -> 0.0053422503 | R19: =IFERROR(H19/H22,"") -> 0.0054777531 | S19: =IFERROR(I19/I22,"") -> 0.00048038295 | T19: =IFERROR(J19/J22,"") -> 0.0008547455
A20: Ertelenmiş Vergi Varlıkları (Deferred tax assets) | B20: 867659 | C20: 844906 | D20: 645497 | E20: 768427 | F20: 532230 | G20: 379768 | H20: 230466 | I20: 45925 | J20: 0 | L20: =IFERROR(B20/B22,"") -> 0.017118846 | M20: =IFERROR(C20/C22,"") -> 0.021127865 | N20: =IFERROR(D20/D22,"") -> 0.021127866 | O20: =IFERROR(E20/E22,"") -> 0.02837977 | P20: =IFERROR(F20/F22,"") -> 0.028379774 | Q20: =IFERROR(G20/G22,"") -> 0.032154937 | R20: =IFERROR(H20/H22,"") -> 0.035909541 | S20: =IFERROR(I20/I22,"") -> 0.014419338 | T20: =IFERROR(J20/J22,"") -> 0
A21: DURAN VARLIKLAR TOPLAM (TOTAL NON-CURRENT ASSETS) | B21: =SUM(B15:B20) -> 14869688 | C21: =SUM(C15:C20) -> 12350159 | D21: =SUM(D15:D20) -> 9435358 | E21: =SUM(E15:E20) -> 8257721 | F21: =SUM(F15:F20) -> 5719484 | G21: =SUM(G15:G20) -> 3282243 | H21: =SUM(H15:H20) -> 1389021 | I21: =SUM(I15:I20) -> 686062 | J21: =SUM(J15:J20) -> 542086 | L21: =IFERROR(B21/B22,"") -> 0.29337782 | M21: =IFERROR(C21/C22,"") -> 0.30883021 | N21: =IFERROR(D21/D22,"") -> 0.30883022 | O21: =IFERROR(E21/E22,"") -> 0.30497656 | P21: =IFERROR(F21/F22,"") -> 0.30497654 | Q21: =IFERROR(G21/G22,"") -> 0.27790734 | R21: =IFERROR(H21/H22,"") -> 0.21642718 | S21: =IFERROR(I21/I22,"") -> 0.21540685 | T21: =IFERROR(J21/J22,"") -> 0.32176776
A22: TOPLAM VARLIKLAR (TOTAL ASSETS) | B22: =B13+B21 -> 50684432 | C22: =C13+C21 -> 39990126 | D22: =D13+D21 -> 30551926 | E22: =E13+E21 -> 27076576 | F22: =F13+F21 -> 18753849 | G22: =G13+G21 -> 11810566 | H22: =H13+H21 -> 6417960 | I22: =I13+I21 -> 3184959 | J22: =J13+J21 -> 1684712 | L22: =IFERROR(B22/B22,"") -> 1 | M22: =IFERROR(C22/C22,"") -> 1 | N22: =IFERROR(D22/D22,"") -> 1 | O22: =IFERROR(E22/E22,"") -> 1 | P22: =IFERROR(F22/F22,"") -> 1 | Q22: =IFERROR(G22/G22,"") -> 1 | R22: =IFERROR(H22/H22,"") -> 1 | S22: =IFERROR(I22/I22,"") -> 1 | T22: =IFERROR(J22/J22,"") -> 1
A23: KAYNAKLAR
A24: KISA VADELİ YÜKÜMLÜLÜKLER
A25: KV Borçlanmalar (ST borrowings) | B25: 4544363 | C25: 2340507 | D25: 1788116 | E25: 1260497 | F25: 873048 | G25: 1668858 | H25: 1012762 | I25: 895927 | J25: 398875 | L25: =IFERROR(B25/B22,"") -> 0.089659937 | M25: =IFERROR(C25/C22,"") -> 0.058527122 | N25: =IFERROR(D25/D22,"") -> 0.058527112 | O25: =IFERROR(E25/E22,"") -> 0.046553043 | P25: =IFERROR(F25/F22,"") -> 0.046553004 | Q25: =IFERROR(G25/G22,"") -> 0.14130212 | R25: =IFERROR(H25/H22,"") -> 0.15780123 | S25: =IFERROR(I25/I22,"") -> 0.28129938 | T25: =IFERROR(J25/J22,"") -> 0.23676154
A26: UV Borçlanmaların KV Kısmı (Current portion of LT borrowings) | B26: 72421 | C26: 157411 | D26: 120260 | E26: 272839 | F26: 188974 | G26: 186580 | H26: 113228 | I26: 125345 | J26: 0 | L26: =IFERROR(B26/B22,"") -> 0.0014288608 | M26: =IFERROR(C26/C22,"") -> 0.0039362467 | N26: =IFERROR(D26/D22,"") -> 0.0039362494 | O26: =IFERROR(E26/E22,"") -> 0.01007657 | P26: =IFERROR(F26/F22,"") -> 0.010076545 | Q26: =IFERROR(G26/G22,"") -> 0.015797719 | R26: =IFERROR(H26/H22,"") -> 0.017642366 | S26: =IFERROR(I26/I22,"") -> 0.039355295 | T26: =IFERROR(J26/J22,"") -> 0
A27: Ticari Borçlar (Trade payables) | B27: 3254658 | C27: 2197236 | D27: 1678659 | E27: 2433085 | F27: 1685210 | G27: 1560368 | H27: 946924 | I27: 466179 | J27: 265003 | L27: =IFERROR(B27/B22,"") -> 0.064214156 | M27: =IFERROR(C27/C22,"") -> 0.054944463 | N27: =IFERROR(D27/D22,"") -> 0.054944458 | O27: =IFERROR(E27/E22,"") -> 0.089859405 | P27: =IFERROR(F27/F22,"") -> 0.08985942 | Q27: =IFERROR(G27/G22,"") -> 0.13211628 | R27: =IFERROR(H27/H22,"") -> 0.14754283 | S27: =IFERROR(I27/I22,"") -> 0.14636892 | T27: =IFERROR(J27/J22,"") -> 0.1572987
A28: Çalışanlara Borçlar (KV Karşılıklar içinde — sıfırlandı) | B28: 348883 | C28: 177062 | D28: 135273 | E28: 74156 | F28: 51362 | G28: 46780 | H28: 28389 | I28: 16194 | J28: 6720
A29: Diğer Borçlar (Other payables - current) | B29: 0 | C29: 0 | D29: 0 | E29: 1 | F29: 1 | G29: 0 | H29: 0 | I29: 2744 | J29: 18006 | L29: =IFERROR(B29/B22,"") -> 0 | M29: =IFERROR(C29/C22,"") -> 0 | N29: =IFERROR(D29/D22,"") -> 0 | O29: =IFERROR(E29/E22,"") -> 3.6932292e-08 | P29: =IFERROR(F29/F22,"") -> 5.3322387e-08 | Q29: =IFERROR(G29/G22,"") -> 0 | R29: =IFERROR(H29/H22,"") -> 0 | S29: =IFERROR(I29/I22,"") -> 0.00086154955 | T29: =IFERROR(J29/J22,"") -> 0.01068788
A30: Ertelenmiş Gelirler (Deferred income) | B30: 8188150 | C30: 7270576 | D30: 5554624 | E30: 4805138 | F30: 3328148 | G30: 1023771 | H30: 617896 | I30: 202160 | J30: 79407 | L30: =IFERROR(B30/B22,"") -> 0.16155158 | M30: =IFERROR(C30/C22,"") -> 0.18180928 | N30: =IFERROR(D30/D22,"") -> 0.18180929 | O30: =IFERROR(E30/E22,"") -> 0.17746476 | P30: =IFERROR(F30/F22,"") -> 0.1774648 | Q30: =IFERROR(G30/G22,"") -> 0.086682637 | R30: =IFERROR(H30/H22,"") -> 0.096276075 | S30: =IFERROR(I30/I22,"") -> 0.063473345 | T30: =IFERROR(J30/J22,"") -> 0.047133872
A31: Dönem Vergi Yükümlülüğü (Current income tax) | B31: 129410 | C31: 0 | D31: 0 | E31: 0 | F31: 0 | G31: 131246 | H31: 79648 | I31: 41060 | J31: 0 | L31: =IFERROR(B31/B22,"") -> 0.0025532495 | M31: =IFERROR(C31/C22,"") -> 0 | N31: =IFERROR(D31/D22,"") -> 0 | O31: =IFERROR(E31/E22,"") -> 0 | P31: =IFERROR(F31/F22,"") -> 0 | Q31: =IFERROR(G31/G22,"") -> 0.011112592 | R31: =IFERROR(H31/H22,"") -> 0.012410174 | S31: =IFERROR(I31/I22,"") -> 0.012891846 | T31: =IFERROR(J31/J22,"") -> 0
A32: KV Karşılıklar (Short-term provisions) | B32: 342988 | C32: 60243 | D32: 46025 | E32: 19610 | F32: 13582 | G32: 13127 | H32: 7966 | I32: 2845 | J32: 1818 | L32: =IFERROR(B32/B22,"") -> 0.0067671272 | M32: =IFERROR(C32/C22,"") -> 0.0015064469 | N32: =IFERROR(D32/D22,"") -> 0.0015064517 | O32: =IFERROR(E32/E22,"") -> 0.00072424224 | P32: =IFERROR(F32/F22,"") -> 0.00072422466 | Q32: =IFERROR(G32/G22,"") -> 0.0011114624 | R32: =IFERROR(H32/H22,"") -> 0.0012412044 | S32: =IFERROR(I32/I22,"") -> 0.00089326111 | T32: =IFERROR(J32/J22,"") -> 0.0010791162
A33: Diğer KV Yükümlülükler (Other current liabilities) | B33: 436151 | C33: 415228 | D33: 317228 | E33: 376693 | F33: 260906 | G33: 198897 | H33: 120703 | I33: 12497 | J33: 2611 | L33: =IFERROR(B33/B22,"") -> 0.0086052262 | M33: =IFERROR(C33/C22,"") -> 0.010383263 | N33: =IFERROR(D33/D22,"") -> 0.010383241 | O33: =IFERROR(E33/E22,"") -> 0.013912136 | P33: =IFERROR(F33/F22,"") -> 0.013912131 | Q33: =IFERROR(G33/G22,"") -> 0.016840598 | R33: =IFERROR(H33/H22,"") -> 0.018807066 | S33: =IFERROR(I33/I22,"") -> 0.0039237554 | T33: =IFERROR(J33/J22,"") -> 0.0015498198
A34: Türev Araçlar (Derivative liabilities) | B34: 0 | C34: 0 | D34: 0 | E34: 0 | F34: 0 | G34: 0 | H34: 0 | I34: 62632 | J34: 0 | L34: =IFERROR(B34/B22,"") -> 0 | M34: =IFERROR(C34/C22,"") -> 0 | N34: =IFERROR(D34/D22,"") -> 0 | O34: =IFERROR(E34/E22,"") -> 0 | P34: =IFERROR(F34/F22,"") -> 0 | Q34: =IFERROR(G34/G22,"") -> 0 | R34: =IFERROR(H34/H22,"") -> 0 | S34: =IFERROR(I34/I22,"") -> 0.019664931 | T34: =IFERROR(J34/J22,"") -> 0
A35: KV YÜKÜMLÜLÜKLER TOPLAM (TOTAL CURRENT LIABILITIES) | B35: =SUM(B25:B34) -> 17317024 | C35: =SUM(C25:C34) -> 12618263 | D35: =SUM(D25:D34) -> 9640185 | E35: =SUM(E25:E34) -> 9242019 | F35: =SUM(F25:F34) -> 6401231 | G35: =SUM(G25:G34) -> 4829627 | H35: =SUM(H25:H34) -> 2927516 | I35: =SUM(I25:I34) -> 1827583 | J35: =SUM(J25:J34) -> 772440 | L35: =IFERROR(B35/B22,"") -> 0.34166357 | M35: =IFERROR(C35/C22,"") -> 0.31553446 | N35: =IFERROR(D35/D22,"") -> 0.31553444 | O35: =IFERROR(E35/E22,"") -> 0.34132894 | P35: =IFERROR(F35/F22,"") -> 0.34132892 | Q35: =IFERROR(G35/G22,"") -> 0.40892426 | R35: =IFERROR(H35/H22,"") -> 0.45614432 | S35: =IFERROR(I35/I22,"") -> 0.57381681 | T35: =IFERROR(J35/J22,"") -> 0.45849973
A36: UZUN VADELİ YÜKÜMLÜLÜKLER
A37: Uzun Vadeli Borçlanmalar (Long-term borrowings) | B37: 0 | C37: 49908 | D37: 38129 | E37: 122942 | F37: 85153 | G37: 262788 | H37: 159475 | I37: 249112 | J37: 331819 | L37: =IFERROR(B37/B22,"") -> 0 | M37: =IFERROR(C37/C22,"") -> 0.0012480081 | N37: =IFERROR(D37/D22,"") -> 0.0012480064 | O37: =IFERROR(E37/E22,"") -> 0.0045405298 | P37: =IFERROR(F37/F22,"") -> 0.0045405612 | Q37: =IFERROR(G37/G22,"") -> 0.022250246 | R37: =IFERROR(H37/H22,"") -> 0.024848238 | S37: =IFERROR(I37/I22,"") -> 0.078215136 | T37: =IFERROR(J37/J22,"") -> 0.19695889
A38: Uzun Vadeli Karşılıklar (Long-term provisions) | B38: 87274 | C38: 64494 | D38: 49273 | E38: 41364 | F38: 28650 | G38: 33123 | H38: 20101 | I38: 9690 | J38: 7441 | L38: =IFERROR(B38/B22,"") -> 0.0017219094 | M38: =IFERROR(C38/C22,"") -> 0.0016127481 | N38: =IFERROR(D38/D22,"") -> 0.0016127625 | O38: =IFERROR(E38/E22,"") -> 0.0015276673 | P38: =IFERROR(F38/F22,"") -> 0.0015276864 | Q38: =IFERROR(G38/G22,"") -> 0.0028045227 | R38: =IFERROR(H38/H22,"") -> 0.0031319921 | S38: =IFERROR(I38/I22,"") -> 0.0030424253 | T38: =IFERROR(J38/J22,"") -> 0.0044167787
A39: Ertelenmiş Vergi Yükümlülüğü (Deferred tax liabilities) | B39: 0 | C39: 0 | D39: 0 | E39: 0 | F39: 0 | G39: 0 | H39: 0 | I39: 0 | J39: 622 | L39: =IFERROR(B39/B22,"") -> 0 | M39: =IFERROR(C39/C22,"") -> 0 | N39: =IFERROR(D39/D22,"") -> 0 | O39: =IFERROR(E39/E22,"") -> 0 | P39: =IFERROR(F39/F22,"") -> 0 | Q39: =IFERROR(G39/G22,"") -> 0 | R39: =IFERROR(H39/H22,"") -> 0 | S39: =IFERROR(I39/I22,"") -> 0 | T39: =IFERROR(J39/J22,"") -> 0.00036920257
A40: UV YÜKÜMLÜLÜKLER TOPLAM (TOTAL NON-CURRENT LIABILITIES) | B40: =SUM(B37:B39) -> 87274 | C40: =SUM(C37:C39) -> 114402 | D40: =SUM(D37:D39) -> 87402 | E40: =SUM(E37:E39) -> 164306 | F40: =SUM(F37:F39) -> 113803 | G40: =SUM(G37:G39) -> 295911 | H40: =SUM(H37:H39) -> 179576 | I40: =SUM(I37:I39) -> 258802 | J40: =SUM(J37:J39) -> 339882 | L40: =IFERROR(B40/B22,"") -> 0.0017219094 | M40: =IFERROR(C40/C22,"") -> 0.0028607562 | N40: =IFERROR(D40/D22,"") -> 0.0028607689 | O40: =IFERROR(E40/E22,"") -> 0.0060681971 | P40: =IFERROR(F40/F22,"") -> 0.0060682476 | Q40: =IFERROR(G40/G22,"") -> 0.025054769 | R40: =IFERROR(H40/H22,"") -> 0.02798023 | S40: =IFERROR(I40/I22,"") -> 0.081257561 | T40: =IFERROR(J40/J22,"") -> 0.20174487
A41: TOPLAM YÜKÜMLÜLÜKLER (TOTAL LIABILITIES) | B41: =B35+B40 -> 17404298 | C41: =C35+C40 -> 12732665 | D41: =D35+D40 -> 9727587 | E41: =E35+E40 -> 9406325 | F41: =F35+F40 -> 6515034 | G41: =G35+G40 -> 5125538 | H41: =H35+H40 -> 3107092 | I41: =I35+I40 -> 2086385 | J41: =J35+J40 -> 1112322 | L41: =IFERROR(B41/B22,"") -> 0.34338548 | M41: =IFERROR(C41/C22,"") -> 0.31839522 | N41: =IFERROR(D41/D22,"") -> 0.31839521 | O41: =IFERROR(E41/E22,"") -> 0.34739714 | P41: =IFERROR(F41/F22,"") -> 0.34739717 | Q41: =IFERROR(G41/G22,"") -> 0.43397903 | R41: =IFERROR(H41/H22,"") -> 0.48412455 | S41: =IFERROR(I41/I22,"") -> 0.65507437 | T41: =IFERROR(J41/J22,"") -> 0.6602446
A42: ÖZKAYNAKLAR
A43: Ödenmiş Sermaye (Paid-in capital) | B43: 998000 | C43: 998000 | D43: 998000 | E43: 998000 | F43: 998000 | G43: 850000 | H43: 850000 | I43: 850000 | J43: 192622 | L43: =IFERROR(B43/B22,"") -> 0.019690464 | M43: =IFERROR(C43/C22,"") -> 0.02495616 | N43: =IFERROR(D43/D22,"") -> 0.032665698 | O43: =IFERROR(E43/E22,"") -> 0.036858427 | P43: =IFERROR(F43/F22,"") -> 0.053215743 | Q43: =IFERROR(G43/G22,"") -> 0.071969455 | R43: =IFERROR(H43/H22,"") -> 0.13244084 | S43: =IFERROR(I43/I22,"") -> 0.26687942 | T43: =IFERROR(J43/J22,"") -> 0.11433527
A44: Sermaye Düzeltme Farkları (Cap. adjustment differences) | B44: 2871730 | C44: 2871730 | D44: 1958422 | E44: 1958422 | F44: 1049685 | G44: 953806 | H44: 0 | I44: 0 | J44: 0 | L44: =IFERROR(B44/B22,"") -> 0.056659015 | M44: =IFERROR(C44/C22,"") -> 0.071810977 | N44: =IFERROR(D44/D22,"") -> 0.064101425 | O44: =IFERROR(E44/E22,"") -> 0.072329012 | P44: =IFERROR(F44/F22,"") -> 0.05597171 | Q44: =IFERROR(G44/G22,"") -> 0.080758704 | R44: =IFERROR(H44/H22,"") -> 0 | S44: =IFERROR(I44/I22,"") -> 0 | T44: =IFERROR(J44/J22,"") -> 0
A45: Hisse Senedi Primleri (Share premiums) | B45: 3072499 | C45: 3072499 | D45: 2347348 | E45: 2347348 | F45: 1625826 | G45: 0 | H45: 0 | I45: 0 | J45: 0 | L45: =IFERROR(B45/B22,"") -> 0.060620172 | M45: =IFERROR(C45/C22,"") -> 0.076831441 | N45: =IFERROR(D45/D22,"") -> 0.076831425 | O45: =IFERROR(E45/E22,"") -> 0.086692941 | P45: =IFERROR(F45/F22,"") -> 0.086692924 | Q45: =IFERROR(G45/G22,"") -> 0 | R45: =IFERROR(H45/H22,"") -> 0 | S45: =IFERROR(I45/I22,"") -> 0 | T45: =IFERROR(J45/J22,"") -> 0
A46: Kar Yedekleri (Retained earnings reserves) | B46: 1095709 | C46: 1095709 | D46: 837107 | E46: 457263 | F46: 365396 | G46: 152450 | H46: 52168 | I46: 27187 | J46: 12776 | L46: =IFERROR(B46/B22,"") -> 0.021618255 | M46: =IFERROR(C46/C22,"") -> 0.027399489 | N46: =IFERROR(D46/D22,"") -> 0.027399484 | O46: =IFERROR(E46/E22,"") -> 0.01688777 | P46: =IFERROR(F46/F22,"") -> 0.019483787 | Q46: =IFERROR(G46/G22,"") -> 0.012907933 | R46: =IFERROR(H46/H22,"") -> 0.0081284396 | S46: =IFERROR(I46/I22,"") -> 0.0085360596 | T46: =IFERROR(J46/J22,"") -> 0.007583492
A47: Yeniden Değerleme ve Diğer Kapsamlı Gelir | B47: 966941 | C47: 987914 | D47: 754753 | E47: 767969 | F47: 531913 | G47: 673011 | H47: 409736 | I47: 24454 | J47: 987 | L47: =IFERROR(B47/B22,"") -> 0.019077673 | M47: =IFERROR(C47/C22,"") -> 0.024703948 | N47: =IFERROR(D47/D22,"") -> 0.024703942 | O47: =IFERROR(E47/E22,"") -> 0.028362855 | P47: =IFERROR(F47/F22,"") -> 0.028362871 | Q47: =IFERROR(G47/G22,"") -> 0.056983806 | R47: =IFERROR(H47/H22,"") -> 0.063842093 | S47: =IFERROR(I47/I22,"") -> 0.0076779638 | T47: =IFERROR(J47/J22,"") -> 0.00058585681
A48: Geçmiş Yıllar Karları (Retained earnings) | B48: 16606345 | C48: 11654428 | D48: 8903828 | E48: 4502239 | F48: 3069667 | G48: 2015270 | H48: 171953 | I48: -320747 | J48: 134583 | L48: =IFERROR(B48/B22,"") -> 0.32764193 | M48: =IFERROR(C48/C22,"") -> 0.29143264 | N48: =IFERROR(D48/D22,"") -> 0.29143263 | O48: =IFERROR(E48/E22,"") -> 0.166278 | P48: =IFERROR(F48/F22,"") -> 0.16368197 | Q48: =IFERROR(G48/G22,"") -> 0.1706328 | R48: =IFERROR(H48/H22,"") -> 0.02679247 | S48: =IFERROR(I48/I22,"") -> -0.10070679 | T48: =IFERROR(J48/J22,"") -> 0.079884871
A49: Net Dönem Karı (Net profit for the period) | B49: 7668909 | C49: 6577183 | D49: 5024880 | E49: 6639008 | F49: 4598327 | G49: 2040490 | H49: 1827009 | I49: 517681 | J49: 231423 | L49: =IFERROR(B49/B22,"") -> 0.15130699 | M49: =IFERROR(C49/C22,"") -> 0.16447017 | N49: =IFERROR(D49/D22,"") -> 0.16447015 | O49: =IFERROR(E49/E22,"") -> 0.24519378 | P49: =IFERROR(F49/F22,"") -> 0.24519377 | Q49: =IFERROR(G49/G22,"") -> 0.17276818 | R49: =IFERROR(H49/H22,"") -> 0.2846713 | S49: =IFERROR(I49/I22,"") -> 0.1625393 | T49: =IFERROR(J49/J22,"") -> 0.13736651
A50: ÖZKAYNAKLAR TOPLAM (TOTAL EQUITY) | B50: =SUM(B43:B49) -> 33280133 | C50: =SUM(C43:C49) -> 27257463 | D50: =SUM(D43:D49) -> 20824338 | E50: =SUM(E43:E49) -> 17670249 | F50: =SUM(F43:F49) -> 12238814 | G50: =SUM(G43:G49) -> 6685027 | H50: =SUM(H43:H49) -> 3310866 | I50: =SUM(I43:I49) -> 1098575 | J50: =SUM(J43:J49) -> 572391 | L50: =IFERROR(B50/B22,"") -> 0.6566145 | M50: =IFERROR(C50/C22,"") -> 0.68160483 | N50: =IFERROR(D50/D22,"") -> 0.68160475 | O50: =IFERROR(E50/E22,"") -> 0.65260279 | P50: =IFERROR(F50/F22,"") -> 0.65260278 | Q50: =IFERROR(G50/G22,"") -> 0.56602088 | R50: =IFERROR(H50/H22,"") -> 0.51587514 | S50: =IFERROR(I50/I22,"") -> 0.34492595 | T50: =IFERROR(J50/J22,"") -> 0.33975599
A51: TOPLAM YÜKÜMLÜLÜKLER VE ÖZKAYNAKLAR (TOTAL LIAB. & EQUITY) | B51: =B41+B50 -> 50684431 | C51: =C41+C50 -> 39990128 | D51: =D41+D50 -> 30551925 | E51: =E41+E50 -> 27076574 | F51: =F41+F50 -> 18753848 | G51: =G41+G50 -> 11810565 | H51: =H41+H50 -> 6417958 | I51: =I41+I50 -> 3184960 | J51: =J41+J50 -> 1684713 | L51: =IFERROR(B51/B22,"") -> 0.99999998 | M51: =IFERROR(C51/C22,"") -> 1.0000001 | N51: =IFERROR(D51/D22,"") -> 0.99999997 | O51: =IFERROR(E51/E22,"") -> 0.99999993 | P51: =IFERROR(F51/F22,"") -> 0.99999995 | Q51: =IFERROR(G51/G22,"") -> 0.99999992 | R51: =IFERROR(H51/H22,"") -> 0.99999969 | S51: =IFERROR(I51/I22,"") -> 1.0000003 | T51: =IFERROR(J51/J22,"") -> 1.0000006
L56: YATAY ANALİZ (YoY % Değişim — Aynı Satın Alma Gücü)
L57: 2025/2024 | M57: 2024/2023 | N57: 2023/2022 | O57: 2022/2021 | P57: 2021/2020
K58: Nakit ve Nakit Benzerleri (Cash & equivalents) | L58: =IFERROR((B5-C5)/ABS(C5),"-") -> -0.79122325 | M58: =IFERROR((D5-E5)/ABS(E5),"-") -> 0.92179765 | N58: =IFERROR((F5-G5)/ABS(G5),"-") -> 6.1350263 | O58: =IFERROR((H5-I5)/ABS(I5),"-") -> -0.51176065 | P58: =IFERROR((I5-J5)/ABS(J5),"-") -> 0.30440549
K59: Finansal Yatırımlar (KV) (Short-term financial investments) | L59: =IFERROR((B6-C6)/ABS(C6),"-") -> 1.6458289 | M59: =IFERROR((D6-E6)/ABS(E6),"-") -> 0.60947652 | N59: =IFERROR((F6-G6)/ABS(G6),"-") -> 1.2838274 | O59: =IFERROR((H6-I6)/ABS(I6),"-") -> 328.48007 | P59: =IFERROR((I6-J6)/ABS(J6),"-") -> -
K60: Ticari Alacaklar - İlişkili (Trade rec. - Related parties) | L60: =IFERROR((B7-C7)/ABS(C7),"-") -> 5.6104984 | M60: =IFERROR((D7-E7)/ABS(E7),"-") -> -0.956784 | N60: =IFERROR((F7-G7)/ABS(G7),"-") -> 5.10387 | O60: =IFERROR((H7-I7)/ABS(I7),"-") -> -0.63524009 | P60: =IFERROR((I7-J7)/ABS(J7),"-") -> 0.30917669
K61: Ticari Alacaklar - Üçüncü (Trade rec. - Third parties) | L61: =IFERROR((B8-C8)/ABS(C8),"-") -> 0.35845584 | M61: =IFERROR((D8-E8)/ABS(E8),"-") -> -0.19943226 | N61: =IFERROR((F8-G8)/ABS(G8),"-") -> 0.34379449 | O61: =IFERROR((H8-I8)/ABS(I8),"-") -> 0.94840026 | P61: =IFERROR((I8-J8)/ABS(J8),"-") -> 2.5265216
K62: Diğer Alacaklar (Other receivables - current) | L62: =IFERROR((B9-C9)/ABS(C9),"-") -> 0.46843843 | M62: =IFERROR((D9-E9)/ABS(E9),"-") -> 1.0988769 | N62: =IFERROR((F9-G9)/ABS(G9),"-") -> -0.68414367 | O62: =IFERROR((H9-I9)/ABS(I9),"-") -> 0.49344234 | P62: =IFERROR((I9-J9)/ABS(J9),"-") -> 0.64708892
K63: Stoklar (Inventories) | L63: =IFERROR((B10-C10)/ABS(C10),"-") -> 1.080753 | M63: =IFERROR((D10-E10)/ABS(E10),"-") -> 0.31115196 | N63: =IFERROR((F10-G10)/ABS(G10),"-") -> -0.2897366 | O63: =IFERROR((H10-I10)/ABS(I10),"-") -> 1.177936 | P63: =IFERROR((I10-J10)/ABS(J10),"-") -> 0.60108378
K64: Peşin Ödenmiş Giderler (Prepaid - current) | L64: =IFERROR((B11-C11)/ABS(C11),"-") -> -0.29801203 | M64: =IFERROR((D11-E11)/ABS(E11),"-") -> 0.0023904305 | N64: =IFERROR((F11-G11)/ABS(G11),"-") -> 1.3050016 | O64: =IFERROR((H11-I11)/ABS(I11),"-") -> 2.5223752 | P64: =IFERROR((I11-J11)/ABS(J11),"-") -> 1.0113313
K65: Diğer Dönen Varlıklar (Other current assets) | L65: =IFERROR((B12-C12)/ABS(C12),"-") -> -0.24320363 | M65: =IFERROR((D12-E12)/ABS(E12),"-") -> 31.545821 | N65: =IFERROR((F12-G12)/ABS(G12),"-") -> -0.38351254 | O65: =IFERROR((H12-I12)/ABS(I12),"-") -> -0.57608015 | P65: =IFERROR((I12-J12)/ABS(J12),"-") -> 2.662844
K66: DÖNEN VARLIKLAR TOPLAM (TOTAL CURRENT ASSETS) | L66: =IFERROR((B13-C13)/ABS(C13),"-") -> 0.29575929 | M66: =IFERROR((D13-E13)/ABS(E13),"-") -> 0.12209632 | N66: =IFERROR((F13-G13)/ABS(G13),"-") -> 0.52836202 | O66: =IFERROR((H13-I13)/ABS(I13),"-") -> 1.0124635 | P66: =IFERROR((I13-J13)/ABS(J13),"-") -> 1.1869772
K67: Diğer Alacaklar (UV) (Other receivables - non-current) | L67: =IFERROR((B15-C15)/ABS(C15),"-") -> 1.8252442 | M67: =IFERROR((D15-E15)/ABS(E15),"-") -> 0.081171486 | N67: =IFERROR((F15-G15)/ABS(G15),"-") -> -0.34458747 | O67: =IFERROR((H15-I15)/ABS(I15),"-") -> 0.020461266 | P67: =IFERROR((I15-J15)/ABS(J15),"-") -> 7.2892157
K68: Finansal Yatırımlar (UV) (LT financial investments) | L68: =IFERROR((B16-C16)/ABS(C16),"-") -> 0.61957766 | M68: =IFERROR((D16-E16)/ABS(E16),"-") -> 1.4919309 | N68: =IFERROR((F16-G16)/ABS(G16),"-") -> 3.577636 | O68: =IFERROR((H16-I16)/ABS(I16),"-") -> - | P68: =IFERROR((I16-J16)/ABS(J16),"-") -> -1
K69: Maddi Duran Varlıklar (Property, plant & equipment) | L69: =IFERROR((B17-C17)/ABS(C17),"-") -> 0.34659993 | M69: =IFERROR((D17-E17)/ABS(E17),"-") -> 0.33218695 | N69: =IFERROR((F17-G17)/ABS(G17),"-") -> 0.32137556 | O69: =IFERROR((H17-I17)/ABS(I17),"-") -> 0.69920423 | P69: =IFERROR((I17-J17)/ABS(J17),"-") -> 0.17274133
K70: Maddi Olmayan Duran Varlıklar (Intangible assets) | L70: =IFERROR((B18-C18)/ABS(C18),"-") -> -0.38829476 | M70: =IFERROR((D18-E18)/ABS(E18),"-") -> 0.092429532 | N70: =IFERROR((F18-G18)/ABS(G18),"-") -> 1.4370445 | O70: =IFERROR((H18-I18)/ABS(I18),"-") -> 0.78832278 | P70: =IFERROR((I18-J18)/ABS(J18),"-") -> 0.38710791
K71: Peşin Ödenmiş Giderler (UV) (Prepaid - non-current) | L71: =IFERROR((B19-C19)/ABS(C19),"-") -> 1.3748433 | M71: =IFERROR((D19-E19)/ABS(E19),"-") -> -0.88981701 | N71: =IFERROR((F19-G19)/ABS(G19),"-") -> 9.4464221 | O71: =IFERROR((H19-I19)/ABS(I19),"-") -> 21.977778 | P71: =IFERROR((I19-J19)/ABS(J19),"-") -> 0.0625
K72: Ertelenmiş Vergi Varlıkları (Deferred tax assets) | L72: =IFERROR((B20-C20)/ABS(C20),"-") -> 0.026929623 | M72: =IFERROR((D20-E20)/ABS(E20),"-") -> -0.15997616 | N72: =IFERROR((F20-G20)/ABS(G20),"-") -> 0.40146089 | O72: =IFERROR((H20-I20)/ABS(I20),"-") -> 4.0183125 | P72: =IFERROR((I20-J20)/ABS(J20),"-") -> -
K73: DURAN VARLIKLAR TOPLAM (TOTAL NON-CURRENT ASSETS) | L73: =IFERROR((B21-C21)/ABS(C21),"-") -> 0.20400782 | M73: =IFERROR((D21-E21)/ABS(E21),"-") -> 0.14261041 | N73: =IFERROR((F21-G21)/ABS(G21),"-") -> 0.74255349 | O73: =IFERROR((H21-I21)/ABS(I21),"-") -> 1.024629 | P73: =IFERROR((I21-J21)/ABS(J21),"-") -> 0.26559623
K74: TOPLAM VARLIKLAR (TOTAL ASSETS) | L74: =IFERROR((B22-C22)/ABS(C22),"-") -> 0.26742366 | M74: =IFERROR((D22-E22)/ABS(E22),"-") -> 0.12835264 | N74: =IFERROR((F22-G22)/ABS(G22),"-") -> 0.58788741 | O74: =IFERROR((H22-I22)/ABS(I22),"-") -> 1.015084 | P74: =IFERROR((I22-J22)/ABS(J22),"-") -> 0.89050651
K75: KV Borçlanmalar (ST borrowings) | L75: =IFERROR((B25-C25)/ABS(C25),"-") -> 0.94161479 | M75: =IFERROR((D25-E25)/ABS(E25),"-") -> 0.41858013 | N75: =IFERROR((F25-G25)/ABS(G25),"-") -> -0.47685903 | O75: =IFERROR((H25-I25)/ABS(I25),"-") -> 0.13040683 | P75: =IFERROR((I25-J25)/ABS(J25),"-") -> 1.2461348
K76: UV Borçlanmaların KV Kısmı (Current portion of LT borrowings) | L76: =IFERROR((B26-C26)/ABS(C26),"-") -> -0.53992415 | M76: =IFERROR((D26-E26)/ABS(E26),"-") -> -0.55922724 | N76: =IFERROR((F26-G26)/ABS(G26),"-") -> 0.012830957 | O76: =IFERROR((H26-I26)/ABS(I26),"-") -> -0.096669193 | P76: =IFERROR((I26-J26)/ABS(J26),"-") -> -
K77: Ticari Borçlar (Trade payables) | L77: =IFERROR((B27-C27)/ABS(C27),"-") -> 0.48125099 | M77: =IFERROR((D27-E27)/ABS(E27),"-") -> -0.31006973 | N77: =IFERROR((F27-G27)/ABS(G27),"-") -> 0.080008049 | O77: =IFERROR((H27-I27)/ABS(I27),"-") -> 1.0312455 | P77: =IFERROR((I27-J27)/ABS(J27),"-") -> 0.75914612
K78: Diğer Borçlar (Other payables - current) | L78: =IFERROR((B29-C29)/ABS(C29),"-") -> - | M78: =IFERROR((D29-E29)/ABS(E29),"-") -> -1 | N78: =IFERROR((F29-G29)/ABS(G29),"-") -> - | O78: =IFERROR((H29-I29)/ABS(I29),"-") -> -1 | P78: =IFERROR((I29-J29)/ABS(J29),"-") -> -0.84760635
K79: Ertelenmiş Gelirler (Deferred income) | L79: =IFERROR((B30-C30)/ABS(C30),"-") -> 0.12620376 | M79: =IFERROR((D30-E30)/ABS(E30),"-") -> 0.15597596 | N79: =IFERROR((F30-G30)/ABS(G30),"-") -> 2.2508715 | O79: =IFERROR((H30-I30)/ABS(I30),"-") -> 2.0564701 | P79: =IFERROR((I30-J30)/ABS(J30),"-") -> 1.5458713
K80: Dönem Vergi Yükümlülüğü (Current income tax) | L80: =IFERROR((B31-C31)/ABS(C31),"-") -> - | M80: =IFERROR((D31-E31)/ABS(E31),"-") -> - | N80: =IFERROR((F31-G31)/ABS(G31),"-") -> -1 | O80: =IFERROR((H31-I31)/ABS(I31),"-") -> 0.93979542 | P80: =IFERROR((I31-J31)/ABS(J31),"-") -> -
K81: KV Karşılıklar (Short-term provisions) | L81: =IFERROR((B32-C32)/ABS(C32),"-") -> 4.6934084 | M81: =IFERROR((D32-E32)/ABS(E32),"-") -> 1.3470168 | N81: =IFERROR((F32-G32)/ABS(G32),"-") -> 0.034661385 | O81: =IFERROR((H32-I32)/ABS(I32),"-") -> 1.8 | P81: =IFERROR((I32-J32)/ABS(J32),"-") -> 0.56490649
K82: Diğer KV Yükümlülükler (Other current liabilities) | L82: =IFERROR((B33-C33)/ABS(C33),"-") -> 0.050389184 | M82: =IFERROR((D33-E33)/ABS(E33),"-") -> -0.15786065 | N82: =IFERROR((F33-G33)/ABS(G33),"-") -> 0.31176438 | O82: =IFERROR((H33-I33)/ABS(I33),"-") -> 8.6585581 | P82: =IFERROR((I33-J33)/ABS(J33),"-") -> 3.7862888
K83: Türev Araçlar (Derivative liabilities) | L83: =IFERROR((B34-C34)/ABS(C34),"-") -> - | M83: =IFERROR((D34-E34)/ABS(E34),"-") -> - | N83: =IFERROR((F34-G34)/ABS(G34),"-") -> - | O83: =IFERROR((H34-I34)/ABS(I34),"-") -> -1 | P83: =IFERROR((I34-J34)/ABS(J34),"-") -> -
K84: KV YÜKÜMLÜLÜKLER TOPLAM (TOTAL CURRENT LIABILITIES) | L84: =IFERROR((B35-C35)/ABS(C35),"-") -> 0.3723778 | M84: =IFERROR((D35-E35)/ABS(E35),"-") -> 0.043082145 | N84: =IFERROR((F35-G35)/ABS(G35),"-") -> 0.32540898 | O84: =IFERROR((H35-I35)/ABS(I35),"-") -> 0.60185119 | P84: =IFERROR((I35-J35)/ABS(J35),"-") -> 1.365987
K85: Uzun Vadeli Borçlanmalar (Long-term borrowings) | L85: =IFERROR((B37-C37)/ABS(C37),"-") -> -1 | M85: =IFERROR((D37-E37)/ABS(E37),"-") -> -0.68986189 | N85: =IFERROR((F37-G37)/ABS(G37),"-") -> -0.67596313 | O85: =IFERROR((H37-I37)/ABS(I37),"-") -> -0.3598261 | P85: =IFERROR((I37-J37)/ABS(J37),"-") -> -0.24925336
K86: Uzun Vadeli Karşılıklar (Long-term provisions) | L86: =IFERROR((B38-C38)/ABS(C38),"-") -> 0.35321115 | M86: =IFERROR((D38-E38)/ABS(E38),"-") -> 0.19120491 | N86: =IFERROR((F38-G38)/ABS(G38),"-") -> -0.13504212 | O86: =IFERROR((H38-I38)/ABS(I38),"-") -> 1.0744066 | P86: =IFERROR((I38-J38)/ABS(J38),"-") -> 0.30224432
K87: Ertelenmiş Vergi Yükümlülüğü (Deferred tax liabilities) | L87: =IFERROR((B39-C39)/ABS(C39),"-") -> - | M87: =IFERROR((D39-E39)/ABS(E39),"-") -> - | N87: =IFERROR((F39-G39)/ABS(G39),"-") -> - | O87: =IFERROR((H39-I39)/ABS(I39),"-") -> - | P87: =IFERROR((I39-J39)/ABS(J39),"-") -> -1
K88: UV YÜKÜMLÜLÜKLER TOPLAM (TOTAL NON-CURRENT LIABILITIES) | L88: =IFERROR((B40-C40)/ABS(C40),"-") -> -0.23712872 | M88: =IFERROR((D40-E40)/ABS(E40),"-") -> -0.46805351 | N88: =IFERROR((F40-G40)/ABS(G40),"-") -> -0.61541477 | O88: =IFERROR((H40-I40)/ABS(I40),"-") -> -0.30612592 | P88: =IFERROR((I40-J40)/ABS(J40),"-") -> -0.23855338
K89: TOPLAM YÜKÜMLÜLÜKLER (TOTAL LIABILITIES) | L89: =IFERROR((B41-C41)/ABS(C41),"-") -> 0.36690143 | M89: =IFERROR((D41-E41)/ABS(E41),"-") -> 0.034153827 | N89: =IFERROR((F41-G41)/ABS(G41),"-") -> 0.27109271 | O89: =IFERROR((H41-I41)/ABS(I41),"-") -> 0.48922275 | P89: =IFERROR((I41-J41)/ABS(J41),"-") -> 0.87570236
K90: Ödenmiş Sermaye (Paid-in capital) | L90: =IFERROR((B43-C43)/ABS(C43),"-") -> 0 | M90: =IFERROR((D43-E43)/ABS(E43),"-") -> 0 | N90: =IFERROR((F43-G43)/ABS(G43),"-") -> 0.17411765 | O90: =IFERROR((H43-I43)/ABS(I43),"-") -> 0 | P90: =IFERROR((I43-J43)/ABS(J43),"-") -> 3.4127877
K91: Sermaye Düzeltme Farkları (Cap. adjustment differences) | L91: =IFERROR((B44-C44)/ABS(C44),"-") -> 0 | M91: =IFERROR((D44-E44)/ABS(E44),"-") -> 0 | N91: =IFERROR((F44-G44)/ABS(G44),"-") -> 0.10052254 | O91: =IFERROR((H44-I44)/ABS(I44),"-") -> - | P91: =IFERROR((I44-J44)/ABS(J44),"-") -> -
K92: Hisse Senedi Primleri (Share premiums) | L92: =IFERROR((B45-C45)/ABS(C45),"-") -> 0 | M92: =IFERROR((D45-E45)/ABS(E45),"-") -> 0 | N92: =IFERROR((F45-G45)/ABS(G45),"-") -> - | O92: =IFERROR((H45-I45)/ABS(I45),"-") -> - | P92: =IFERROR((I45-J45)/ABS(J45),"-") -> -
K93: Kar Yedekleri (Retained earnings reserves) | L93: =IFERROR((B46-C46)/ABS(C46),"-") -> 0 | M93: =IFERROR((D46-E46)/ABS(E46),"-") -> 0.83069043 | N93: =IFERROR((F46-G46)/ABS(G46),"-") -> 1.3968252 | O93: =IFERROR((H46-I46)/ABS(I46),"-") -> 0.91885828 | P93: =IFERROR((I46-J46)/ABS(J46),"-") -> 1.1279743
K94: Yeniden Değerleme ve Diğer Kapsamlı Gelir | L94: =IFERROR((B47-C47)/ABS(C47),"-") -> -0.021229581 | M94: =IFERROR((D47-E47)/ABS(E47),"-") -> -0.017209028 | N94: =IFERROR((F47-G47)/ABS(G47),"-") -> -0.20965185 | O94: =IFERROR((H47-I47)/ABS(I47),"-") -> 15.755377 | P94: =IFERROR((I47-J47)/ABS(J47),"-") -> 23.776089
K95: Geçmiş Yıllar Karları (Retained earnings) | L95: =IFERROR((B48-C48)/ABS(C48),"-") -> 0.42489576 | M95: =IFERROR((D48-E48)/ABS(E48),"-") -> 0.97764446 | N95: =IFERROR((F48-G48)/ABS(G48),"-") -> 0.52320384 | O95: =IFERROR((H48-I48)/ABS(I48),"-") -> 1.5361017 | P95: =IFERROR((I48-J48)/ABS(J48),"-") -> -3.3832653
K96: Net Dönem Karı (Net profit for the period) | L96: =IFERROR((B49-C49)/ABS(C49),"-") -> 0.16598687 | M96: =IFERROR((D49-E49)/ABS(E49),"-") -> -0.24312789 | N96: =IFERROR((F49-G49)/ABS(G49),"-") -> 1.2535406 | O96: =IFERROR((H49-I49)/ABS(I49),"-") -> 2.5292178 | P96: =IFERROR((I49-J49)/ABS(J49),"-") -> 1.2369471
K97: ÖZKAYNAKLAR TOPLAM (TOTAL EQUITY) | L97: =IFERROR((B50-C50)/ABS(C50),"-") -> 0.2209549 | M97: =IFERROR((D50-E50)/ABS(E50),"-") -> 0.17849715 | N97: =IFERROR((F50-G50)/ABS(G50),"-") -> 0.83078004 | O97: =IFERROR((H50-I50)/ABS(I50),"-") -> 2.0137824 | P97: =IFERROR((I50-J50)/ABS(J50),"-") -> 0.91927371
K98: TOPLAM YÜKÜMLÜLÜKLER VE ÖZKAYNAKLAR (TOTAL LIAB. & EQUITY) | L98: =IFERROR((B51-C51)/ABS(C51),"-") -> 0.26742358 | M98: =IFERROR((D51-E51)/ABS(E51),"-") -> 0.12835269 | N98: =IFERROR((F51-G51)/ABS(G51),"-") -> 0.58788746 | O98: =IFERROR((H51-I51)/ABS(I51),"-") -> 1.0150828 | P98: =IFERROR((I51-J51)/ABS(J51),"-") -> 0.89050598

Sheet ASTOR_PLS
A1: ASTOR ENERJİ A.Ş. — KONSOLİDE KAR/ZARAR TABLOSU / CONSOLIDATED P&L | L1: DİKEY ANALİZ (% HASILAT)
A2: KALEM (BİN TL) | B2: 31.12.2025 (2025 SAG) | C2: 31.12.2024 (2025 SAG) | D2: 31.12.2024 (2024 SAG) | E2: 31.12.2023 (2024 SAG) | F2: 31.12.2023 (2023 SAG) | G2: 31.12.2022 (2023 SAG) | H2: 31.12.2022 (Nominal) | I2: 31.12.2021 (Nominal) | J2: 31.12.2020 (Nominal) | L2: 31.12.2025 (2025 SAG) | M2: 31.12.2024 (2025 SAG) | N2: 31.12.2024 (2024 SAG) | O2: 31.12.2023 (2024 SAG) | P2: 31.12.2023 (2023 SAG) | Q2: 31.12.2022 (2023 SAG) | R2: 31.12.2022 (Nominal) | S2: 31.12.2021 (Nominal) | T2: 31.12.2020 (Nominal)
A3: Hasılat (Net Revenue) | B3: 35290767 | C3: 34848865 | D3: 26624070 | E3: 24420786 | F3: 16914388 | G3: 13783508 | H3: 7392433 | I3: 3154302 | J3: 1448766 | L3: =IFERROR(B3/B3,"") -> 1 | M3: =IFERROR(C3/C3,"") -> 1 | N3: =IFERROR(D3/D3,"") -> 1 | O3: =IFERROR(E3/E3,"") -> 1 | P3: =IFERROR(F3/F3,"") -> 1 | Q3: =IFERROR(G3/G3,"") -> 1 | R3: =IFERROR(H3/H3,"") -> 1 | S3: =IFERROR(I3/I3,"") -> 1 | T3: =IFERROR(J3/J3,"") -> 1
A4: Satışların Maliyeti (Cost of sales) | B4: -22250945 | C4: -22796923 | D4: -17416547 | E4: -15068862 | F4: -10437034 | G4: -9598256 | H4: -4906915 | I4: -2270193 | J4: -1016663 | L4: =IFERROR(B4/B3,"") -> -0.6305033 | M4: =IFERROR(C4/C3,"") -> -0.65416544 | N4: =IFERROR(D4/D3,"") -> -0.65416546 | O4: =IFERROR(E4/E3,"") -> -0.61705066 | P4: =IFERROR(F4/F3,"") -> -0.61705064 | Q4: =IFERROR(G4/G3,"") -> -0.696358 | R4: =IFERROR(H4/H3,"") -> -0.66377538 | S4: =IFERROR(I4/I3,"") -> -0.71971327 | T4: =IFERROR(J4/J3,"") -> -0.7017441
A5: BRÜT KAR (Gross Profit) | B5: =B3+B4 -> 13039822 | C5: =C3+C4 -> 12051942 | D5: =D3+D4 -> 9207523 | E5: =E3+E4 -> 9351924 | F5: =F3+F4 -> 6477354 | G5: =G3+G4 -> 4185252 | H5: =H3+H4 -> 2485518 | I5: =I3+I4 -> 884109 | J5: =J3+J4 -> 432103 | L5: =IFERROR(B5/B3,"") -> 0.3694967 | M5: =IFERROR(C5/C3,"") -> 0.34583456 | N5: =IFERROR(D5/D3,"") -> 0.34583454 | O5: =IFERROR(E5/E3,"") -> 0.38294934 | P5: =IFERROR(F5/F3,"") -> 0.38294936 | Q5: =IFERROR(G5/G3,"") -> 0.303642 | R5: =IFERROR(H5/H3,"") -> 0.33622462 | S5: =IFERROR(I5/I3,"") -> 0.28028673 | T5: =IFERROR(J5/J3,"") -> 0.2982559
A6: Genel Yönetim Giderleri (G&A expenses) | B6: -628308 | C6: -611063 | D6: -466844 | E6: -357025 | F6: -247284 | G6: -121207 | H6: -67521 | I6: -20465 | J6: -36991 | L6: =IFERROR(B6/B3,"") -> -0.01780375 | M6: =IFERROR(C6/C3,"") -> -0.01753466 | N6: =IFERROR(D6/D3,"") -> -0.017534659 | O6: =IFERROR(E6/E3,"") -> -0.014619718 | P6: =IFERROR(F6/F3,"") -> -0.014619743 | Q6: =IFERROR(G6/G3,"") -> -0.008793625 | R6: =IFERROR(H6/H3,"") -> -0.0091337994 | S6: =IFERROR(I6/I3,"") -> -0.0064879647 | T6: =IFERROR(J6/J3,"") -> -0.025532764
A7: Pazarlama, Satış ve Dağıtım Giderleri (S&M expenses) | B7: -2107723 | C7: -1886918 | D7: -1441580 | E7: -976752 | F7: -676521 | G7: -527455 | H7: -304665 | I7: -65601 | J7: -46987 | L7: =IFERROR(B7/B3,"") -> -0.059724488 | M7: =IFERROR(C7/C3,"") -> -0.054145752 | N7: =IFERROR(D7/D3,"") -> -0.054145741 | O7: =IFERROR(E7/E3,"") -> -0.039996747 | P7: =IFERROR(F7/F3,"") -> -0.039996777 | Q7: =IFERROR(G7/G3,"") -> -0.038267109 | R7: =IFERROR(H7/H3,"") -> -0.041213089 | S7: =IFERROR(I7/I3,"") -> -0.020797311 | T7: =IFERROR(J7/J3,"") -> -0.032432429
A8: Araştırma ve Geliştirme Giderleri (R&D expenses) | B8: -258962 | C8: -250678 | D8: -191515 | E8: -102990 | F8: -71334 | G8: -52209 | H8: -28709 | I8: -22590 | J8: -3315 | L8: =IFERROR(B8/B3,"") -> -0.0073379533 | M8: =IFERROR(C8/C3,"") -> -0.0071932902 | N8: =IFERROR(D8/D3,"") -> -0.0071933029 | O8: =IFERROR(E8/E3,"") -> -0.004217309 | P8: =IFERROR(F8/F3,"") -> -0.0042173563 | Q8: =IFERROR(G8/G3,"") -> -0.0037877876 | R8: =IFERROR(H8/H3,"") -> -0.0038835658 | S8: =IFERROR(I8/I3,"") -> -0.0071616478 | T8: =IFERROR(J8/J3,"") -> -0.0022881542
A9: Esas Faaliyetlerden Diğer Gelirler (Other operating income) | B9: 4159608 | C9: 2328305 | D9: 1778794 | E9: 1886215 | F9: 1306435 | G9: 1035734 | H9: 600298 | I9: 555210 | J9: 228370 | L9: =IFERROR(B9/B3,"") -> 0.11786675 | M9: =IFERROR(C9/C3,"") -> 0.066811502 | N9: =IFERROR(D9/D3,"") -> 0.066811498 | O9: =IFERROR(E9/E3,"") -> 0.077238095 | P9: =IFERROR(F9/F3,"") -> 0.077238089 | Q9: =IFERROR(G9/G3,"") -> 0.07514299 | R9: =IFERROR(H9/H3,"") -> 0.081204388 | S9: =IFERROR(I9/I3,"") -> 0.17601675 | T9: =IFERROR(J9/J3,"") -> 0.1576307
A10: Esas Faaliyetlerden Diğer Giderler (Other operating exp.) | B10: -4427042 | C10: -2993626 | D10: -2287090 | E10: -1828777 | F10: -1266652 | G10: -845227 | H10: -492391 | I10: -324353 | J10: -246893 | L10: =IFERROR(B10/B3,"") -> -0.12544477 | M10: =IFERROR(C10/C3,"") -> -0.085903113 | N10: =IFERROR(D10/D3,"") -> -0.085903094 | O10: =IFERROR(E10/E3,"") -> -0.074886083 | P10: =IFERROR(F10/F3,"") -> -0.074886067 | Q10: =IFERROR(G10/G3,"") -> -0.061321617 | R10: =IFERROR(H10/H3,"") -> -0.066607435 | S10: =IFERROR(I10/I3,"") -> -0.10282877 | T10: =IFERROR(J10/J3,"") -> -0.17041606
A11: FAALİYET KARI (Operating Profit / EBIT) | B11: =B5+SUM(B6:B10) -> 9777395 | C11: =C5+SUM(C6:C10) -> 8637962 | D11: =D5+SUM(D6:D10) -> 6599288 | E11: =E5+SUM(E6:E10) -> 7972595 | F11: =F5+SUM(F6:F10) -> 5521998 | G11: =G5+SUM(G6:G10) -> 3674888 | H11: =H5+SUM(H6:H10) -> 2192530 | I11: =I5+SUM(I6:I10) -> 1006310 | J11: =J5+SUM(J6:J10) -> 326287 | L11: =IFERROR(B11/B3,"") -> 0.27705249 | M11: =IFERROR(C11/C3,"") -> 0.24786925 | N11: =IFERROR(D11/D3,"") -> 0.24786924 | O11: =IFERROR(E11/E3,"") -> 0.32646758 | P11: =IFERROR(F11/F3,"") -> 0.3264675 | Q11: =IFERROR(G11/G3,"") -> 0.26661486 | R11: =IFERROR(H11/H3,"") -> 0.29659112 | S11: =IFERROR(I11/I3,"") -> 0.31902779 | T11: =IFERROR(J11/J3,"") -> 0.22521718
A12: (+) Amortisman ve İtfa Payları (Depreciation & amort.) | B12: 1057758 | C12: 1129742 | D12: 863108 | E12: 454087 | F12: 314584 | G12: 131218 | H12: 79631 | I12: 67565 | J12: 56715 | L12: =IFERROR(B12/B3,"") -> 0.029972655 | M12: =IFERROR(C12/C3,"") -> 0.03241833 | N12: =IFERROR(D12/D3,"") -> 0.032418334 | O12: =IFERROR(E12/E3,"") -> 0.018594283 | P12: =IFERROR(F12/F3,"") -> 0.018598604 | Q12: =IFERROR(G12/G3,"") -> 0.0095199277 | R12: =IFERROR(H12/H3,"") -> 0.010771961 | S12: =IFERROR(I12/I3,"") -> 0.021419953 | T12: =IFERROR(J12/J3,"") -> 0.039147109
A13: FAVÖK (EBITDA) | B13: =B11+B12 -> 10835153 | C13: =C11+C12 -> 9767704 | D13: =D11+D12 -> 7462396 | E13: =E11+E12 -> 8426682 | F13: =F11+F12 -> 5836582 | G13: =G11+G12 -> 3806106 | H13: =H11+H12 -> 2272161 | I13: =I11+I12 -> 1073875 | J13: =J11+J12 -> 383002 | L13: =IFERROR(B13/B3,"") -> 0.30702515 | M13: =IFERROR(C13/C3,"") -> 0.28028758 | N13: =IFERROR(D13/D3,"") -> 0.28028757 | O13: =IFERROR(E13/E3,"") -> 0.34506187 | P13: =IFERROR(F13/F3,"") -> 0.34506611 | Q13: =IFERROR(G13/G3,"") -> 0.27613478 | R13: =IFERROR(H13/H3,"") -> 0.30736308 | S13: =IFERROR(I13/I3,"") -> 0.34044774 | T13: =IFERROR(J13/J3,"") -> 0.26436429
A14: Yatırım Faaliyetlerinden Gelirler (Income from investments) | B14: 5905860 | C14: 2247241 | D14: 1716862 | E14: 797204 | F14: 552162 | G14: 193574 | H14: 118253 | I14: 5127 | J14: 6694 | L14: =IFERROR(B14/B3,"") -> 0.16734859 | M14: =IFERROR(C14/C3,"") -> 0.064485343 | N14: =IFERROR(D14/D3,"") -> 0.064485332 | O14: =IFERROR(E14/E3,"") -> 0.032644486 | P14: =IFERROR(F14/F3,"") -> 0.032644515 | Q14: =IFERROR(G14/G3,"") -> 0.014043885 | R14: =IFERROR(H14/H3,"") -> 0.015996493 | S14: =IFERROR(I14/I3,"") -> 0.0016253992 | T14: =IFERROR(J14/J3,"") -> 0.0046204839
A15: Yatırım Faaliyetlerinden Giderler (Expenses from inv.) | B15: -142910 | C15: -578722 | D15: -442136 | E15: -411459 | F15: -284986 | G15: -16654 | H15: -10106 | I15: -13814 | J15: 0 | L15: =IFERROR(B15/B3,"") -> -0.0040495011 | M15: =IFERROR(C15/C3,"") -> -0.016606624 | N15: =IFERROR(D15/D3,"") -> -0.016606627 | O15: =IFERROR(E15/E3,"") -> -0.016848721 | P15: =IFERROR(F15/F3,"") -> -0.016848733 | Q15: =IFERROR(G15/G3,"") -> -0.0012082555 | R15: =IFERROR(H15/H3,"") -> -0.0013670736 | S15: =IFERROR(I15/I3,"") -> -0.0043794158 | T15: =IFERROR(J15/J3,"") -> 0
A16: Finansman Öncesi Faaliyet Karı (Op. profit before fin.) | B16: =B11+B14+B15 -> 15540345 | C16: =C11+C14+C15 -> 10306481 | D16: =D11+D14+D15 -> 7874014 | E16: =E11+E14+E15 -> 8358340 | F16: =F11+F14+F15 -> 5789174 | G16: =G11+G14+G15 -> 3851808 | H16: =H11+H14+H15 -> 2300677 | I16: =I11+I14+I15 -> 997623 | J16: =J11+J14+J15 -> 332981 | L16: =IFERROR(B16/B3,"") -> 0.44035158 | M16: =IFERROR(C16/C3,"") -> 0.29574797 | N16: =IFERROR(D16/D3,"") -> 0.29574795 | O16: =IFERROR(E16/E3,"") -> 0.34226335 | P16: =IFERROR(F16/F3,"") -> 0.34226328 | Q16: =IFERROR(G16/G3,"") -> 0.27945049 | R16: =IFERROR(H16/H3,"") -> 0.31122054 | S16: =IFERROR(I16/I3,"") -> 0.31627377 | T16: =IFERROR(J16/J3,"") -> 0.22983767
A17: Finansal Gelirler (Financial income) | B17: 1817789 | C17: 2316704 | D17: 1769931 | E17: 1472871 | F17: 1020144 | G17: 717193 | H17: 35679 | I17: 16916 | J17: 0 | L17: =IFERROR(B17/B3,"") -> 0.051508912 | M17: =IFERROR(C17/C3,"") -> 0.066478607 | N17: =IFERROR(D17/D3,"") -> 0.066478604 | O17: =IFERROR(E17/E3,"") -> 0.060312187 | P17: =IFERROR(F17/F3,"") -> 0.060312203 | Q17: =IFERROR(G17/G3,"") -> 0.05203269 | R17: =IFERROR(H17/H3,"") -> 0.0048264218 | S17: =IFERROR(I17/I3,"") -> 0.0053628346 | T17: =IFERROR(J17/J3,"") -> 0
A18: Finansal Giderler (Financial expenses) | B18: -1497125 | C18: -1143016 | D18: -873249 | E18: -1214248 | F18: -841016 | G18: -1241955 | H18: -358014 | I18: -459443 | J18: -101320 | L18: =IFERROR(B18/B3,"") -> -0.042422569 | M18: =IFERROR(C18/C3,"") -> -0.032799232 | N18: =IFERROR(D18/D3,"") -> -0.03279923 | O18: =IFERROR(E18/E3,"") -> -0.049721905 | P18: =IFERROR(F18/F3,"") -> -0.049721929 | Q18: =IFERROR(G18/G3,"") -> -0.09010442 | R18: =IFERROR(H18/H3,"") -> -0.048429793 | S18: =IFERROR(I18/I3,"") -> -0.145656 | T18: =IFERROR(J18/J3,"") -> -0.069935379
A19: Net Parasal Pozisyon Kaybı (Net monetary loss) | B19: -8068557 | C19: -4744207 | D19: -3624511 | E19: -1059874 | F19: -734093 | G19: -1043997 | H19: 0 | I19: 0 | J19: 0 | L19: =IFERROR(B19/B3,"") -> -0.22863082 | M19: =IFERROR(C19/C3,"") -> -0.13613663 | N19: =IFERROR(D19/D3,"") -> -0.13613662 | O19: =IFERROR(E19/E3,"") -> -0.043400487 | P19: =IFERROR(F19/F3,"") -> -0.043400506 | Q19: =IFERROR(G19/G3,"") -> -0.075742474 | R19: =IFERROR(H19/H3,"") -> 0 | S19: =IFERROR(I19/I3,"") -> 0 | T19: =IFERROR(J19/J3,"") -> 0
A20: VERGİ ÖNCESİ KAR (Profit before tax) | B20: =B16+B17+B18+B19 -> 7792452 | C20: =C16+C17+C18+C19 -> 6735962 | D20: =D16+D17+D18+D19 -> 5146185 | E20: =E16+E17+E18+E19 -> 7557089 | F20: =F16+F17+F18+F19 -> 5234209 | G20: =G16+G17+G18+G19 -> 2283049 | H20: =H16+H17+H18+H19 -> 1978342 | I20: =I16+I17+I18+I19 -> 555096 | J20: =J16+J17+J18+J19 -> 231661 | L20: =IFERROR(B20/B3,"") -> 0.2208071 | M20: =IFERROR(C20/C3,"") -> 0.19329071 | N20: =IFERROR(D20/D3,"") -> 0.1932907 | O20: =IFERROR(E20/E3,"") -> 0.30945314 | P20: =IFERROR(F20/F3,"") -> 0.30945305 | Q20: =IFERROR(G20/G3,"") -> 0.16563628 | R20: =IFERROR(H20/H3,"") -> 0.26761717 | S20: =IFERROR(I20/I3,"") -> 0.17598061 | T20: =IFERROR(J20/J3,"") -> 0.15990229
A21: Dönem Vergi Gideri (Current tax expense) | B21: -495655 | C21: -577372 | D21: -441104 | E21: -1150076 | F21: -796568 | G21: -441768 | H21: -253435 | I21: -57469 | J21: -485 | L21: =IFERROR(B21/B3,"") -> -0.014044892 | M21: =IFERROR(C21/C3,"") -> -0.016567885 | N21: =IFERROR(D21/D3,"") -> -0.016567865 | O21: =IFERROR(E21/E3,"") -> -0.047094143 | P21: =IFERROR(F21/F3,"") -> -0.047094107 | Q21: =IFERROR(G21/G3,"") -> -0.032050477 | R21: =IFERROR(H21/H3,"") -> -0.03428303 | S21: =IFERROR(I21/I3,"") -> -0.018219245 | T21: =IFERROR(J21/J3,"") -> -0.00033476766
A22: Ertelenmiş Vergi Geliri/(Gideri) (Deferred tax inc./(exp.)) | B22: 372113 | C22: 418593 | D22: 319800 | E22: 231995 | F22: 160685 | G22: 199209 | H22: 102103 | I22: 20054 | J22: 245 | L22: =IFERROR(B22/B3,"") -> 0.010544203 | M22: =IFERROR(C22/C3,"") -> 0.012011668 | N22: =IFERROR(D22/D3,"") -> 0.012011687 | O22: =IFERROR(E22/E3,"") -> 0.009499899 | P22: =IFERROR(F22/F3,"") -> 0.0094999003 | Q22: =IFERROR(G22/G3,"") -> 0.014452707 | R22: =IFERROR(H22/H3,"") -> 0.013811826 | S22: =IFERROR(I22/I3,"") -> 0.0063576665 | T22: =IFERROR(J22/J3,"") -> 0.00016910944
A23: NET DÖNEM KARI (Net Profit) | B23: =B20+B21+B22 -> 7668910 | C23: =C20+C21+C22 -> 6577183 | D23: =D20+D21+D22 -> 5024881 | E23: =E20+E21+E22 -> 6639008 | F23: =F20+F21+F22 -> 4598326 | G23: =G20+G21+G22 -> 2040490 | H23: =H20+H21+H22 -> 1827010 | I23: =I20+I21+I22 -> 517681 | J23: =J20+J21+J22 -> 231421 | L23: =IFERROR(B23/B3,"") -> 0.21730641 | M23: =IFERROR(C23/C3,"") -> 0.1887345 | N23: =IFERROR(D23/D3,"") -> 0.18873452 | O23: =IFERROR(E23/E3,"") -> 0.2718589 | P23: =IFERROR(F23/F3,"") -> 0.27185885 | Q23: =IFERROR(G23/G3,"") -> 0.14803851 | R23: =IFERROR(H23/H3,"") -> 0.24714597 | S23: =IFERROR(I23/I3,"") -> 0.16411903 | T23: =IFERROR(J23/J3,"") -> 0.15973663
A24: Hisse Başına Kazanç - TL (Earnings per Share) | B24: 7.68 | C24: 6.59 | D24: 5.03 | E24: 6.7 | F24: 4.64 | G24: 2.4 | H24: 2.15 | I24: 2.52 | J24: 1.21 | L24: =IFERROR(B24/B3,"") -> 2.1762066e-07 | M24: =IFERROR(C24/C3,"") -> 1.8910228e-07 | N24: =IFERROR(D24/D3,"") -> 1.8892679e-07 | O24: =IFERROR(E24/E3,"") -> 2.7435644e-07 | P24: =IFERROR(F24/F3,"") -> 2.7432267e-07 | Q24: =IFERROR(G24/G3,"") -> 1.7412113e-07 | R24: =IFERROR(H24/H3,"") -> 2.9083794e-07 | S24: =IFERROR(I24/I3,"") -> 7.9890892e-07 | T24: =IFERROR(J24/J3,"") -> 8.3519354e-07
L29: YATAY ANALİZ (YoY % Değişim — Aynı Satın Alma Gücü)
L30: 2025/2024 | M30: 2024/2023 | N30: 2023/2022 | O30: 2022/2021 | P30: 2021/2020
K31: Hasılat (Net Revenue) | L31: =IFERROR((B3-C3)/ABS(C3),"-") -> 0.012680528 | M31: =IFERROR((D3-E3)/ABS(E3),"-") -> 0.090221666 | N31: =IFERROR((F3-G3)/ABS(G3),"-") -> 0.22714682 | O31: =IFERROR((H3-I3)/ABS(I3),"-") -> 1.3436034 | P31: =IFERROR((I3-J3)/ABS(J3),"-") -> 1.1772336
K32: Satışların Maliyeti (Cost of sales) | L32: =IFERROR((B4-C4)/ABS(C4),"-") -> 0.023949636 | M32: =IFERROR((D4-E4)/ABS(E4),"-") -> -0.1557971 | N32: =IFERROR((F4-G4)/ABS(G4),"-") -> -0.087388584 | O32: =IFERROR((H4-I4)/ABS(I4),"-") -> -1.1614528 | P32: =IFERROR((I4-J4)/ABS(J4),"-") -> -1.2329848
K33: BRÜT KAR (Gross Profit) | L33: =IFERROR((B5-C5)/ABS(C5),"-") -> 0.081968533 | M33: =IFERROR((D5-E5)/ABS(E5),"-") -> -0.01544078 | N33: =IFERROR((F5-G5)/ABS(G5),"-") -> 0.54766165 | O33: =IFERROR((H5-I5)/ABS(I5),"-") -> 1.8113253 | P33: =IFERROR((I5-J5)/ABS(J5),"-") -> 1.0460608
K34: Genel Yönetim Giderleri (G&A expenses) | L34: =IFERROR((B6-C6)/ABS(C6),"-") -> -0.028221313 | M34: =IFERROR((D6-E6)/ABS(E6),"-") -> -0.30759471 | N34: =IFERROR((F6-G6)/ABS(G6),"-") -> -1.0401792 | O34: =IFERROR((H6-I6)/ABS(I6),"-") -> -2.2993403 | P34: =IFERROR((I6-J6)/ABS(J6),"-") -> 0.44675732
K35: Pazarlama, Satış ve Dağıtım Giderleri (S&M expenses) | L35: =IFERROR((B7-C7)/ABS(C7),"-") -> -0.11701886 | M35: =IFERROR((D7-E7)/ABS(E7),"-") -> -0.47589153 | N35: =IFERROR((F7-G7)/ABS(G7),"-") -> -0.28261368 | O35: =IFERROR((H7-I7)/ABS(I7),"-") -> -3.6442127 | P35: =IFERROR((I7-J7)/ABS(J7),"-") -> -0.39615213
K36: Araştırma ve Geliştirme Giderleri (R&D expenses) | L36: =IFERROR((B8-C8)/ABS(C8),"-") -> -0.033046378 | M36: =IFERROR((D8-E8)/ABS(E8),"-") -> -0.85954947 | N36: =IFERROR((F8-G8)/ABS(G8),"-") -> -0.36631615 | O36: =IFERROR((H8-I8)/ABS(I8),"-") -> -0.27087207 | P36: =IFERROR((I8-J8)/ABS(J8),"-") -> -5.8144796
K37: Esas Faaliyetlerden Diğer Gelirler (Other operating income) | L37: =IFERROR((B9-C9)/ABS(C9),"-") -> 0.78653913 | M37: =IFERROR((D9-E9)/ABS(E9),"-") -> -0.05695056 | N37: =IFERROR((F9-G9)/ABS(G9),"-") -> 0.26136151 | O37: =IFERROR((H9-I9)/ABS(I9),"-") -> 0.081208912 | P37: =IFERROR((I9-J9)/ABS(J9),"-") -> 1.4311862
K38: Esas Faaliyetlerden Diğer Giderler (Other operating exp.) | L38: =IFERROR((B10-C10)/ABS(C10),"-") -> -0.47882267 | M38: =IFERROR((D10-E10)/ABS(E10),"-") -> -0.25061175 | N38: =IFERROR((F10-G10)/ABS(G10),"-") -> -0.49859387 | O38: =IFERROR((H10-I10)/ABS(I10),"-") -> -0.51807136 | P38: =IFERROR((I10-J10)/ABS(J10),"-") -> -0.31373915
K39: FAALİYET KARI (Operating Profit / EBIT) | L39: =IFERROR((B11-C11)/ABS(C11),"-") -> 0.13190993 | M39: =IFERROR((D11-E11)/ABS(E11),"-") -> -0.17225345 | N39: =IFERROR((F11-G11)/ABS(G11),"-") -> 0.50263028 | O39: =IFERROR((H11-I11)/ABS(I11),"-") -> 1.1787819 | P39: =IFERROR((I11-J11)/ABS(J11),"-") -> 2.0841253
K40: (+) Amortisman ve İtfa Payları (Depreciation & amort.) | L40: =IFERROR((B12-C12)/ABS(C12),"-") -> -0.063717203 | M40: =IFERROR((D12-E12)/ABS(E12),"-") -> 0.9007547 | N40: =IFERROR((F12-G12)/ABS(G12),"-") -> 1.397415 | O40: =IFERROR((H12-I12)/ABS(I12),"-") -> 0.17858359 | P40: =IFERROR((I12-J12)/ABS(J12),"-") -> 0.19130741
K41: FAVÖK (EBITDA) | L41: =IFERROR((B13-C13)/ABS(C13),"-") -> 0.10928351 | M41: =IFERROR((D13-E13)/ABS(E13),"-") -> -0.11443247 | N41: =IFERROR((F13-G13)/ABS(G13),"-") -> 0.53347857 | O41: =IFERROR((H13-I13)/ABS(I13),"-") -> 1.1158524 | P41: =IFERROR((I13-J13)/ABS(J13),"-") -> 1.8038365
K42: Yatırım Faaliyetlerinden Gelirler (Income from investments) | L42: =IFERROR((B14-C14)/ABS(C14),"-") -> 1.6280492 | M42: =IFERROR((D14-E14)/ABS(E14),"-") -> 1.1536043 | N42: =IFERROR((F14-G14)/ABS(G14),"-") -> 1.8524595 | O42: =IFERROR((H14-I14)/ABS(I14),"-") -> 22.064755 | P42: =IFERROR((I14-J14)/ABS(J14),"-") -> -0.23409023
... K52: Hisse Başına Kazanç - TL (Earnings per Share) | L52: =IFERROR((B24-C24)/ABS(C24),"-") -> 0.16540212 | M52: =IFERROR((D24-E24)/ABS(E24),"-") -> -0.24925373 | N52: =IFERROR((F24-G24)/ABS(G24),"-") -> 0.93333333 | O52: =IFERROR((H24-I24)/ABS(I24),"-") -> -0.1468254 | P52: =IFERROR((I24-J24)/ABS(J24),"-") -> 1.0826446

Sheet ASTOR_CFS
A1: ASTOR ENERJİ A.Ş. — KONSOLİDE NAKİT AKIŞ TABLOSU / CONSOLIDATED CASH FLOW | L1: DİKEY ANALİZ (% İŞL. NAKİT AKIŞI)
A2: KALEM (BİN TL) | B2: 31.12.2025 (2025 SAG) | C2: 31.12.2024 (2025 SAG) | D2: 31.12.2024 (2024 SAG) | E2: 31.12.2023 (2024 SAG) | F2: 31.12.2023 (2023 SAG) | G2: 31.12.2022 (2023 SAG) | H2: 31.12.2022 (Nominal) | I2: 31.12.2021 (Nominal) | J2: 31.12.2020 (Nominal) | L2: 31.12.2025 (2025 SAG) | M2: 31.12.2024 (2025 SAG) | N2: 31.12.2024 (2024 SAG) | O2: 31.12.2023 (2024 SAG) | P2: 31.12.2023 (2023 SAG) | Q2: 31.12.2022 (2023 SAG) | R2: 31.12.2022 (Nominal) | S2: 31.12.2021 (Nominal) | T2: 31.12.2020 (Nominal)
A3: A. İŞLETME FAALİYETLERİNDEN NAKİT AKIŞLARI
A4: İŞLETME FAALİYETLERİNDEN NAKİT AKIŞI (Operating Cash Flow) | B4: =SUM(B5:B12) -> 2756906 | C4: =SUM(C5:C12) -> 10219484 | D4: =SUM(D5:D12) -> 7060886 | E4: =SUM(E5:E12) -> 5799053 | F4: =SUM(F5:F12) -> 2999528 | G4: =SUM(G5:G12) -> 613051 | H4: =SUM(H5:H12) -> 560393 | I4: =SUM(I5:I12) -> -234573 | J4: =SUM(J5:J12) -> -8189 | L4: =IFERROR(B4/B4,"") -> 1 | M4: =IFERROR(C4/C4,"") -> 1 | N4: =IFERROR(D4/D4,"") -> 1 | O4: =IFERROR(E4/E4,"") -> 1 | P4: =IFERROR(F4/F4,"") -> 1 | Q4: =IFERROR(G4/G4,"") -> 1 | R4: =IFERROR(H4/H4,"") -> 1 | S4: =IFERROR(I4/I4,"") -> 1 | T4: =IFERROR(J4/J4,"") -> 1
A5: Dönem Karı (Profit for the year) | B5: 7668909 | C5: 6577183 | D5: 5024880 | E5: 6639008 | F5: 4598327 | G5: 2040490 | H5: 1827009 | I5: 517681 | J5: 231423 | L5: =IFERROR(B5/B4,"") -> 2.7817086 | M5: =IFERROR(C5/C4,"") -> 0.64359247 | N5: =IFERROR(D5/D4,"") -> 0.71165007 | O5: =IFERROR(E5/E4,"") -> 1.1448435 | P5: =IFERROR(F5/F4,"") -> 1.5330169 | Q5: =IFERROR(G5/G4,"") -> 3.328418 | R5: =IFERROR(H5/H4,"") -> 3.2602281 | S5: =IFERROR(I5/I4,"") -> -2.2069079 | T5: =IFERROR(J5/J4,"") -> -28.260227
A6: (+) Amortisman ve İtfa (Depreciation & amortization) | B6: 1057758 | C6: 1129742 | D6: 863108 | E6: 454087 | F6: 314584 | G6: 131218 | H6: 79631 | I6: 67565 | J6: 56715 | L6: =IFERROR(B6/B4,"") -> 0.38367576 | M6: =IFERROR(C6/C4,"") -> 0.11054785 | N6: =IFERROR(D6/D4,"") -> 0.12223792 | O6: =IFERROR(E6/E4,"") -> 0.078303647 | P6: =IFERROR(F6/F4,"") -> 0.10487783 | Q6: =IFERROR(G6/G4,"") -> 0.21404092 | R6: =IFERROR(H6/H4,"") -> 0.14209849 | S6: =IFERROR(I6/I4,"") -> -0.288034 | T6: =IFERROR(J6/J4,"") -> -6.9257541
A7: Karşılık Gid. ve Diğer Düz. (Provisions & other adj.) | B7: 957079 | C7: 1054971 | D7: 808871 | E7: 1067741 | F7: 738824 | G7: 314717 | H7: 170601 | I7: 72947 | J7: 16809 | L7: =IFERROR(B7/B4,"") -> 0.34715692 | M7: =IFERROR(C7/C4,"") -> 0.10323134 | N7: =IFERROR(D7/D4,"") -> 0.11455659 | O7: =IFERROR(E7/E4,"") -> 0.18412334 | P7: =IFERROR(F7/F4,"") -> 0.24631342 | Q7: =IFERROR(G7/G4,"") -> 0.51336186 | R7: =IFERROR(H7/H4,"") -> 0.304431 | S7: =IFERROR(I7/I4,"") -> -0.31097782 | T7: =IFERROR(J7/J4,"") -> -2.0526316
A8: Faiz Düz. - Net (Net interest adjustments) | B8: -276167 | C8: -1093944 | D8: -835758 | E8: -768781 | F8: -225960 | G8: 297741 | H8: 180687 | I8: 68466 | J8: 43740 | L8: =IFERROR(B8/B4,"") -> -0.1001728 | M8: =IFERROR(C8/C4,"") -> -0.10704493 | N8: =IFERROR(D8/D4,"") -> -0.11836447 | O8: =IFERROR(E8/E4,"") -> -0.13257009 | P8: =IFERROR(F8/F4,"") -> -0.075331852 | Q8: =IFERROR(G8/G4,"") -> 0.48567085 | R8: =IFERROR(H8/H4,"") -> 0.32242908 | S8: =IFERROR(I8/I4,"") -> -0.29187502 | T8: =IFERROR(J8/J4,"") -> -5.3413115
A9: Parasal Kazanç/Kayıp (Monetary gain/loss adj.) | B9: 5063860 | C9: 1342932 | D9: 577932 | E9: -316985 | F9: -132366 | G9: 659724 | H9: 0 | I9: 0 | J9: 0 | L9: =IFERROR(B9/B4,"") -> 1.836791 | M9: =IFERROR(C9/C4,"") -> 0.13140898 | N9: =IFERROR(D9/D4,"") -> 0.081849785 | O9: =IFERROR(E9/E4,"") -> -0.054661511 | P9: =IFERROR(F9/F4,"") -> -0.044128943 | Q9: =IFERROR(G9/G4,"") -> 1.0761323 | R9: =IFERROR(H9/H4,"") -> 0 | S9: =IFERROR(I9/I4,"") -> 0 | T9: =IFERROR(J9/J4,"") -> 0
A10: Diğer Düzeltmeler (Other adjustments) | B10: -4517642 | C10: -81631 | D10: -62946 | E10: -8977 | F10: -16020 | G10: -255147 | H10: -134451 | I10: 69750 | J10: -37860 | L10: =IFERROR(B10/B4,"") -> -1.6386638 | M10: =IFERROR(C10/C4,"") -> -0.007987781 | N10: =IFERROR(D10/D4,"") -> -0.0089147453 | O10: =IFERROR(E10/E4,"") -> -0.0015480114 | P10: =IFERROR(F10/F4,"") -> -0.0053408403 | Q10: =IFERROR(G10/G4,"") -> -0.41619213 | R10: =IFERROR(H10/H4,"") -> -0.2399227 | S10: =IFERROR(I10/I4,"") -> -0.2973488 | T10: =IFERROR(J10/J4,"") -> 4.6232751
A11: İşletme Sermayesi Değişimleri (Working capital changes) | B11: -6928778 | C11: 1290231 | D11: 684799 | E11: -1267040 | F11: -2277861 | G11: -2575692 | H11: -1563084 | I11: -1030982 | J11: -319016 | L11: =IFERROR(B11/B4,"") -> -2.5132442 | M11: =IFERROR(C11/C4,"") -> 0.12625207 | N11: =IFERROR(D11/D4,"") -> 0.096984854 | O11: =IFERROR(E11/E4,"") -> -0.21849085 | P11: =IFERROR(F11/F4,"") -> -0.75940648 | Q11: =IFERROR(G11/G4,"") -> -4.2014319 | R11: =IFERROR(H11/H4,"") -> -2.789264 | S11: =IFERROR(I11/I4,"") -> 4.3951435 | T11: =IFERROR(J11/J4,"") -> 38.956649
A12: (-) Ödenen Vergiler (Taxes paid) | B12: -268113 | C12: 0 | D12: 0 | E12: 0 | F12: 0 | G12: 0 | H12: 0 | I12: 0 | J12: 0 | L12: =IFERROR(B12/B4,"") -> -0.097251412 | M12: =IFERROR(C12/C4,"") -> 0 | N12: =IFERROR(D12/D4,"") -> 0 | O12: =IFERROR(E12/E4,"") -> 0 | P12: =IFERROR(F12/F4,"") -> 0 | Q12: =IFERROR(G12/G4,"") -> 0 | R12: =IFERROR(H12/H4,"") -> 0 | S12: =IFERROR(I12/I4,"") -> 0 | T12: =IFERROR(J12/J4,"") -> 0
A13: B. YATIRIM FAALİYETLERİNDEN NAKİT AKIŞLARI
A14: YATIRIM FAALİYETLERİNDEN NAKİT AKIŞI (Investing Cash Flow) | B14: =SUM(B15:B17) -> -6993637 | C14: =SUM(C15:C17) -> -5478621 | D14: =SUM(D15:D17) -> -4185594 | E14: =SUM(E15:E17) -> -3899946 | F14: =SUM(F15:F17) -> -2034351 | G14: =SUM(G15:G17) -> -312939 | H14: =SUM(H15:H17) -> -189909 | I14: =SUM(I15:I17) -> -185945 | J14: =SUM(J15:J17) -> -143683 | L14: =IFERROR(B14/B4,"") -> -2.5367702 | M14: =IFERROR(C14/C4,"") -> -0.53609566 | N14: =IFERROR(D14/D4,"") -> -0.59278595 | O14: =IFERROR(E14/E4,"") -> -0.67251429 | P14: =IFERROR(F14/F4,"") -> -0.67822371 | Q14: =IFERROR(G14/G4,"") -> -0.51046161 | R14: =IFERROR(H14/H4,"") -> -0.33888539 | S14: =IFERROR(I14/I4,"") -> 0.79269566 | T14: =IFERROR(J14/J4,"") -> 17.545854
A15: (-) MDV+MODV Alımları (Tangible/intangible CAPEX) | B15: -4557006 | C15: -4847161 | D15: -3703167 | E15: -2656743 | F15: -1840120 | G15: -404755 | H15: -245629 | I15: -193170 | J15: -143798 | L15: =IFERROR(B15/B4,"") -> -1.6529421 | M15: =IFERROR(C15/C4,"") -> -0.47430585 | N15: =IFERROR(D15/D4,"") -> -0.52446209 | O15: =IFERROR(E15/E4,"") -> -0.45813394 | P15: =IFERROR(F15/F4,"") -> -0.61346985 | Q15: =IFERROR(G15/G4,"") -> -0.66023055 | R15: =IFERROR(H15/H4,"") -> -0.43831561 | S15: =IFERROR(I15/I4,"") -> 0.82349631 | T15: =IFERROR(J15/J4,"") -> 17.559897
A16: (+) MDV Satışlarından Girişler (Proceeds from sales) | B16: 2129202 | C16: 1711331 | D16: 1307434 | E16: 27035 | F16: 18725 | G16: 131115 | H16: 79569 | I16: 7225 | J16: 4421 | L16: =IFERROR(B16/B4,"") -> 0.77231578 | M16: =IFERROR(C16/C4,"") -> 0.16745767 | N16: =IFERROR(D16/D4,"") -> 0.18516571 | O16: =IFERROR(E16/E4,"") -> 0.0046619681 | P16: =IFERROR(F16/F4,"") -> 0.0062426488 | Q16: =IFERROR(G16/G4,"") -> 0.21387291 | R16: =IFERROR(H16/H4,"") -> 0.14198785 | S16: =IFERROR(I16/I4,"") -> -0.030800646 | T16: =IFERROR(J16/J4,"") -> -0.53987056
A17: (-) Finansal Yatırım Çıkışları (Financial investments) | B17: -4565833 | C17: -2342791 | D17: -1789861 | E17: -1270238 | F17: -212956 | G17: -39299 | H17: -23849 | I17: 0 | J17: -4306 | L17: =IFERROR(B17/B4,"") -> -1.6561439 | M17: =IFERROR(C17/C4,"") -> -0.22924748 | N17: =IFERROR(D17/D4,"") -> -0.25348958 | O17: =IFERROR(E17/E4,"") -> -0.21904232 | P17: =IFERROR(F17/F4,"") -> -0.070996503 | Q17: =IFERROR(G17/G4,"") -> -0.064103965 | R17: =IFERROR(H17/H4,"") -> -0.042557634 | S17: =IFERROR(I17/I4,"") -> 0 | T17: =IFERROR(J17/J4,"") -> 0.52582733
A18: C. FİNANSMAN FAALİYETLERİNDEN NAKİT AKIŞLARI
A19: FİNANSMAN FAALİYETLERİNDEN NAKİT AKIŞI (Financing Cash Flow) | B19: =SUM(B20:B23) -> 844128 | C19: =SUM(C20:C23) -> -832619 | D19: =SUM(D20:D23) -> -636110 | E19: =SUM(E20:E23) -> 189587 | F19: =SUM(F20:F23) -> 481499 | G19: =SUM(G20:G23) -> -857660 | H19: =SUM(H20:H23) -> -520479 | I19: =SUM(I20:I23) -> 488916 | J19: =SUM(J20:J23) -> 282564 | L19: =IFERROR(B19/B4,"") -> 0.30618672 | M19: =IFERROR(C19/C4,"") -> -0.081473683 | N19: =IFERROR(D19/D4,"") -> -0.090089261 | O19: =IFERROR(E19/E4,"") -> 0.032692752 | P19: =IFERROR(F19/F4,"") -> 0.16052492 | Q19: =IFERROR(G19/G4,"") -> -1.3990027 | R19: =IFERROR(H19/H4,"") -> -0.92877498 | S19: =IFERROR(I19/I4,"") -> -2.0842808 | T19: =IFERROR(J19/J4,"") -> -34.505312
A20: Kredilerden Net Nakit Girişi (Net borrowings) | B20: 3439575 | C20: 2833804 | D20: 277940 | E20: -1441283 | F20: -998265 | G20: 97474 | H20: 59153 | I20: 530217 | J20: 327497 | L20: =IFERROR(B20/B4,"") -> 1.2476214 | M20: =IFERROR(C20/C4,"") -> 0.27729424 | N20: =IFERROR(D20/D4,"") -> 0.039363332 | O20: =IFERROR(E20/E4,"") -> -0.24853765 | P20: =IFERROR(F20/F4,"") -> -0.33280736 | Q20: =IFERROR(G20/G4,"") -> 0.15899819 | R20: =IFERROR(H20/H4,"") -> 0.10555628 | S20: =IFERROR(I20/I4,"") -> -2.2603497 | T20: =IFERROR(J20/J4,"") -> -39.992307
A21: (-) Ödenen Faizler (Interest paid) | B21: -970181 | C21: -1235001 | D21: -943524 | E21: -399782 | F21: -276898 | G21: -411740 | H21: -249868 | I21: -47549 | J21: -44933 | L21: =IFERROR(B21/B4,"") -> -0.35190935 | M21: =IFERROR(C21/C4,"") -> -0.12084769 | N21: =IFERROR(D21/D4,"") -> -0.13362686 | O21: =IFERROR(E21/E4,"") -> -0.068939187 | P21: =IFERROR(F21/F4,"") -> -0.092313857 | Q21: =IFERROR(G21/G4,"") -> -0.67162438 | R21: =IFERROR(H21/H4,"") -> -0.44587994 | S21: =IFERROR(I21/I4,"") -> 0.20270449 | T21: =IFERROR(J21/J4,"") -> 5.4869947
A22: (-) Ödenen Temettüler (Dividends paid) | B22: -1625266 | C22: -2431422 | D22: -1857574 | E22: -1116260 | F22: 0 | G22: 0 | H22: 0 | I22: 0 | J22: 0 | L22: =IFERROR(B22/B4,"") -> -0.58952536 | M22: =IFERROR(C22/C4,"") -> -0.23792023 | N22: =IFERROR(D22/D4,"") -> -0.26307945 | O22: =IFERROR(E22/E4,"") -> -0.19249005 | P22: =IFERROR(F22/F4,"") -> 0 | Q22: =IFERROR(G22/G4,"") -> 0 | R22: =IFERROR(H22/H4,"") -> 0 | S22: =IFERROR(I22/I4,"") -> 0 | T22: =IFERROR(J22/J4,"") -> 0
A23: Diğer Finansman, Net (Pay ihracı/FX dahil) (Other financing, net) | B23: 0 | C23: 0 | D23: 1887048 | E23: 3146912 | F23: 1756662 | G23: -543394 | H23: -329764 | I23: 6248 | J23: 0 | L23: =IFERROR(B23/B4,"") -> 0 | M23: =IFERROR(C23/C4,"") -> 0 | N23: =IFERROR(D23/D4,"") -> 0.26725371 | O23: =IFERROR(E23/E4,"") -> 0.54265964 | P23: =IFERROR(F23/F4,"") -> 0.58564614 | Q23: =IFERROR(G23/G4,"") -> -0.8863765 | R23: =IFERROR(H23/H4,"") -> -0.58845132 | S23: =IFERROR(I23/I4,"") -> -0.026635632 | T23: =IFERROR(J23/J4,"") -> 0
A24: NAKİTTE NET DEĞİŞİM (Net change in cash) | B24: =B4+B14+B19 -> -3392603 | C24: =C4+C14+C19 -> 3908244 | D24: =D4+D14+D19 -> 2239182 | E24: =E4+E14+E19 -> 2088694 | F24: =F4+F14+F19 -> 1446676 | G24: =G4+G14+G19 -> -557548 | H24: =H4+H14+H19 -> -149995 | I24: =I4+I14+I19 -> 68398 | J24: =J4+J14+J19 -> 130692 | L24: =IFERROR(B24/B4,"") -> -1.2305835 | M24: =IFERROR(C24/C4,"") -> 0.38243066 | N24: =IFERROR(D24/D4,"") -> 0.31712479 | O24: =IFERROR(E24/E4,"") -> 0.36017846 | P24: =IFERROR(F24/F4,"") -> 0.48230122 | Q24: =IFERROR(G24/G4,"") -> -0.9094643 | R24: =IFERROR(H24/H4,"") -> -0.26766037 | S24: =IFERROR(I24/I4,"") -> -0.29158514 | T24: =IFERROR(J24/J4,"") -> -15.959458
A25: Dönem Başı Nakit (Cash at beginning) | B25: 6110484 | C25: 3179567 | D25: 2429147 | E25: 340453 | F25: 235806 | G25: 793354 | H25: 293096 | I25: 224697 | J25: 94005 | L25: =IFERROR(B25/B4,"") -> 2.2164281 | M25: =IFERROR(C25/C4,"") -> 0.31112794 | N25: =IFERROR(D25/D4,"") -> 0.34402864 | O25: =IFERROR(E25/E4,"") -> 0.058708379 | P25: =IFERROR(F25/F4,"") -> 0.078614369 | Q25: =IFERROR(G25/G4,"") -> 1.2941077 | R25: =IFERROR(H25/H4,"") -> 0.52301867 | S25: =IFERROR(I25/I4,"") -> -0.95789797 | T25: =IFERROR(J25/J4,"") -> -11.479424
A26: Nakit Üzerindeki Enflasyon Etkisi (Monetary effect on cash) | B26: -1442156 | C26: -977327 | D26: 0 | E26: 0 | F26: 0 | G26: 0 | H26: 0 | I26: 0 | J26: 0 | L26: =IFERROR(B26/B4,"") -> -0.5231067 | M26: =IFERROR(C26/C4,"") -> -0.095633693 | N26: =IFERROR(D26/D4,"") -> 0 | O26: =IFERROR(E26/E4,"") -> 0 | P26: =IFERROR(F26/F4,"") -> 0 | Q26: =IFERROR(G26/G4,"") -> 0 | R26: =IFERROR(H26/H4,"") -> 0 | S26: =IFERROR(I26/I4,"") -> 0 | T26: =IFERROR(J26/J4,"") -> 0
A27: DÖNEM SONU NAKİT (Cash at end of period) | B27: =B25+B24+B26 -> 1275725 | C27: =C25+C24+C26 -> 6110484 | D27: =D25+D24+D26 -> 4668329 | E27: =E25+E24+E26 -> 2429147 | F27: =F25+F24+F26 -> 1682482 | G27: =G25+G24+G26 -> 235806 | H27: =H25+H24+H26 -> 143101 | I27: =I25+I24+I26 -> 293095 | J27: =J25+J24+J26 -> 224697 | L27: =IFERROR(B27/B4,"") -> 0.46273794 | M27: =IFERROR(C27/C4,"") -> 0.59792491 | N27: =IFERROR(D27/D4,"") -> 0.66115343 | O27: =IFERROR(E27/E4,"") -> 0.41888684 | P27: =IFERROR(F27/F4,"") -> 0.56091558 | Q27: =IFERROR(G27/G4,"") -> 0.38464337 | R27: =IFERROR(H27/H4,"") -> 0.25535829 | S27: =IFERROR(I27/I4,"") -> -1.2494831 | T27: =IFERROR(J27/J4,"") -> -27.438881
L32: YATAY ANALİZ (YoY % Değişim — Aynı Satın Alma Gücü)
L33: 2025/2024 | M33: 2024/2023 | N33: 2023/2022 | O33: 2022/2021 | P33: 2021/2020
K34: İŞLETME FAALİYETLERİNDEN NAKİT AKIŞI (Operating Cash Flow) | L34: =IFERROR((B4-C4)/ABS(C4),"-") -> -0.73023041 | M34: =IFERROR((D4-E4)/ABS(E4),"-") -> 0.21759294 | N34: =IFERROR((F4-G4)/ABS(G4),"-") -> 3.8927871 | O34: =IFERROR((H4-I4)/ABS(I4),"-") -> 3.3889919 | P34: =IFERROR((I4-J4)/ABS(J4),"-") -> -27.644889
K35: Dönem Karı (Profit for the year) | L35: =IFERROR((B5-C5)/ABS(C5),"-") -> 0.16598687 | M35: =IFERROR((D5-E5)/ABS(E5),"-") -> -0.24312789 | N35: =IFERROR((F5-G5)/ABS(G5),"-") -> 1.2535406 | O35: =IFERROR((H5-I5)/ABS(I5),"-") -> 2.5292178 | P35: =IFERROR((I5-J5)/ABS(J5),"-") -> 1.2369471
K36: (+) Amortisman ve İtfa (Depreciation & amortization) | L36: =IFERROR((B6-C6)/ABS(C6),"-") -> -0.063717203 | M36: =IFERROR((D6-E6)/ABS(E6),"-") -> 0.9007547 | N36: =IFERROR((F6-G6)/ABS(G6),"-") -> 1.397415 | O36: =IFERROR((H6-I6)/ABS(I6),"-") -> 0.17858359 | P36: =IFERROR((I6-J6)/ABS(J6),"-") -> 0.19130741
K37: Karşılık Gid. ve Diğer Düz. (Provisions & other adj.) | L37: =IFERROR((B7-C7)/ABS(C7),"-") -> -0.092791176 | M37: =IFERROR((D7-E7)/ABS(E7),"-") -> -0.24244644 | N37: =IFERROR((F7-G7)/ABS(G7),"-") -> 1.3475821 | O37: =IFERROR((H7-I7)/ABS(I7),"-") -> 1.338698 | P37: =IFERROR((I7-J7)/ABS(J7),"-") -> 3.3397585
K38: Faiz Düz. - Net (Net interest adjustments) | L38: =IFERROR((B8-C8)/ABS(C8),"-") -> 0.74754923 | M38: =IFERROR((D8-E8)/ABS(E8),"-") -> -0.08712104 | N38: =IFERROR((F8-G8)/ABS(G8),"-") -> -1.7589146 | O38: =IFERROR((H8-I8)/ABS(I8),"-") -> 1.6390763 | P38: =IFERROR((I8-J8)/ABS(J8),"-") -> 0.56529492
K39: Parasal Kazanç/Kayıp (Monetary gain/loss adj.) | L39: =IFERROR((B9-C9)/ABS(C9),"-") -> 2.7707494 | M39: =IFERROR((D9-E9)/ABS(E9),"-") -> 2.8232156 | N39: =IFERROR((F9-G9)/ABS(G9),"-") -> -1.2006384 | O39: =IFERROR((H9-I9)/ABS(I9),"-") -> - | P39: =IFERROR((I9-J9)/ABS(J9),"-") -> -
K40: Diğer Düzeltmeler (Other adjustments) | L40: =IFERROR((B10-C10)/ABS(C10),"-") -> -54.342235 | M40: =IFERROR((D10-E10)/ABS(E10),"-") -> -6.0119193 | N40: =IFERROR((F10-G10)/ABS(G10),"-") -> 0.93721267 | O40: =IFERROR((H10-I10)/ABS(I10),"-") -> -2.9276129 | P40: =IFERROR((I10-J10)/ABS(J10),"-") -> 2.8423138
K41: İşletme Sermayesi Değişimleri (Working capital changes) | L41: =IFERROR((B11-C11)/ABS(C11),"-") -> -6.3701841 | M41: =IFERROR((D11-E11)/ABS(E11),"-") -> 1.5404715 | N41: =IFERROR((F11-G11)/ABS(G11),"-") -> 0.11563145 | O41: =IFERROR((H11-I11)/ABS(I11),"-") -> -0.51611182 | P41: =IFERROR((I11-J11)/ABS(J11),"-") -> -2.2317564
K42: (-) Ödenen Vergiler (Taxes paid) | L42: =IFERROR((B12-C12)/ABS(C12),"-") -> - | M42: =IFERROR((D12-E12)/ABS(E12),"-") -> - | N42: =IFERROR((F12-G12)/ABS(G12),"-") -> - | O42: =IFERROR((H12-I12)/ABS(I12),"-") -> - | P42: =IFERROR((I12-J12)/ABS(J12),"-") -> -
K43: YATIRIM FAALİYETLERİNDEN NAKİT AKIŞI (Investing Cash Flow) | L43: =IFERROR((B14-C14)/ABS(C14),"-") -> -0.27653236 | M43: =IFERROR((D14-E14)/ABS(E14),"-") -> -0.073244091 | N43: =IFERROR((F14-G14)/ABS(G14),"-") -> -5.5007909 | O43: =IFERROR((H14-I14)/ABS(I14),"-") -> -0.021318132 | P43: =IFERROR((I14-J14)/ABS(J14),"-") -> -0.29413361
K44: (-) MDV+MODV Alımları (Tangible/intangible CAPEX) | L44: =IFERROR((B15-C15)/ABS(C15),"-") -> 0.059860813 | M44: =IFERROR((D15-E15)/ABS(E15),"-") -> -0.39387476 | N44: =IFERROR((F15-G15)/ABS(G15),"-") -> -3.5462564 | O44: =IFERROR((H15-I15)/ABS(I15),"-") -> -0.27156908 | P44: =IFERROR((I15-J15)/ABS(J15),"-") -> -0.34334274
K45: (+) MDV Satışlarından Girişler (Proceeds from sales) | L45: =IFERROR((B16-C16)/ABS(C16),"-") -> 0.24417895 | M45: =IFERROR((D16-E16)/ABS(E16),"-") -> 47.360792 | N45: =IFERROR((F16-G16)/ABS(G16),"-") -> -0.85718644 | O45: =IFERROR((H16-I16)/ABS(I16),"-") -> 10.01301 | P45: =IFERROR((I16-J16)/ABS(J16),"-") -> 0.63424565
K46: (-) Finansal Yatırım Çıkışları (Financial investments) | L46: =IFERROR((B17-C17)/ABS(C17),"-") -> -0.94888618 | M46: =IFERROR((D17-E17)/ABS(E17),"-") -> -0.40907531 | N46: =IFERROR((F17-G17)/ABS(G17),"-") -> -4.4188656 | O46: =IFERROR((H17-I17)/ABS(I17),"-") -> - | P46: =IFERROR((I17-J17)/ABS(J17),"-") -> 1
K47: FİNANSMAN FAALİYETLERİNDEN NAKİT AKIŞI (Financing Cash Flow) | L47: =IFERROR((B19-C19)/ABS(C19),"-") -> 2.0138226 | M47: =IFERROR((D19-E19)/ABS(E19),"-") -> -4.3552406 | N47: =IFERROR((F19-G19)/ABS(G19),"-") -> 1.5614101 | O47: =IFERROR((H19-I19)/ABS(I19),"-") -> -2.0645571 | P47: =IFERROR((I19-J19)/ABS(J19),"-") -> 0.73028411
K48: Kredilerden Net Nakit Girişi (Net borrowings) | L48: =IFERROR((B20-C20)/ABS(C20),"-") -> 0.21376602 | M48: =IFERROR((D20-E20)/ABS(E20),"-") -> 1.1928421 | N48: =IFERROR((F20-G20)/ABS(G20),"-") -> -11.241346 | O48: =IFERROR((H20-I20)/ABS(I20),"-") -> -0.88843624 | P48: =IFERROR((I20-J20)/ABS(J20),"-") -> 0.61899804
K49: (-) Ödenen Faizler (Interest paid) | L49: =IFERROR((B21-C21)/ABS(C21),"-") -> 0.21442898 | M49: =IFERROR((D21-E21)/ABS(E21),"-") -> -1.3600963 | N49: =IFERROR((F21-G21)/ABS(G21),"-") -> 0.32749308 | O49: =IFERROR((H21-I21)/ABS(I21),"-") -> -4.254958 | P49: =IFERROR((I21-J21)/ABS(J21),"-") -> -0.058220016
K50: (-) Ödenen Temettüler (Dividends paid) | L50: =IFERROR((B22-C22)/ABS(C22),"-") -> 0.33155742 | M50: =IFERROR((D22-E22)/ABS(E22),"-") -> -0.66410514 | N50: =IFERROR((F22-G22)/ABS(G22),"-") -> - | O50: =IFERROR((H22-I22)/ABS(I22),"-") -> - | P50: =IFERROR((I22-J22)/ABS(J22),"-") -> -
K51: Sermaye Girişi (Capital inflow) | L51: =IFERROR((B23-C23)/ABS(C23),"-") -> - | M51: =IFERROR((D23-E23)/ABS(E23),"-") -> -0.40034929 | N51: =IFERROR((F23-G23)/ABS(G23),"-") -> 4.2327593 | O51: =IFERROR((H23-I23)/ABS(I23),"-") -> -53.779129 | P51: =IFERROR((I23-J23)/ABS(J23),"-") -> -
K52: NAKİTTE NET DEĞİŞİM (Net change in cash) | L52: =IFERROR((B24-C24)/ABS(C24),"-") -> -1.8680633 | M52: =IFERROR((D24-E24)/ABS(E24),"-") -> 0.07204885 | N52: =IFERROR((F24-G24)/ABS(G24),"-") -> 3.5947111 | O52: =IFERROR((H24-I24)/ABS(I24),"-") -> -3.1929735 | P52: =IFERROR((I24-J24)/ABS(J24),"-") -> -0.47664738
K53: Dönem Başı Nakit (Cash at beginning) | L53: =IFERROR((B25-C25)/ABS(C25),"-") -> 0.92179753 | M53: =IFERROR((D25-E25)/ABS(E25),"-") -> 6.1350436 | N53: =IFERROR((F25-G25)/ABS(G25),"-") -> -0.70277329 | O53: =IFERROR((H25-I25)/ABS(I25),"-") -> 0.30440549 | P53: =IFERROR((I25-J25)/ABS(J25),"-") -> 1.3902665
K54: Nakit Üzerindeki Enflasyon Etkisi (Monetary effect on cash) | L54: =IFERROR((B26-C26)/ABS(C26),"-") -> -0.47561256 | M54: =IFERROR((D26-E26)/ABS(E26),"-") -> - | N54: =IFERROR((F26-G26)/ABS(G26),"-") -> - | O54: =IFERROR((H26-I26)/ABS(I26),"-") -> - | P54: =IFERROR((I26-J26)/ABS(J26),"-") -> -
K55: DÖNEM SONU NAKİT (Cash at end of period) | L55: =IFERROR((B27-C27)/ABS(C27),"-") -> -0.79122358 | M55: =IFERROR((D27-E27)/ABS(E27),"-") -> 0.92179765 | N55: =IFERROR((F27-G27)/ABS(G27),"-") -> 6.1350263 | O55: =IFERROR((H27-I27)/ABS(I27),"-") -> -0.51175899 | P55: =IFERROR((I27-J27)/ABS(J27),"-") -> 0.30440104

Sheet ASTOR_Ratios
A1: ASTOR ENERJİ — FİNANSAL ORAN ANALİZİ / FINANCIAL RATIO ANALYSIS (2020–2025)
A2: Oran Adı | B2: Formül / Formula | C2: Sektörel Referans / Sector Reference | D2: 2025 | E2: 2024 | F2: 2023 | G2: 2022 | H2: 2021 | I2: 2020
A3: LİKİDİTE ORANLARI / LIQUIDITY RATIOS
A4: Cari Oran (Current Ratio) | B4: Dönen Var. / KV Yükümlülükler | C4: 1.50–2.00x | D4: =IFERROR(ASTOR_BS!B13/ASTOR_BS!B35,"-") -> 2.0681812 | E4: =IFERROR(ASTOR_BS!D13/ASTOR_BS!D35,"-") -> 2.1904733 | F4: =IFERROR(ASTOR_BS!F13/ASTOR_BS!F35,"-") -> 2.0362279 | G4: =IFERROR(ASTOR_BS!H13/ASTOR_BS!H35,"-") -> 1.7178178 | H4: =IFERROR(ASTOR_BS!I13/ASTOR_BS!I35,"-") -> 1.3673234 | I4: =IFERROR(ASTOR_BS!J13/ASTOR_BS!J35,"-") -> 1.4792424
A5: Asit-Test Oranı (Quick Ratio) | B5: (Dönen Var. - Stoklar)/KV Y. | C5: 0.80–1.50x | D5: =IFERROR((ASTOR_BS!B13-ASTOR_BS!B10)/ASTOR_BS!B35,"-") -> 1.6179481 | E5: =IFERROR((ASTOR_BS!D13-ASTOR_BS!D10)/ASTOR_BS!D35,"-") -> 1.8935183 | F5: =IFERROR((ASTOR_BS!F13-ASTOR_BS!F10)/ASTOR_BS!F35,"-") -> 1.7999864 | G5: =IFERROR((ASTOR_BS!H13-ASTOR_BS!H10)/ASTOR_BS!H35,"-") -> 1.3074299 | H5: =IFERROR((ASTOR_BS!I13-ASTOR_BS!I10)/ASTOR_BS!I35,"-") -> 1.065487 | I5: =IFERROR((ASTOR_BS!J13-ASTOR_BS!J10)/ASTOR_BS!J35,"-") -> 1.0332065
A6: Nakit Oranı (Cash Ratio) | B6: (Nakit + Fin.Yatırım) / KV Y. | C6: > 0.20x | D6: =IFERROR((ASTOR_BS!B5+ASTOR_BS!B6)/ASTOR_BS!B35,"-") -> 0.7242312 | E6: =IFERROR((ASTOR_BS!D5+ASTOR_BS!D6)/ASTOR_BS!D35,"-") -> 0.82170052 | F6: =IFERROR((ASTOR_BS!F5+ASTOR_BS!F6)/ASTOR_BS!F35,"-") -> 0.48153019 | G6: =IFERROR((ASTOR_BS!H5+ASTOR_BS!H6)/ASTOR_BS!H35,"-") -> 0.17594575 | H6: =IFERROR((ASTOR_BS!I5+ASTOR_BS!I6)/ASTOR_BS!I35,"-") -> 0.16099132 | I6: =IFERROR((ASTOR_BS!J5+ASTOR_BS!J6)/ASTOR_BS!J35,"-") -> 0.2908925
A7: BORÇLULUK / FİNANSAL YAPI ORANLARI / LEVERAGE & SOLVENCY
A8: Kaldıraç Oranı (Debt-to-Assets) | B8: Toplam Yüküm. / Toplam Aktifler | C8: %40–%60 | D8: =IFERROR(ASTOR_BS!B41/ASTOR_BS!B22,"-") -> 0.34338548 | E8: =IFERROR(ASTOR_BS!D41/ASTOR_BS!D22,"-") -> 0.31839521 | F8: =IFERROR(ASTOR_BS!F41/ASTOR_BS!F22,"-") -> 0.34739717 | G8: =IFERROR(ASTOR_BS!H41/ASTOR_BS!H22,"-") -> 0.48412455 | H8: =IFERROR(ASTOR_BS!I41/ASTOR_BS!I22,"-") -> 0.65507437 | I8: =IFERROR(ASTOR_BS!J41/ASTOR_BS!J22,"-") -> 0.6602446
A9: Borç / Özkaynak (D/E) | B9: Toplam Yüküm. / Özkaynak | C9: 0.50–1.50x | D9: =IFERROR(ASTOR_BS!B41/ASTOR_BS!B50,"-") -> 0.5229636 | E9: =IFERROR(ASTOR_BS!D41/ASTOR_BS!D50,"-") -> 0.46712587 | F9: =IFERROR(ASTOR_BS!F41/ASTOR_BS!F50,"-") -> 0.5323256 | G9: =IFERROR(ASTOR_BS!H41/ASTOR_BS!H50,"-") -> 0.93845296 | H9: =IFERROR(ASTOR_BS!I41/ASTOR_BS!I50,"-") -> 1.8991739 | I9: =IFERROR(ASTOR_BS!J41/ASTOR_BS!J50,"-") -> 1.9432905
A10: Fin. Borç / Özkaynak (Net Debt Ratio) | B10: (KV+UV Fin.Borç) / Özkaynak | C10: 0.30–1.00x | D10: =IFERROR((ASTOR_BS!B25+ASTOR_BS!B26+ASTOR_BS!B37)/ASTOR_BS!B50,"-") -> 0.13872493 | E10: =IFERROR((ASTOR_BS!D25+ASTOR_BS!D26+ASTOR_BS!D37)/ASTOR_BS!D50,"-") -> 0.093472599 | F10: =IFERROR((ASTOR_BS!F25+ASTOR_BS!F26+ASTOR_BS!F37)/ASTOR_BS!F50,"-") -> 0.09373253 | G10: =IFERROR((ASTOR_BS!H25+ASTOR_BS!H26+ASTOR_BS!H37)/ASTOR_BS!H50,"-") -> 0.38825643 | H10: =IFERROR((ASTOR_BS!I25+ASTOR_BS!I26+ASTOR_BS!I37)/ASTOR_BS!I50,"-") -> 1.1563926 | I10: =IFERROR((ASTOR_BS!J25+ASTOR_BS!J26+ASTOR_BS!J37)/ASTOR_BS!J50,"-") -> 1.2765644
A11: Net Borç / FAVÖK | B11: (Fin.Borç - Nakit - Fin.Yat.) / FAVÖK | C11: < 2.00x | D11: =IFERROR((ASTOR_BS!B25+ASTOR_BS!B26+ASTOR_BS!B37-ASTOR_BS!B5-ASTOR_BS!B6-ASTOR_BS!B16)/ASTOR_PLS!B13,"-") -> -0.91374363 | E11: =IFERROR((ASTOR_BS!D25+ASTOR_BS!D26+ASTOR_BS!D37-ASTOR_BS!D5-ASTOR_BS!D6-ASTOR_BS!D16)/ASTOR_PLS!D13,"-") -> -0.92555622 | F11: =IFERROR((ASTOR_BS!F25+ASTOR_BS!F26+ASTOR_BS!F37-ASTOR_BS!F5-ASTOR_BS!F6-ASTOR_BS!F16)/ASTOR_PLS!F13,"-") -> -0.37595017 | G11: =IFERROR((ASTOR_BS!H25+ASTOR_BS!H26+ASTOR_BS!H37-ASTOR_BS!H5-ASTOR_BS!H6-ASTOR_BS!H16)/ASTOR_PLS!H13,"-") -> 0.32393743 | H11: =IFERROR((ASTOR_BS!I25+ASTOR_BS!I26+ASTOR_BS!I37-ASTOR_BS!I5-ASTOR_BS!I6-ASTOR_BS!I16)/ASTOR_PLS!I13,"-") -> 0.90900617 | I11: =IFERROR((ASTOR_BS!J25+ASTOR_BS!J26+ASTOR_BS!J37-ASTOR_BS!J5-ASTOR_BS!J6-ASTOR_BS!J16)/ASTOR_PLS!J13,"-") -> 1.2778079
A12: Faiz Karşılama (Interest Coverage) | B12: EBIT / |Finansman Gid.| | C12: > 4.00x | D12: =IFERROR(ASTOR_PLS!B11/ABS(ASTOR_PLS!B18),"-") -> 6.5307807 | E12: =IFERROR(ASTOR_PLS!D11/ABS(ASTOR_PLS!D18),"-") -> 7.5571664 | F12: =IFERROR(ASTOR_PLS!F11/ABS(ASTOR_PLS!F18),"-") -> 6.5658656 | G12: =IFERROR(ASTOR_PLS!H11/ABS(ASTOR_PLS!H18),"-") -> 6.124146 | H12: =IFERROR(ASTOR_PLS!I11/ABS(ASTOR_PLS!I18),"-") -> 2.1902826 | I12: =IFERROR(ASTOR_PLS!J11/ABS(ASTOR_PLS!J18),"-") -> 3.2203612
A13: Özkaynak Çarpanı (Equity Multiplier) | B13: Toplam Aktifler / Özkaynak | C13: 1.50–2.50x | D13: =IFERROR(ASTOR_BS!B22/ASTOR_BS!B50,"-") -> 1.5229636 | E13: =IFERROR(ASTOR_BS!D22/ASTOR_BS!D50,"-") -> 1.4671259 | F13: =IFERROR(ASTOR_BS!F22/ASTOR_BS!F50,"-") -> 1.5323257 | G13: =IFERROR(ASTOR_BS!H22/ASTOR_BS!H50,"-") -> 1.9384536 | H13: =IFERROR(ASTOR_BS!I22/ASTOR_BS!I50,"-") -> 2.899173 | I13: =IFERROR(ASTOR_BS!J22/ASTOR_BS!J50,"-") -> 2.9432888
A14: KARLILIK ORANLARI / PROFITABILITY RATIOS
A15: Brüt Kar Marjı (Gross Margin) | B15: Brüt Kar / Hasılat | C15: %20–%35 | D15: =IFERROR(ASTOR_PLS!B5/ASTOR_PLS!B3,"-") -> 0.3694967 | E15: =IFERROR(ASTOR_PLS!D5/ASTOR_PLS!D3,"-") -> 0.34583454 | F15: =IFERROR(ASTOR_PLS!F5/ASTOR_PLS!F3,"-") -> 0.38294936 | G15: =IFERROR(ASTOR_PLS!H5/ASTOR_PLS!H3,"-") -> 0.33622462 | H15: =IFERROR(ASTOR_PLS!I5/ASTOR_PLS!I3,"-") -> 0.28028673 | I15: =IFERROR(ASTOR_PLS!J5/ASTOR_PLS!J3,"-") -> 0.2982559
A16: FAVÖK Marjı (EBITDA Margin) | B16: FAVÖK / Hasılat | C16: %18–%30 | D16: =IFERROR(ASTOR_PLS!B13/ASTOR_PLS!B3,"-") -> 0.30702515 | E16: =IFERROR(ASTOR_PLS!D13/ASTOR_PLS!D3,"-") -> 0.28028757 | F16: =IFERROR(ASTOR_PLS!F13/ASTOR_PLS!F3,"-") -> 0.34506611 | G16: =IFERROR(ASTOR_PLS!H13/ASTOR_PLS!H3,"-") -> 0.30736308 | H16: =IFERROR(ASTOR_PLS!I13/ASTOR_PLS!I3,"-") -> 0.34044774 | I16: =IFERROR(ASTOR_PLS!J13/ASTOR_PLS!J3,"-") -> 0.26436429
A17: EBIT Marjı (Operating Margin) | B17: EBIT / Hasılat | C17: %15–%25 | D17: =IFERROR(ASTOR_PLS!B11/ASTOR_PLS!B3,"-") -> 0.27705249 | E17: =IFERROR(ASTOR_PLS!D11/ASTOR_PLS!D3,"-") -> 0.24786924 | F17: =IFERROR(ASTOR_PLS!F11/ASTOR_PLS!F3,"-") -> 0.3264675 | G17: =IFERROR(ASTOR_PLS!H11/ASTOR_PLS!H3,"-") -> 0.29659112 | H17: =IFERROR(ASTOR_PLS!I11/ASTOR_PLS!I3,"-") -> 0.31902779 | I17: =IFERROR(ASTOR_PLS!J11/ASTOR_PLS!J3,"-") -> 0.22521718
A18: Net Kar Marjı (Net Margin) | B18: Net Kar / Hasılat | C18: %8–%18 | D18: =IFERROR(ASTOR_PLS!B23/ASTOR_PLS!B3,"-") -> 0.21730641 | E18: =IFERROR(ASTOR_PLS!D23/ASTOR_PLS!D3,"-") -> 0.18873452 | F18: =IFERROR(ASTOR_PLS!F23/ASTOR_PLS!F3,"-") -> 0.27185885 | G18: =IFERROR(ASTOR_PLS!H23/ASTOR_PLS!H3,"-") -> 0.24714597 | H18: =IFERROR(ASTOR_PLS!I23/ASTOR_PLS!I3,"-") -> 0.16411903 | I18: =IFERROR(ASTOR_PLS!J23/ASTOR_PLS!J3,"-") -> 0.15973663
A19: ROA (Aktif Karlılığı) | B19: Net Kar / Toplam Aktifler | C19: %5–%12 | D19: =IFERROR(ASTOR_PLS!B23/ASTOR_BS!B22,"-") -> 0.15130701 | E19: =IFERROR(ASTOR_PLS!D23/ASTOR_BS!D22,"-") -> 0.16447019 | F19: =IFERROR(ASTOR_PLS!F23/ASTOR_BS!F22,"-") -> 0.24519372 | G19: =IFERROR(ASTOR_PLS!H23/ASTOR_BS!H22,"-") -> 0.28467145 | H19: =IFERROR(ASTOR_PLS!I23/ASTOR_BS!I22,"-") -> 0.1625393 | I19: =IFERROR(ASTOR_PLS!J23/ASTOR_BS!J22,"-") -> 0.13736532
A20: ROE (Özkaynak Karlılığı) | B20: Net Kar / Özkaynak | C20: %15–%30 | D20: =IFERROR(ASTOR_PLS!B23/ASTOR_BS!B50,"-") -> 0.23043508 | E20: =IFERROR(ASTOR_PLS!D23/ASTOR_BS!D50,"-") -> 0.24129847 | F20: =IFERROR(ASTOR_PLS!F23/ASTOR_BS!F50,"-") -> 0.37571663 | G20: =IFERROR(ASTOR_PLS!H23/ASTOR_BS!H50,"-") -> 0.55182239 | H20: =IFERROR(ASTOR_PLS!I23/ASTOR_BS!I50,"-") -> 0.47122955 | I20: =IFERROR(ASTOR_PLS!J23/ASTOR_BS!J50,"-") -> 0.4043058
A21: FAALİYET VERİMLİLİĞİ / OPERATING EFFICIENCY
A22: Aktif Devir Hızı (Asset Turnover) | B22: Hasılat / Toplam Aktifler | C22: 0.60–1.20x | D22: =IFERROR(ASTOR_PLS!B3/ASTOR_BS!B22,"-") -> 0.69628416 | E22: =IFERROR(ASTOR_PLS!D3/ASTOR_BS!D22,"-") -> 0.87143671 | F22: =IFERROR(ASTOR_PLS!F3/ASTOR_BS!F22,"-") -> 0.90191555 | G22: =IFERROR(ASTOR_PLS!H3/ASTOR_BS!H22,"-") -> 1.1518353 | H22: =IFERROR(ASTOR_PLS!I3/ASTOR_BS!I22,"-") -> 0.99037444 | I22: =IFERROR(ASTOR_PLS!J3/ASTOR_BS!J22,"-") -> 0.85994876
A23: Tic. Alacak Devir Hızı (Trade Rec. Turnover) | B23: Hasılat / Tic. Alacaklar | C23: 4–10x | D23: =IFERROR(ASTOR_PLS!B3/(ASTOR_BS!B7+ASTOR_BS!B8),"-") -> 3.001523 | E23: =IFERROR(ASTOR_PLS!D3/(ASTOR_BS!D7+ASTOR_BS!D8),"-") -> 4.0682347 | F23: =IFERROR(ASTOR_PLS!F3/(ASTOR_BS!F7+ASTOR_BS!F8),"-") -> 2.8529429 | G23: =IFERROR(ASTOR_PLS!H3/(ASTOR_BS!H7+ASTOR_BS!H8),"-") -> 2.8673802 | H23: =IFERROR(ASTOR_PLS!I3/(ASTOR_BS!I7+ASTOR_BS!I8),"-") -> 2.2763699 | I23: =IFERROR(ASTOR_PLS!J3/(ASTOR_BS!J7+ASTOR_BS!J8),"-") -> 3.3704303
A24: Ort. Tahsilat Süresi (DSO, gün) | B24: 365 / Tic.Alacak Devir Hızı | C24: 60–100 gün | D24: =IFERROR(365/(ASTOR_PLS!B3/(ASTOR_BS!B7+ASTOR_BS!B8)),"-") -> 121.60493 | E24: =IFERROR(365/(ASTOR_PLS!D3/(ASTOR_BS!D7+ASTOR_BS!D8)),"-") -> 89.719503 | F24: =IFERROR(365/(ASTOR_PLS!F3/(ASTOR_BS!F7+ASTOR_BS!F8)),"-") -> 127.93807 | G24: =IFERROR(365/(ASTOR_PLS!H3/(ASTOR_BS!H7+ASTOR_BS!H8)),"-") -> 127.2939 | H24: =IFERROR(365/(ASTOR_PLS!I3/(ASTOR_BS!I7+ASTOR_BS!I8)),"-") -> 160.34301 | I24: =IFERROR(365/(ASTOR_PLS!J3/(ASTOR_BS!J7+ASTOR_BS!J8)),"-") -> 108.29478
A25: Stok Devir Hızı (Inventory Turnover) | B25: Satışların Maliyeti / Stoklar | C25: 4–8x | D25: =IFERROR(ABS(ASTOR_PLS!B4)/ASTOR_BS!B10,"-") -> 2.8538934 | E25: =IFERROR(ABS(ASTOR_PLS!D4)/ASTOR_BS!D10,"-") -> 6.083956 | F25: =IFERROR(ABS(ASTOR_PLS!F4)/ASTOR_BS!F10,"-") -> 6.901723 | G25: =IFERROR(ABS(ASTOR_PLS!H4)/ASTOR_BS!H10,"-") -> 4.084273 | H25: =IFERROR(ABS(ASTOR_PLS!I4)/ASTOR_BS!I10,"-") -> 4.1154195 | I25: =IFERROR(ABS(ASTOR_PLS!J4)/ASTOR_BS!J10,"-") -> 2.9508179
A26: Ort. Stok Süresi (Days Inventory, gün) | B26: 365 / Stok Devir Hızı | C26: 45–90 gün | D26: =IFERROR(365/(ABS(ASTOR_PLS!B4)/ASTOR_BS!B10),"-") -> 127.89546 | E26: =IFERROR(365/(ABS(ASTOR_PLS!D4)/ASTOR_BS!D10),"-") -> 59.993859 | F26: =IFERROR(365/(ABS(ASTOR_PLS!F4)/ASTOR_BS!F10),"-") -> 52.885345 | G26: =IFERROR(365/(ABS(ASTOR_PLS!H4)/ASTOR_BS!H10),"-") -> 89.36719 | H26: =IFERROR(365/(ABS(ASTOR_PLS!I4)/ASTOR_BS!I10),"-") -> 88.690836 | I26: =IFERROR(365/(ABS(ASTOR_PLS!J4)/ASTOR_BS!J10),"-") -> 123.69452
A27: Tic. Borç Devir Hızı (Trade Pay. Turnover) | B27: Hasılat / Ticari Borçlar | C27: 6–12x | D27: =IFERROR(ASTOR_PLS!B3/ASTOR_BS!B27,"-") -> 10.843157 | E27: =IFERROR(ASTOR_PLS!D3/ASTOR_BS!D27,"-") -> 15.860321 | F27: =IFERROR(ASTOR_PLS!F3/ASTOR_BS!F27,"-") -> 10.036962 | G27: =IFERROR(ASTOR_PLS!H3/ASTOR_BS!H27,"-") -> 7.806786 | H27: =IFERROR(ASTOR_PLS!I3/ASTOR_BS!I27,"-") -> 6.7662893 | I27: =IFERROR(ASTOR_PLS!J3/ASTOR_BS!J27,"-") -> 5.4669796
A28: NAKİT AKIŞ ORANLARI / CASH FLOW RATIOS
A29: İşletme Nakdi / Net Kar | B29: OCF / Net Dönem Karı | C29: > 0.80x | D29: =IFERROR(ASTOR_CFS!B4/ASTOR_PLS!B23,"-") -> 0.35949124 | E29: =IFERROR(ASTOR_CFS!D4/ASTOR_PLS!D23,"-") -> 1.4051847 | F29: =IFERROR(ASTOR_CFS!F4/ASTOR_PLS!F23,"-") -> 0.65230869 | G29: =IFERROR(ASTOR_CFS!H4/ASTOR_PLS!H23,"-") -> 0.30672684 | H29: =IFERROR(ASTOR_CFS!I4/ASTOR_PLS!I23,"-") -> -0.45312268 | I29: =IFERROR(ASTOR_CFS!J4/ASTOR_PLS!J23,"-") -> -0.035385726
A30: FAVÖK / Faiz Gideri | B30: FAVÖK / |Finansman Gid.| | C30: > 3.00x | D30: =IFERROR(ASTOR_PLS!B13/ABS(ASTOR_PLS!B18),"-") -> 7.2373068 | E30: =IFERROR(ASTOR_PLS!D13/ABS(ASTOR_PLS!D18),"-") -> 8.5455534 | F30: =IFERROR(ASTOR_PLS!F13/ABS(ASTOR_PLS!F18),"-") -> 6.9399179 | G30: =IFERROR(ASTOR_PLS!H13/ABS(ASTOR_PLS!H18),"-") -> 6.3465702 | H30: =IFERROR(ASTOR_PLS!I13/ABS(ASTOR_PLS!I18),"-") -> 2.3373411 | I30: =IFERROR(ASTOR_PLS!J13/ABS(ASTOR_PLS!J18),"-") -> 3.7801224
A31: Serbest Nakit Akışı / Hasılat | B31: (OCF + Yat.CF) / Hasılat | C31: >%5 | D31: =IFERROR((ASTOR_CFS!B4+ASTOR_CFS!B14)/ASTOR_PLS!B3,"-") -> -0.12005211 | E31: =IFERROR((ASTOR_CFS!D4+ASTOR_CFS!D14)/ASTOR_PLS!D3,"-") -> 0.10799596 | F31: =IFERROR((ASTOR_CFS!F4+ASTOR_CFS!F14)/ASTOR_PLS!F3,"-") -> 0.057062484 | G31: =IFERROR((ASTOR_CFS!H4+ASTOR_CFS!H14)/ASTOR_PLS!H3,"-") -> 0.050116653 | H31: =IFERROR((ASTOR_CFS!I4+ASTOR_CFS!I14)/ASTOR_PLS!I3,"-") -> -0.13331571 | I31: =IFERROR((ASTOR_CFS!J4+ASTOR_CFS!J14)/ASTOR_PLS!J3,"-") -> -0.10482852
A32: HİSSE ANALİZİ / EQUITY METRICS
A33: Hisse Adedi (mn) (Shares Outstanding, mn) | B33: 998 mn (sabit) / Constant 998 mn | C33: — | D33: 998 | E33: 998 | F33: 998 | G33: 850 | H33: 850 | I33: 192.6
A34: Hisse Başına Kazanç - TL (EPS) | B34: Net Kar / Hisse Adedi | C34: — | D34: =IFERROR(ASTOR_PLS!B23/998000,"-") -> 7.6842786 | E34: =IFERROR(ASTOR_PLS!D23/998000,"-") -> 5.0349509 | F34: =IFERROR(ASTOR_PLS!F23/998000,"-") -> 4.6075411 | G34: =IFERROR(ASTOR_PLS!H23/850000,"-") -> 2.1494235 | H34: =IFERROR(ASTOR_PLS!I23/850000,"-") -> 0.60903647 | I34: =IFERROR(ASTOR_PLS!J23/192600,"-") -> 1.2015628
A35: Hisse Başına Defter Değeri - TL (BVPS) | B35: Özkaynak / Hisse Adedi | C35: — | D35: =IFERROR(ASTOR_BS!B50/998000,"-") -> 33.346827 | E35: =IFERROR(ASTOR_BS!D50/998000,"-") -> 20.86607 | F35: =IFERROR(ASTOR_BS!F50/998000,"-") -> 12.263341 | G35: =IFERROR(ASTOR_BS!H50/850000,"-") -> 3.8951365 | H35: =IFERROR(ASTOR_BS!I50/850000,"-") -> 1.2924412 | I35: =IFERROR(ASTOR_BS!J50/192600,"-") -> 2.9719159
A36: Hisse Başına Temettü - TL (DPS) | B36: |Ödenen Temettü| / Hisse Adedi | C36: — | D36: =IFERROR(ABS(ASTOR_CFS!B22)/998000,"-") -> 1.628523 | E36: =IFERROR(ABS(ASTOR_CFS!D22)/998000,"-") -> 1.8612966 | F36: =IFERROR(ABS(ASTOR_CFS!F22)/998000,"-") -> 0 | G36: =IFERROR(ABS(ASTOR_CFS!H22)/850000,"-") -> 0 | H36: =IFERROR(ABS(ASTOR_CFS!I22)/850000,"-") -> 0 | I36: =IFERROR(ABS(ASTOR_CFS!J22)/192600,"-") -> 0
A37: DEĞERLEME ÇARPANLARI / VALUATION MULTIPLES
A38: Dönem Sonu Hisse Fiyatı - TL (Year-end share price) | B38: BIST son işlem günü kapanış (Year-end close) | C38: N/A pre-2023 IPO | D38: 159.8 | E38: 117.9 | F38: 38.84 | G38: Halka arz öncesi | H38: Halka arz öncesi | I38: Halka arz öncesi | M38: 15/05/2026 hisse fiyati: 332.5
A39: Piyasa Değeri - Bin TL (Market Cap) | B39: Fiyat × Hisse Adedi | C39: — | D39: 114670200 | E39: =E38*998*1000 -> 1.176642e+08 | F39: =F38*998*1000 -> 38762320 | G39: N/A | H39: N/A | I39: N/A
A40: F/K (P/E - Price/Earnings) | B40: Piyasa Değeri (mn TL) / Net Kar (mn TL) | C40: 8–18x (enerji ekipman) | D40: =IFERROR(D39/(ASTOR_PLS!B23),"-") -> 14.952607 | E40: =IFERROR(E39/(ASTOR_PLS!D23),"-") -> 23.416316 | F40: =IFERROR(F39/(ASTOR_PLS!F23),"-") -> 8.429659 | G40: N/A | H40: N/A | I40: N/A
A41: PD/DD (P/B - Price/Book) | B41: Piyasa Değeri (mn TL) / Özkaynak (mn TL) | C41: 1.5–4.0x | D41: =IFERROR(D39/(ASTOR_BS!B50),"-") -> 3.4456052 | E41: =IFERROR(E39/(ASTOR_BS!D50),"-") -> 5.6503213 | F41: =IFERROR(F39/(ASTOR_BS!F50),"-") -> 3.1671631 | G41: N/A | H41: N/A | I41: N/A
A42: FD/FAVÖK (EV/EBITDA) | B42: (PD + Net Fin.Borç) / FAVÖK | C42: 5–12x | D42: =IFERROR((D39+(ASTOR_BS!B25+ASTOR_BS!B26+ASTOR_BS!B37-ASTOR_BS!B5-ASTOR_BS!B6-ASTOR_BS!B16))/ASTOR_PLS!B13,"-") -> 9.6694203 | E42: =IFERROR((E39+(ASTOR_BS!D25+ASTOR_BS!D26+ASTOR_BS!D37-ASTOR_BS!D5-ASTOR_BS!D6-ASTOR_BS!D16))/ASTOR_PLS!D13,"-") -> 14.842061 | F42: =IFERROR((F39+(ASTOR_BS!F25+ASTOR_BS!F26+ASTOR_BS!F37-ASTOR_BS!F5-ASTOR_BS!F6-ASTOR_BS!F16))/ASTOR_PLS!F13,"-") -> 6.2653204 | G42: N/A | H42: N/A | I42: N/A
A43: Temettü Verimi (Dividend Yield) | B43: DPS / Fiyat | C43: > %1 | D43: =IFERROR(ABS(ASTOR_CFS!B22)/998000/114.9,"-") -> 0.014173395 | E43: =IFERROR(ABS(ASTOR_CFS!D22)/998000/110,"-") -> 0.016920878 | F43: =IFERROR(ABS(ASTOR_CFS!F22)/998000/95,"-") -> 0 | G43: N/A | H43: N/A | I43: N/A

Sheet AKSEN_BS
A1: AKSA ENERJİ ÜRETİM A.Ş. (AKSEN) — KONSOLİDE BİLANÇO (Bin TL) | L1: DİKEY ANALİZ (% TOPLAM AKTİF)
A2: KALEM (BİN TL) | B2: 31.12.2025 (2025 SAG) | C2: 31.12.2024 (2025 SAG) | D2: 31.12.2024 (2024 SAG) | E2: 31.12.2023 (2024 SAG) | F2: 31.12.2023 (2023 SAG) | G2: 31.12.2022 (2023 SAG) | H2: 31.12.2022 (Nominal) | I2: 31.12.2021 (Nominal) | J2: 31.12.2020 (Nominal) | L2: 31.12.2025 (2025 SAG) | M2: 31.12.2024 (2025 SAG) | N2: 31.12.2024 (2024 SAG) | O2: 31.12.2023 (2024 SAG) | P2: 31.12.2023 (2023 SAG) | Q2: 31.12.2022 (2023 SAG) | R2: 31.12.2022 (Nominal) | S2: 31.12.2021 (Nominal) | T2: 31.12.2020 (Nominal)
A3: VARLIKLAR
A4: DÖNEN VARLIKLAR
A5: Nakit ve Nakit Benzerleri | B5: 6520056 | C5: 1380113 | D5: 1054407 | E5: 1147651 | F5: 794882 | G5: 1544463 | H5: 937345 | I5: 524702 | J5: 314172 | L5: =IFERROR(B5/B24,"") -> 0.050312779 | M5: =IFERROR(C5/C24,"") -> 0.012738449 | N5: =IFERROR(D5/D24,"") -> 0.012738452 | O5: =IFERROR(E5/E24,"") -> 0.014243598 | P5: =IFERROR(F5/F24,"") -> 0.014243594 | Q5: =IFERROR(G5/G24,"") -> 0.027977526 | R5: =IFERROR(H5/H24,"") -> 0.028205666 | S5: =IFERROR(I5/I24,"") -> 0.025409868 | T5: =IFERROR(J5/J24,"") -> 0.033061361
A6: Finansal Yatırımlar | B6: 0 | C6: 0 | D6: 0 | E6: 1265188 | F6: 876290 | G6: 504878 | H6: 306414 | I6: 592983 | J6: 0 | L6: =IFERROR(B6/B24,"") -> 0 | M6: =IFERROR(C6/C24,"") -> 0 | N6: =IFERROR(D6/D24,"") -> 0 | O6: =IFERROR(E6/E24,"") -> 0.01570236 | P6: =IFERROR(F6/F24,"") -> 0.015702355 | Q6: =IFERROR(G6/G24,"") -> 0.0091457272 | R6: =IFERROR(H6/H24,"") -> 0.0092203095 | S6: =IFERROR(I6/I24,"") -> 0.028716528 | T6: =IFERROR(J6/J24,"") -> 0
A7: Ticari Alacaklar (net) | B7: 7647990 | C7: 13062173 | D7: 9979504 | E7: 19534752 | F7: 13530095 | G7: 15187559 | H7: 9217430 | I7: 5327704 | J7: 2705620 | L7: =IFERROR(B7/B24,"") -> 0.059016615 | M7: =IFERROR(C7/C24,"") -> 0.12056391 | N7: =IFERROR(D7/D24,"") -> 0.12056391 | O7: =IFERROR(E7/E24,"") -> 0.24244754 | P7: =IFERROR(F7/F24,"") -> 0.24244753 | Q7: =IFERROR(G7/G24,"") -> 0.27511849 | R7: =IFERROR(H7/H24,"") -> 0.27736186 | S7: =IFERROR(I7/I24,"") -> 0.25800598 | T7: =IFERROR(J7/J24,"") -> 0.28472136
A8: Diğer Alacaklar | B8: 94286 | C8: 95876 | D8: 73249 | E8: 82452 | F8: 57107 | G8: 96076 | H8: 58309 | I8: 100823 | J8: 76414 | L8: =IFERROR(B8/B24,"") -> 0.00072756901 | M8: =IFERROR(C8/C24,"") -> 0.00088493588 | N8: =IFERROR(D8/D24,"") -> 0.00088493236 | O8: =IFERROR(E8/E24,"") -> 0.0010233191 | P8: =IFERROR(F8/F24,"") -> 0.0010233078 | Q8: =IFERROR(G8/G24,"") -> 0.0017403905 | R8: =IFERROR(H8/H24,"") -> 0.0017545772 | S8: =IFERROR(I8/I24,"") -> 0.0048825792 | T8: =IFERROR(J8/J24,"") -> 0.0080412986
A9: Türev Araçlar (varlık) | B9: 0 | C9: 6210 | D9: 4745 | E9: 37495 | F9: 25969 | G9: 37203 | H9: 22579 | I9: 3859 | J9: 2149 | L9: =IFERROR(B9/B24,"") -> 0 | M9: =IFERROR(C9/C24,"") -> 5.7318326e-05 | N9: =IFERROR(D9/D24,"") -> 5.732507e-05 | O9: =IFERROR(E9/E24,"") -> 0.00046535376 | P9: =IFERROR(F9/F24,"") -> 0.00046534189 | Q9: =IFERROR(G9/G24,"") -> 0.00067392219 | R9: =IFERROR(H9/H24,"") -> 0.00067942512 | S9: =IFERROR(I9/I24,"") -> 0.0001868807 | T9: =IFERROR(J9/J24,"") -> 0.0002261464
A10: Stoklar | B10: 2224109 | C10: 1803785 | D10: 1378092 | E10: 1293612 | F10: 895977 | G10: 320594 | H10: 244346 | I10: 225353 | J10: 138323 | L10: =IFERROR(B10/B24,"") -> 0.017162599 | M10: =IFERROR(C10/C24,"") -> 0.016648943 | N10: =IFERROR(D10/D24,"") -> 0.01664894 | O10: =IFERROR(E10/E24,"") -> 0.016055133 | P10: =IFERROR(F10/F24,"") -> 0.016055129 | Q10: =IFERROR(G10/G24,"") -> 0.0058074728 | R10: =IFERROR(H10/H24,"") -> 0.0073526201 | S10: =IFERROR(I10/I24,"") -> 0.010913223 | T10: =IFERROR(J10/J24,"") -> 0.014556188
A11: Peşin Ödenmiş Giderler | B11: 628400 | C11: 1131250 | D11: 864275 | E11: 617527 | F11: 427710 | G11: 543953 | H11: 282517 | I11: 145129 | J11: 116007 | L11: =IFERROR(B11/B24,"") -> 0.0048491225 | M11: =IFERROR(C11/C24,"") -> 0.010441442 | N11: =IFERROR(D11/D24,"") -> 0.010441438 | O11: =IFERROR(E11/E24,"") -> 0.0076641823 | P11: =IFERROR(F11/F24,"") -> 0.0076641912 | Q11: =IFERROR(G11/G24,"") -> 0.0098535602 | R11: =IFERROR(H11/H24,"") -> 0.0085012244 | S11: =IFERROR(I11/I24,"") -> 0.0070281963 | T11: =IFERROR(J11/J24,"") -> 0.012207801
A12: Cari Dönem Vergi Varlığı | B12: 327065 | C12: 51371 | D12: 39247 | E12: 34010 | F12: 23556 | G12: 244376 | H12: 148313 | I12: 991 | J12: 37623 | L12: =IFERROR(B12/B24,"") -> 0.0025238356 | M12: =IFERROR(C12/C24,"") -> 0.00047415454 | N12: =IFERROR(D12/D24,"") -> 0.000474149 | O12: =IFERROR(E12/E24,"") -> 0.00042210112 | P12: =IFERROR(F12/F24,"") -> 0.00042210303 | Q12: =IFERROR(G12/G24,"") -> 0.0044268046 | R12: =IFERROR(H12/H24,"") -> 0.0044628893 | S12: =IFERROR(I12/I24,"") -> 4.7991391e-05 | T12: =IFERROR(J12/J24,"") -> 0.003959193
A13: Diğer Dönen Varlıklar | B13: 2548952 | C13: 1859740 | D13: 1420842 | E13: 662779 | F13: 459052 | G13: 327645 | H13: 198850 | I13: 207556 | J13: 73475 | L13: =IFERROR(B13/B24,"") -> 0.019669288 | M13: =IFERROR(C13/C24,"") -> 0.017165408 | N13: =IFERROR(D13/D24,"") -> 0.017165409 | O13: =IFERROR(E13/E24,"") -> 0.0082258088 | P13: =IFERROR(F13/F24,"") -> 0.0082258126 | Q13: =IFERROR(G13/G24,"") -> 0.0059351998 | R13: =IFERROR(H13/H24,"") -> 0.0059835991 | S13: =IFERROR(I13/I24,"") -> 0.010051363 | T13: =IFERROR(J13/J24,"") -> 0.0077320179
A14: DÖNEN VARLIKLAR TOPLAM | B14: =SUM(B5:B13) -> 19990858 | C14: =SUM(C5:C13) -> 19390518 | D14: =SUM(D5:D13) -> 14814361 | E14: =SUM(E5:E13) -> 24675466 | F14: =SUM(F5:F13) -> 17090638 | G14: =SUM(G5:G13) -> 18806747 | H14: =SUM(H5:H13) -> 11416103 | I14: =SUM(I5:I13) -> 7129100 | J14: =SUM(J5:J13) -> 3463783 | L14: =IFERROR(B14/B24,"") -> 0.15426181 | M14: =IFERROR(C14/C24,"") -> 0.17897456 | N14: =IFERROR(D14/D24,"") -> 0.17897456 | O14: =IFERROR(E14/E24,"") -> 0.30624939 | P14: =IFERROR(F14/F24,"") -> 0.30624937 | Q14: =IFERROR(G14/G24,"") -> 0.34067909 | R14: =IFERROR(H14/H24,"") -> 0.34352217 | S14: =IFERROR(I14/I24,"") -> 0.34524261 | T14: =IFERROR(J14/J24,"") -> 0.36450537
A15: DURAN VARLIKLAR
A16: Finansal Yatırımlar (UV) | B16: 8000 | C16: 8000 | D16: 6112 | E16: 4469 | F16: 3095 | G16: 3095 | H16: 412 | I16: 412 | J16: 412 | L16: =IFERROR(B16/B24,"") -> 6.1732941e-05 | M16: =IFERROR(C16/C24,"") -> 7.3840033e-05 | N16: =IFERROR(D16/D24,"") -> 7.3840006e-05 | O16: =IFERROR(E16/E24,"") -> 5.5465155e-05 | P16: =IFERROR(F16/F24,"") -> 5.5459708e-05 | Q16: =IFERROR(G16/G24,"") -> 5.6065081e-05 | R16: =IFERROR(H16/H24,"") -> 1.23975e-05 | S16: =IFERROR(I16/I24,"") -> 1.9952021e-05 | T16: =IFERROR(J16/J24,"") -> 4.3356126e-05
A17: Diğer Alacaklar (UV) | B17: 13591 | C17: 13578 | D17: 10373 | E17: 9214 | F17: 6382 | G17: 22114 | H17: 13421 | I17: 12137 | J17: 6530 | L17: =IFERROR(B17/B24,"") -> 0.00010487655 | M17: =IFERROR(C17/C24,"") -> 0.000125325 | N17: =IFERROR(D17/D24,"") -> 0.0001253178 | O17: =IFERROR(E17/E24,"") -> 0.00011435577 | P17: =IFERROR(F17/F24,"") -> 0.00011435989 | Q17: =IFERROR(G17/G24,"") -> 0.00040058908 | R17: =IFERROR(H17/H24,"") -> 0.00040385157 | S17: =IFERROR(I17/I24,"") -> 0.00058776136 | T17: =IFERROR(J17/J24,"") -> 0.00068717355
A18: Maddi Duran Varlıklar | B18: 102179333 | C18: 80880023 | D18: 61792362 | E18: 50556985 | F18: 35016612 | G18: 35283432 | H18: 21295294 | I18: 13037533 | J18: 5655051 | L18: =IFERROR(B18/B24,"") -> 0.78847884 | M18: =IFERROR(C18/C24,"") -> 0.74652295 | N18: =IFERROR(D18/D24,"") -> 0.74652297 | O18: =IFERROR(E18/E24,"") -> 0.62746722 | P18: =IFERROR(F18/F24,"") -> 0.62746723 | Q18: =IFERROR(G18/G24,"") -> 0.63914974 | R18: =IFERROR(H18/H24,"") -> 0.6407971 | S18: =IFERROR(I18/I24,"") -> 0.63137169 | T18: =IFERROR(J18/J24,"") -> 0.59509977
A19: Kullanım Hakkı Varlıkları | B19: 426824 | C19: 332169 | D19: 253777 | E19: 420456 | F19: 291215 | G19: 223831 | H19: 98237 | I19: 64594 | J19: 73524 | L19: =IFERROR(B19/B24,"") -> 0.0032936376 | M19: =IFERROR(C19/C24,"") -> 0.0030659213 | N19: =IFERROR(D19/D24,"") -> 0.0030659187 | O19: =IFERROR(E19/E24,"") -> 0.0052183166 | P19: =IFERROR(F19/F24,"") -> 0.0052183195 | Q19: =IFERROR(G19/G24,"") -> 0.0040546375 | R19: =IFERROR(H19/H24,"") -> 0.0029560514 | S19: =IFERROR(I19/I24,"") -> 0.0031281089 | T19: =IFERROR(J19/J24,"") -> 0.0077371743
A20: Maddi Olmayan Duran Varlıklar | B20: 3453698 | C20: 2120568 | D20: 1620114 | E20: 1597614 | F20: 1106534 | G20: 740730 | H20: 345839 | I20: 222088 | J20: 115885 | L20: =IFERROR(B20/B24,"") -> 0.026650867 | M20: =IFERROR(C20/C24,"") -> 0.019572851 | N20: =IFERROR(D20/D24,"") -> 0.019572845 | O20: =IFERROR(E20/E24,"") -> 0.019828129 | P20: =IFERROR(F20/F24,"") -> 0.019828127 | Q20: =IFERROR(G20/G24,"") -> 0.013418122 | R20: =IFERROR(H20/H24,"") -> 0.010406648 | S20: =IFERROR(I20/I24,"") -> 0.010755108 | T20: =IFERROR(J20/J24,"") -> 0.012194963
A21: Peşin Ödenmiş Giderler (UV) | B21: 3212342 | C21: 4885269 | D21: 3732347 | E21: 2689942 | F21: 1863099 | G21: 34704 | H21: 21062 | I21: 153147 | J21: 2289 | L21: =IFERROR(B21/B24,"") -> 0.024788415 | M21: =IFERROR(C21/C24,"") -> 0.045091053 | N21: =IFERROR(D21/D24,"") -> 0.045091054 | O21: =IFERROR(E21/E24,"") -> 0.033385108 | P21: =IFERROR(F21/F24,"") -> 0.033385114 | Q21: =IFERROR(G21/G24,"") -> 0.00062865349 | R21: =IFERROR(H21/H24,"") -> 0.00063377704 | S21: =IFERROR(I21/I24,"") -> 0.0074164859 | T21: =IFERROR(J21/J24,"") -> 0.00024087906
A22: Ertelenmiş Vergi Varlığı | B22: 305810 | C22: 712188 | D22: 544112 | E22: 618964 | F22: 428705 | G22: 89049 | H22: 42139 | I22: 30526 | J22: 185220 | L22: =IFERROR(B22/B24,"") -> 0.0023598188 | M22: =IFERROR(C22/C24,"") -> 0.0065734982 | N22: =IFERROR(D22/D24,"") -> 0.0065735002 | O22: =IFERROR(E22/E24,"") -> 0.007682017 | P22: =IFERROR(F22/F24,"") -> 0.0076820207 | Q22: =IFERROR(G22/G24,"") -> 0.0016130983 | R22: =IFERROR(H22/H24,"") -> 0.0012680055 | S22: =IFERROR(I22/I24,"") -> 0.0014782898 | T22: =IFERROR(J22/J24,"") -> 0.019491315
A23: DURAN VARLIKLAR TOPLAM | B23: =SUM(B16:B22) -> 109599598 | C23: =SUM(C16:C22) -> 88951795 | D23: =SUM(D16:D22) -> 67959197 | E23: =SUM(E16:E22) -> 55897644 | F23: =SUM(F16:F22) -> 38715642 | G23: =SUM(G16:G22) -> 36396955 | H23: =SUM(H16:H22) -> 21816404 | I23: =SUM(I16:I22) -> 13520437 | J23: =SUM(J16:J22) -> 6038911 | L23: =IFERROR(B23/B24,"") -> 0.84573819 | M23: =IFERROR(C23/C24,"") -> 0.82102544 | N23: =IFERROR(D23/D24,"") -> 0.82102544 | O23: =IFERROR(E23/E24,"") -> 0.69375061 | P23: =IFERROR(F23/F24,"") -> 0.69375063 | Q23: =IFERROR(G23/G24,"") -> 0.65932091 | R23: =IFERROR(H23/H24,"") -> 0.65647783 | S23: =IFERROR(I23/I24,"") -> 0.65475739 | T23: =IFERROR(J23/J24,"") -> 0.63549463
A24: TOPLAM VARLIKLAR | B24: =B14+B23 -> 129590456 | C24: =C14+C23 -> 108342313 | D24: =D14+D23 -> 82773558 | E24: =E14+E23 -> 80573110 | F24: =F14+F23 -> 55806280 | G24: =G14+G23 -> 55203702 | H24: =H14+H23 -> 33232507 | I24: =I14+I23 -> 20649537 | J24: =J14+J23 -> 9502694 | L24: =IFERROR(B24/B24,"") -> 1 | M24: =IFERROR(C24/C24,"") -> 1 | N24: =IFERROR(D24/D24,"") -> 1 | O24: =IFERROR(E24/E24,"") -> 1 | P24: =IFERROR(F24/F24,"") -> 1 | Q24: =IFERROR(G24/G24,"") -> 1 | R24: =IFERROR(H24/H24,"") -> 1 | S24: =IFERROR(I24/I24,"") -> 1 | T24: =IFERROR(J24/J24,"") -> 1
A26: KAYNAKLAR
A27: KISA VADELİ YÜKÜMLÜLÜKLER
A28: Kısa Vadeli Borçlanmalar | B28: 6762388 | C28: 8700125 | D28: 6646898 | E28: 4269226 | F28: 2956937 | G28: 3943581 | H28: 2393385 | I28: 1923308 | J28: 728277 | L28: =IFERROR(B28/B24,"") -> 0.052182763 | M28: =IFERROR(C28/C24,"") -> 0.08030219 | N28: =IFERROR(D28/D24,"") -> 0.08030219 | O28: =IFERROR(E28/E24,"") -> 0.052985742 | P28: =IFERROR(F28/F24,"") -> 0.052985739 | Q28: =IFERROR(G28/G24,"") -> 0.071436894 | R28: =IFERROR(H28/H24,"") -> 0.072019394 | S28: =IFERROR(I28/I24,"") -> 0.09314049 | T28: =IFERROR(J28/J24,"") -> 0.076639004
A29: UV Borçlanmaların KV Kısımları | B29: 12854305 | C29: 8710253 | D29: 6654636 | E29: 7528107 | F29: 5214093 | G29: 3856471 | H29: 2340518 | I29: 1225737 | J29: 1292954 | L29: =IFERROR(B29/B24,"") -> 0.099191757 | M29: =IFERROR(C29/C24,"") -> 0.080395671 | N29: =IFERROR(D29/D24,"") -> 0.080395674 | O29: =IFERROR(E29/E24,"") -> 0.093432002 | P29: =IFERROR(F29/F24,"") -> 0.093432012 | Q29: =IFERROR(G29/G24,"") -> 0.06985892 | R29: =IFERROR(H29/H24,"") -> 0.070428572 | S29: =IFERROR(I29/I24,"") -> 0.059359055 | T29: =IFERROR(J29/J24,"") -> 0.13606184
A30: KV Kiralama İşl. Borçları | B30: 68646 | C30: 6981 | D30: 5333 | E30: 5321 | F30: 3685 | G30: 4507 | H30: 2736 | I30: 7581 | J30: 831 | L30: =IFERROR(B30/B24,"") -> 0.00052971494 | M30: =IFERROR(C30/C24,"") -> 6.4434659e-05 | N30: =IFERROR(D30/D24,"") -> 6.4428788e-05 | O30: =IFERROR(E30/E24,"") -> 6.6039402e-05 | P30: =IFERROR(F30/F24,"") -> 6.6031995e-05 | Q30: =IFERROR(G30/G24,"") -> 8.1643075e-05 | R30: =IFERROR(H30/H24,"") -> 8.2329028e-05 | S30: =IFERROR(I30/I24,"") -> 0.00036712688 | T30: =IFERROR(J30/J24,"") -> 8.7448886e-05
A31: UV Kiralama İşl. KV Kısımları | B31: 79291 | C31: 36619 | D31: 27977 | E31: 48033 | F31: 33269 | G31: 10674 | H31: 6478 | I31: 2798 | J31: 3396 | L31: =IFERROR(B31/B24,"") -> 0.00061185833 | M31: =IFERROR(C31/C24,"") -> 0.00033799352 | N31: =IFERROR(D31/D24,"") -> 0.00033799441 | O31: =IFERROR(E31/E24,"") -> 0.00059614181 | P31: =IFERROR(F31/F24,"") -> 0.00059615154 | Q31: =IFERROR(G31/G24,"") -> 0.0001933566 | R31: =IFERROR(H31/H24,"") -> 0.00019492962 | S31: =IFERROR(I31/I24,"") -> 0.00013549941 | T31: =IFERROR(J31/J24,"") -> 0.00035737234
A32: Ticari Borçlar | B32: 4363435 | C32: 8153947 | D32: 6229618 | E32: 4822815 | F32: 3340362 | G32: 3511100 | H32: 2126648 | I32: 2019866 | J32: 779913 | L32: =IFERROR(B32/B24,"") -> 0.03367096 | M32: =IFERROR(C32/C24,"") -> 0.075260965 | N32: =IFERROR(D32/D24,"") -> 0.075260967 | O32: =IFERROR(E32/E24,"") -> 0.059856384 | P32: =IFERROR(F32/F24,"") -> 0.059856382 | Q32: =IFERROR(G32/G24,"") -> 0.063602619 | R32: =IFERROR(H32/H24,"") -> 0.063993005 | S32: =IFERROR(I32/I24,"") -> 0.097816527 | T32: =IFERROR(J32/J24,"") -> 0.082072831
A33: Çalışanlara Sağlanan Faydalar | B33: 94841 | C33: 108055 | D33: 82554 | E33: 98485 | F33: 68212 | G33: 38748 | H33: 23517 | I33: 18189 | J33: 8597 | L33: =IFERROR(B33/B24,"") -> 0.00073185173 | M33: =IFERROR(C33/C24,"") -> 0.0009973481 | N33: =IFERROR(D33/D24,"") -> 0.00099734749 | O33: =IFERROR(E33/E24,"") -> 0.0012223061 | P33: =IFERROR(F33/F24,"") -> 0.0012222997 | Q33: =IFERROR(G33/G24,"") -> 0.00070190945 | R33: =IFERROR(H33/H24,"") -> 0.00070765049 | S33: =IFERROR(I33/I24,"") -> 0.00088084299 | T33: =IFERROR(J33/J24,"") -> 0.00090469082
A34: Diğer Borçlar | B34: 494276 | C34: 488799 | D34: 373443 | E34: 1028337 | F34: 712243 | G34: 779420 | H34: 473035 | I34: 351951 | J34: 197360 | L34: =IFERROR(B34/B24,"") -> 0.0038141389 | M34: =IFERROR(C34/C24,"") -> 0.0045116168 | N34: =IFERROR(D34/D24,"") -> 0.0045116219 | O34: =IFERROR(E34/E24,"") -> 0.012762782 | P34: =IFERROR(F34/F24,"") -> 0.012762775 | Q34: =IFERROR(G34/G24,"") -> 0.014118981 | R34: =IFERROR(H34/H24,"") -> 0.014234105 | S34: =IFERROR(I34/I24,"") -> 0.017044014 | T34: =IFERROR(J34/J24,"") -> 0.020768847
A35: Türev Araçlar (yükümlülük) | B35: 52398 | C35: 49699 | D35: 37970 | E35: 0 | F35: 0 | G35: 0 | H35: 0 | I35: 83074 | J35: 60716 | L35: =IFERROR(B35/B24,"") -> 0.00040433533 | M35: =IFERROR(C35/C24,"") -> 0.00045872198 | N35: =IFERROR(D35/D24,"") -> 0.00045872137 | O35: =IFERROR(E35/E24,"") -> 0 | P35: =IFERROR(F35/F24,"") -> 0 | Q35: =IFERROR(G35/G24,"") -> 0 | R35: =IFERROR(H35/H24,"") -> 0 | S35: =IFERROR(I35/I24,"") -> 0.0040230442 | T35: =IFERROR(J35/J24,"") -> 0.006389346
A36: Dönem Karı Vergi Yükümlülüğü | B36: 1024914 | C36: 1361145 | D36: 1039915 | E36: 1967895 | F36: 1362997 | G36: 943654 | H36: 572710 | I36: 626693 | J36: 183176 | L36: =IFERROR(B36/B24,"") -> 0.0079088695 | M36: =IFERROR(C36/C24,"") -> 0.012563374 | N36: =IFERROR(D36/D24,"") -> 0.012563372 | O36: =IFERROR(E36/E24,"") -> 0.024423719 | P36: =IFERROR(F36/F24,"") -> 0.024423721 | Q36: =IFERROR(G36/G24,"") -> 0.017094035 | R36: =IFERROR(H36/H24,"") -> 0.017233427 | S36: =IFERROR(I36/I24,"") -> 0.03034901 | T36: =IFERROR(J36/J24,"") -> 0.019276218
A37: KV Karşılıklar | B37: 282112 | C37: 226362 | D37: 172941 | E37: 57882 | F37: 40090 | G37: 39400 | H37: 23912 | I37: 11369 | J37: 23856 | L37: =IFERROR(B37/B24,"") -> 0.0021769504 | M37: =IFERROR(C37/C24,"") -> 0.0020893222 | N37: =IFERROR(D37/D24,"") -> 0.0020893266 | O37: =IFERROR(E37/E24,"") -> 0.00071837863 | P37: =IFERROR(F37/F24,"") -> 0.00071837793 | Q37: =IFERROR(G37/G24,"") -> 0.00071372025 | R37: =IFERROR(H37/H24,"") -> 0.00071953645 | S37: =IFERROR(I37/I24,"") -> 0.00055056925 | T37: =IFERROR(J37/J24,"") -> 0.002510446
A38: Diğer KV Yükümlülükler | B38: 161375 | C38: 580263 | D38: 443321 | E38: 49444 | F38: 34245 | G38: 28097 | H38: 17053 | I38: 1305 | J38: 18588 | L38: =IFERROR(B38/B24,"") -> 0.0012452692 | M38: =IFERROR(C38/C24,"") -> 0.0053558299 | N38: =IFERROR(D38/D24,"") -> 0.0053558287 | O38: =IFERROR(E38/E24,"") -> 0.00061365386 | P38: =IFERROR(F38/F24,"") -> 0.00061364062 | Q38: =IFERROR(G38/G24,"") -> 0.00050896949 | R38: =IFERROR(H38/H24,"") -> 0.00051314215 | S38: =IFERROR(I38/I24,"") -> 6.3197543e-05 | T38: =IFERROR(J38/J24,"") -> 0.0019560769
A39: KISA VADELİ YÜKÜMLÜLÜKLER TOPLAM | B39: =SUM(B28:B38) -> 26237981 | C39: =SUM(C28:C38) -> 28422248 | D39: =SUM(D28:D38) -> 21714606 | E39: =SUM(E28:E38) -> 19875545 | F39: =SUM(F28:F38) -> 13766133 | G39: =SUM(G28:G38) -> 13155652 | H39: =SUM(H28:H38) -> 7979992 | I39: =SUM(I28:I38) -> 6271871 | J39: =SUM(J28:J38) -> 3297664 | L39: =IFERROR(B39/B24,"") -> 0.20246847 | M39: =IFERROR(C39/C24,"") -> 0.26233747 | N39: =IFERROR(D39/D24,"") -> 0.26233747 | O39: =IFERROR(E39/E24,"") -> 0.24667715 | P39: =IFERROR(F39/F24,"") -> 0.24667713 | Q39: =IFERROR(G39/G24,"") -> 0.23831105 | R39: =IFERROR(H39/H24,"") -> 0.24012609 | S39: =IFERROR(I39/I24,"") -> 0.30372938 | T39: =IFERROR(J39/J24,"") -> 0.34702412
A40: UZUN VADELİ YÜKÜMLÜLÜKLER
A41: Uzun Vadeli Borçlanmalar | B41: 34450834 | C41: 19182193 | D41: 14655202 | E41: 7331121 | F41: 5077657 | G41: 6237182 | H41: 3785387 | I41: 2435863 | J41: 834710 | L41: =IFERROR(B41/B24,"") -> 0.26584391 | M41: =IFERROR(C41/C24,"") -> 0.17705172 | N41: =IFERROR(D41/D24,"") -> 0.17705173 | O41: =IFERROR(E41/E24,"") -> 0.090987192 | P41: =IFERROR(F41/F24,"") -> 0.090987197 | Q41: =IFERROR(G41/G24,"") -> 0.11298485 | R41: =IFERROR(H41/H24,"") -> 0.11390615 | S41: =IFERROR(I41/I24,"") -> 0.11796211 | T41: =IFERROR(J41/J24,"") -> 0.087839301
A42: UV Kiralama İşl. Borçları | B42: 208363 | C42: 231702 | D42: 177020 | E42: 223007 | F42: 154458 | G42: 131762 | H42: 79967 | I42: 67438 | J42: 74975 | L42: =IFERROR(B42/B24,"") -> 0.0016078576 | M42: =IFERROR(C42/C24,"") -> 0.0021386104 | N42: =IFERROR(D42/D24,"") -> 0.0021386057 | O42: =IFERROR(E42/E24,"") -> 0.0027677596 | P42: =IFERROR(F42/F24,"") -> 0.002767753 | Q42: =IFERROR(G42/G24,"") -> 0.0023868327 | R42: =IFERROR(H42/H24,"") -> 0.0024062885 | S42: =IFERROR(I42/I24,"") -> 0.0032658359 | T42: =IFERROR(J42/J24,"") -> 0.0078898679
A43: Uzun Vadeli Karşılıklar | B43: 195659 | C43: 228012 | D43: 174201 | E43: 1640421 | F43: 1136183 | G43: 1108992 | H43: 673054 | I43: 427117 | J43: 81568 | L43: =IFERROR(B43/B24,"") -> 0.0015098257 | M43: =IFERROR(C43/C24,"") -> 0.0021045517 | N43: =IFERROR(D43/D24,"") -> 0.0021045489 | O43: =IFERROR(E43/E24,"") -> 0.02035941 | P43: =IFERROR(F43/F24,"") -> 0.020359411 | Q43: =IFERROR(G43/G24,"") -> 0.020089088 | R43: =IFERROR(H43/H24,"") -> 0.020252881 | S43: =IFERROR(I43/I24,"") -> 0.020684096 | T43: =IFERROR(J43/J24,"") -> 0.0085836711
A44: Ertelenmiş Vergi Yükümlülüğü | B44: 3366765 | C44: 1990982 | D44: 1521111 | E44: 1496079 | F44: 1036209 | G44: 2155904 | H44: 1755544 | I44: 863042 | J44: 588434 | L44: =IFERROR(B44/B24,"") -> 0.025980038 | M44: =IFERROR(C44/C24,"") -> 0.018376772 | N44: =IFERROR(D44/D24,"") -> 0.018376774 | O44: =IFERROR(E44/E24,"") -> 0.018567969 | P44: =IFERROR(F44/F24,"") -> 0.018567964 | Q44: =IFERROR(G44/G24,"") -> 0.039053613 | R44: =IFERROR(H44/H24,"") -> 0.052826108 | S44: =IFERROR(I44/I24,"") -> 0.041794739 | T44: =IFERROR(J44/J24,"") -> 0.061922861
A45: UZUN VADELİ YÜKÜMLÜLÜKLER TOPLAM | B45: =SUM(B41:B44) -> 38221621 | C45: =SUM(C41:C44) -> 21632889 | D45: =SUM(D41:D44) -> 16527534 | E45: =SUM(E41:E44) -> 10690628 | F45: =SUM(F41:F44) -> 7404507 | G45: =SUM(G41:G44) -> 9633840 | H45: =SUM(H41:H44) -> 6293952 | I45: =SUM(I41:I44) -> 3793460 | J45: =SUM(J41:J44) -> 1579687 | L45: =IFERROR(B45/B24,"") -> 0.29494164 | M45: =IFERROR(C45/C24,"") -> 0.19967166 | N45: =IFERROR(D45/D24,"") -> 0.19967166 | O45: =IFERROR(E45/E24,"") -> 0.13268233 | P45: =IFERROR(F45/F24,"") -> 0.13268233 | Q45: =IFERROR(G45/G24,"") -> 0.17451438 | R45: =IFERROR(H45/H24,"") -> 0.18939143 | S45: =IFERROR(I45/I24,"") -> 0.18370678 | T45: =IFERROR(J45/J24,"") -> 0.1662357
A46: TOPLAM YÜKÜMLÜLÜKLER | B46: =B39+B45 -> 64459602 | C46: =C39+C45 -> 50055137 | D46: =D39+D45 -> 38242140 | E46: =E39+E45 -> 30566173 | F46: =F39+F45 -> 21170640 | G46: =G39+G45 -> 22789492 | H46: =H39+H45 -> 14273944 | I46: =I39+I45 -> 10065331 | J46: =J39+J45 -> 4877351 | L46: =IFERROR(B46/B24,"") -> 0.4974101 | M46: =IFERROR(C46/C24,"") -> 0.46200912 | N46: =IFERROR(D46/D24,"") -> 0.46200914 | O46: =IFERROR(E46/E24,"") -> 0.37935948 | P46: =IFERROR(F46/F24,"") -> 0.37935946 | Q46: =IFERROR(G46/G24,"") -> 0.41282543 | R46: =IFERROR(H46/H24,"") -> 0.42951752 | S46: =IFERROR(I46/I24,"") -> 0.48743616 | T46: =IFERROR(J46/J24,"") -> 0.51325982
A48: ÖZKAYNAKLAR
A49: Ödenmiş Sermaye | B49: 1226338 | C49: 1226338 | D49: 1226338 | E49: 1226338 | F49: 1226338 | G49: 1226338 | H49: 1226338 | I49: 1226338 | J49: 613169 | L49: =IFERROR(B49/B24,"") -> 0.0094631815 | M49: =IFERROR(C49/C24,"") -> 0.011319105 | N49: =IFERROR(D49/D24,"") -> 0.014815577 | O49: =IFERROR(E49/E24,"") -> 0.015220189 | P49: =IFERROR(F49/F24,"") -> 0.02197491 | Q49: =IFERROR(G49/G24,"") -> 0.022214778 | R49: =IFERROR(H49/H24,"") -> 0.03690176 | S49: =IFERROR(I49/I24,"") -> 0.05938816 | T49: =IFERROR(J49/J24,"") -> 0.064525807
A50: Sermaye Düzeltme Farkları | B50: 17396662 | C50: 17396662 | D50: 13001640 | E50: 13001640 | F50: 8628197 | G50: 8628197 | H50: 10727 | I50: 10727 | J50: 247404 | L50: =IFERROR(B50/B24,"") -> 0.13424339 | M50: =IFERROR(C50/C24,"") -> 0.16057126 | N50: =IFERROR(D50/D24,"") -> 0.1570748 | O50: =IFERROR(E50/E24,"") -> 0.1613645 | P50: =IFERROR(F50/F24,"") -> 0.15460979 | Q50: =IFERROR(G50/G24,"") -> 0.15629743 | R50: =IFERROR(H50/H24,"") -> 0.00032278636 | S50: =IFERROR(I50/I24,"") -> 0.00051947896 | T50: =IFERROR(J50/J24,"") -> 0.026035143
A51: Geri Alınmış Paylar (-) | B51: -81136 | C51: -81136 | D51: -61988 | E51: -61988 | F51: -42934 | G51: 0 | H51: 0 | I51: 0 | J51: 0 | L51: =IFERROR(B51/B24,"") -> -0.00062609549 | M51: =IFERROR(C51/C24,"") -> -0.00074888562 | N51: =IFERROR(D51/D24,"") -> -0.0007488865 | O51: =IFERROR(E51/E24,"") -> -0.00076933855 | P51: =IFERROR(F51/F24,"") -> -0.00076933994 | Q51: =IFERROR(G51/G24,"") -> 0 | R51: =IFERROR(H51/H24,"") -> 0 | S51: =IFERROR(I51/I24,"") -> 0 | T51: =IFERROR(J51/J24,"") -> 0
A52: Yeniden Değerleme Artışları | B52: 9727908 | C52: 6275752 | D52: 4794677 | E52: 4804145 | F52: 3327431 | G52: 3207688 | H52: 6142637 | I52: 3740068 | J52: 2196268 | L52: =IFERROR(B52/B24,"") -> 0.075066547 | M52: =IFERROR(C52/C24,"") -> 0.057925217 | N52: =IFERROR(D52/D24,"") -> 0.057925225 | O52: =IFERROR(E52/E24,"") -> 0.059624669 | P52: =IFERROR(F52/F24,"") -> 0.059624669 | Q52: =IFERROR(G52/G24,"") -> 0.058106393 | R52: =IFERROR(H52/H24,"") -> 0.18483821 | S52: =IFERROR(I52/I24,"") -> 0.18112116 | T52: =IFERROR(J52/J24,"") -> 0.23112056
A53: Yabancı Para Çevrim Farkları | B53: -10978487 | C53: -8773326 | D53: -6702823 | E53: 485705 | F53: 336407 | G53: 3078065 | H53: 3960108 | I53: 2514679 | J53: 520340 | L53: =IFERROR(B53/B24,"") -> -0.084716787 | M53: =IFERROR(C53/C24,"") -> -0.080977836 | N53: =IFERROR(D53/D24,"") -> -0.080977829 | O53: =IFERROR(E53/E24,"") -> 0.0060281277 | P53: =IFERROR(F53/F24,"") -> 0.0060281208 | Q53: =IFERROR(G53/G24,"") -> 0.055758308 | R53: =IFERROR(H53/H24,"") -> 0.11916369 | S53: =IFERROR(I53/I24,"") -> 0.12177895 | T53: =IFERROR(J53/J24,"") -> 0.054757104
A54: Riskten Korunma Kayıpları | B54: 0 | C54: -1053662 | D54: -804998 | E54: -2059722 | F54: -1426598 | G54: -2021934 | H54: -911613 | I54: -535290 | J54: -26366 | L54: =IFERROR(B54/B24,"") -> 0 | M54: =IFERROR(C54/C24,"") -> -0.0097253046 | N54: =IFERROR(D54/D24,"") -> -0.0097253038 | O54: =IFERROR(E54/E24,"") -> -0.025563392 | P54: =IFERROR(F54/F24,"") -> -0.025563395 | Q54: =IFERROR(G54/G24,"") -> -0.036626783 | R54: =IFERROR(H54/H24,"") -> -0.027431364 | S54: =IFERROR(I54/I24,"") -> -0.025922615 | T54: =IFERROR(J54/J24,"") -> -0.0027745816
A55: Kısıtlanmış Yedekler | B55: 3626538 | C55: 3626538 | D55: 2770676 | E55: 1882876 | F55: 1304112 | G55: 1003991 | H55: 332248 | I55: 82932 | J55: 68743 | L55: =IFERROR(B55/B24,"") -> 0.027984607 | M55: =IFERROR(C55/C24,"") -> 0.033472961 | N55: =IFERROR(D55/D24,"") -> 0.03347296 | O55: =IFERROR(E55/E24,"") -> 0.023368541 | P55: =IFERROR(F55/F24,"") -> 0.023368553 | Q55: =IFERROR(G55/G24,"") -> 0.018187023 | R55: =IFERROR(H55/H24,"") -> 0.0099976809 | S55: =IFERROR(I55/I24,"") -> 0.0040161675 | T55: =IFERROR(J55/J24,"") -> 0.0072340538
A56: Geçmiş Yıllar Karları | B56: 34989567 | C56: 31956801 | D56: 24415006 | E56: 18595556 | F56: 12879593 | G56: 8826027 | H56: 1886123 | I56: 932614 | J56: 129592 | L56: =IFERROR(B56/B24,"") -> 0.27000111 | M56: =IFERROR(C56/C24,"") -> 0.29496141 | N56: =IFERROR(D56/D24,"") -> 0.29496142 | O56: =IFERROR(E56/E24,"") -> 0.23079109 | P56: =IFERROR(F56/F24,"") -> 0.2307911 | Q56: =IFERROR(G56/G24,"") -> 0.15988107 | R56: =IFERROR(H56/H24,"") -> 0.056755363 | S56: =IFERROR(I56/I24,"") -> 0.045163918 | T56: =IFERROR(J56/J24,"") -> 0.013637396
A57: Net Dönem Karı | B57: 3652368 | C57: 2627314 | D57: 2007269 | E57: 7935940 | F57: 5496565 | G57: 5581566 | H57: 4561511 | I57: 1679750 | J57: 470036 | L57: =IFERROR(B57/B24,"") -> 0.028183927 | M57: =IFERROR(C57/C24,"") -> 0.024250119 | N57: =IFERROR(D57/D24,"") -> 0.024250123 | O57: =IFERROR(E57/E24,"") -> 0.098493654 | P57: =IFERROR(F57/F24,"") -> 0.098493664 | Q57: =IFERROR(G57/G24,"") -> 0.10110855 | R57: =IFERROR(H57/H24,"") -> 0.13726051 | S57: =IFERROR(I57/I24,"") -> 0.08134565 | T57: =IFERROR(J57/J24,"") -> 0.049463447
A58: Ana Ortaklığa Ait Özkaynaklar | B58: =SUM(B49:B57) -> 59559758 | C58: =SUM(C49:C57) -> 53201281 | D58: =SUM(D49:D57) -> 40645797 | E58: =SUM(E49:E57) -> 45810490 | F58: =SUM(F49:F57) -> 31729111 | G58: =SUM(G49:G57) -> 29529938 | H58: =SUM(H49:H57) -> 17208079 | I58: =SUM(I49:I57) -> 9651818 | J58: =SUM(J49:J57) -> 4219186 | L58: =IFERROR(B58/B24,"") -> 0.45959988 | M58: =IFERROR(C58/C24,"") -> 0.49104805 | N58: =IFERROR(D58/D24,"") -> 0.49104808 | O58: =IFERROR(E58/E24,"") -> 0.56855805 | P58: =IFERROR(F58/F24,"") -> 0.56855807 | Q58: =IFERROR(G58/G24,"") -> 0.53492677 | R58: =IFERROR(H58/H24,"") -> 0.51780863 | S58: =IFERROR(I58/I24,"") -> 0.46741087 | T58: =IFERROR(J58/J24,"") -> 0.44399893
A59: Kontrol Gücü Olmayan Paylar | B59: 5571092 | C59: 5085891 | D59: 3885622 | E59: 4196447 | F59: 2906530 | G59: 2884272 | H59: 1750483 | I59: 932390 | J59: 406159 | L59: =IFERROR(B59/B24,"") -> 0.042989987 | M59: =IFERROR(C59/C24,"") -> 0.046942795 | N59: =IFERROR(D59/D24,"") -> 0.046942793 | O59: =IFERROR(E59/E24,"") -> 0.052082475 | P59: =IFERROR(F59/F24,"") -> 0.05208249 | Q59: =IFERROR(G59/G24,"") -> 0.0522478 | R59: =IFERROR(H59/H24,"") -> 0.052673817 | S59: =IFERROR(I59/I24,"") -> 0.045153071 | T59: =IFERROR(J59/J24,"") -> 0.042741458
A60: ÖZKAYNAKLAR TOPLAM | B60: =B58+B59 -> 65130850 | C60: =C58+C59 -> 58287172 | D60: =D58+D59 -> 44531419 | E60: =E58+E59 -> 50006937 | F60: =F58+F59 -> 34635641 | G60: =G58+G59 -> 32414210 | H60: =H58+H59 -> 18958562 | I60: =I58+I59 -> 10584208 | J60: =J58+J59 -> 4625345 | L60: =IFERROR(B60/B24,"") -> 0.50258987 | M60: =IFERROR(C60/C24,"") -> 0.53799084 | N60: =IFERROR(D60/D24,"") -> 0.53799088 | O60: =IFERROR(E60/E24,"") -> 0.62064052 | P60: =IFERROR(F60/F24,"") -> 0.62064056 | Q60: =IFERROR(G60/G24,"") -> 0.58717457 | R60: =IFERROR(H60/H24,"") -> 0.57048245 | S60: =IFERROR(I60/I24,"") -> 0.51256394 | T60: =IFERROR(J60/J24,"") -> 0.48674039
A61: TOPLAM YÜKÜMLÜLÜKLER VE ÖZKAYNAKLAR | B61: =B46+B60 -> 129590452 | C61: =C46+C60 -> 108342309 | D61: =D46+D60 -> 82773559 | E61: =E46+E60 -> 80573110 | F61: =F46+F60 -> 55806281 | G61: =G46+G60 -> 55203702 | H61: =H46+H60 -> 33232506 | I61: =I46+I60 -> 20649539 | J61: =J46+J60 -> 9502696 | L61: =IFERROR(B61/B24,"") -> 0.99999997 | M61: =IFERROR(C61/C24,"") -> 0.99999996 | N61: =IFERROR(D61/D24,"") -> 1 | O61: =IFERROR(E61/E24,"") -> 1 | P61: =IFERROR(F61/F24,"") -> 1 | Q61: =IFERROR(G61/G24,"") -> 1 | R61: =IFERROR(H61/H24,"") -> 0.99999997 | S61: =IFERROR(I61/I24,"") -> 1.0000001 | T61: =IFERROR(J61/J24,"") -> 1.0000002
L64: YATAY ANALİZ (YoY % Değişim — Aynı Satın Alma Gücü)
L65: 2025/2024 | M65: 2024/2023 | N65: 2023/2022 | O65: 2022/2021 | P65: 2021/2020
K66: Nakit ve Nakit Benzerleri | L66: =IFERROR((B5-C5)/ABS(C5),"-") -> 3.7242914 | M66: =IFERROR((D5-E5)/ABS(E5),"-") -> -0.081247696 | N66: =IFERROR((F5-G5)/ABS(G5),"-") -> -0.48533438 | O66: =IFERROR((H5-I5)/ABS(I5),"-") -> 0.78643306 | P66: =IFERROR((I5-J5)/ABS(J5),"-") -> 0.67011064
K67: Finansal Yatırımlar | L67: =IFERROR((B6-C6)/ABS(C6),"-") -> - | M67: =IFERROR((D6-E6)/ABS(E6),"-") -> -1 | N67: =IFERROR((F6-G6)/ABS(G6),"-") -> 0.73564703 | O67: =IFERROR((H6-I6)/ABS(I6),"-") -> -0.48326681 | P67: =IFERROR((I6-J6)/ABS(J6),"-") -> -
K68: Ticari Alacaklar (net) | L68: =IFERROR((B7-C7)/ABS(C7),"-") -> -0.41449329 | M68: =IFERROR((D7-E7)/ABS(E7),"-") -> -0.48914099 | N68: =IFERROR((F7-G7)/ABS(G7),"-") -> -0.10913301 | O68: =IFERROR((H7-I7)/ABS(I7),"-") -> 0.73009424 | P68: =IFERROR((I7-J7)/ABS(J7),"-") -> 0.96912501
K69: Diğer Alacaklar | L69: =IFERROR((B8-C8)/ABS(C8),"-") -> -0.016583921 | M69: =IFERROR((D8-E8)/ABS(E8),"-") -> -0.11161646 | N69: =IFERROR((F8-G8)/ABS(G8),"-") -> -0.40560598 | O69: =IFERROR((H8-I8)/ABS(I8),"-") -> -0.42166966 | P69: =IFERROR((I8-J8)/ABS(J8),"-") -> 0.31943099
K70: Türev Araçlar (varlık) | L70: =IFERROR((B9-C9)/ABS(C9),"-") -> -1 | M70: =IFERROR((D9-E9)/ABS(E9),"-") -> -0.87344979 | N70: =IFERROR((F9-G9)/ABS(G9),"-") -> -0.3019649 | O70: =IFERROR((H9-I9)/ABS(I9),"-") -> 4.8509977 | P70: =IFERROR((I9-J9)/ABS(J9),"-") -> 0.79571894
K71: Stoklar | L71: =IFERROR((B10-C10)/ABS(C10),"-") -> 0.23302334 | M71: =IFERROR((D10-E10)/ABS(E10),"-") -> 0.065305517 | N71: =IFERROR((F10-G10)/ABS(G10),"-") -> 1.7947404 | O71: =IFERROR((H10-I10)/ABS(I10),"-") -> 0.084281106 | P71: =IFERROR((I10-J10)/ABS(J10),"-") -> 0.62917953
K72: Peşin Ödenmiş Giderler | L72: =IFERROR((B11-C11)/ABS(C11),"-") -> -0.44450829 | M72: =IFERROR((D11-E11)/ABS(E11),"-") -> 0.39957443 | N72: =IFERROR((F11-G11)/ABS(G11),"-") -> -0.21370045 | O72: =IFERROR((H11-I11)/ABS(I11),"-") -> 0.94666125 | P72: =IFERROR((I11-J11)/ABS(J11),"-") -> 0.25103658
K73: Cari Dönem Vergi Varlığı | L73: =IFERROR((B12-C12)/ABS(C12),"-") -> 5.3667244 | M73: =IFERROR((D12-E12)/ABS(E12),"-") -> 0.15398412 | N73: =IFERROR((F12-G12)/ABS(G12),"-") -> -0.90360756 | O73: =IFERROR((H12-I12)/ABS(I12),"-") -> 148.65994 | P73: =IFERROR((I12-J12)/ABS(J12),"-") -> -0.97365973
K74: Diğer Dönen Varlıklar | L74: =IFERROR((B13-C13)/ABS(C13),"-") -> 0.37059589 | M74: =IFERROR((D13-E13)/ABS(E13),"-") -> 1.1437644 | N74: =IFERROR((F13-G13)/ABS(G13),"-") -> 0.40106518 | O74: =IFERROR((H13-I13)/ABS(I13),"-") -> -0.041945306 | P74: =IFERROR((I13-J13)/ABS(J13),"-") -> 1.824852
K75: DÖNEN VARLIKLAR TOPLAM | L75: =IFERROR((B14-C14)/ABS(C14),"-") -> 0.030960493 | M75: =IFERROR((D14-E14)/ABS(E14),"-") -> -0.39963197 | N75: =IFERROR((F14-G14)/ABS(G14),"-") -> -0.091249646 | O75: =IFERROR((H14-I14)/ABS(I14),"-") -> 0.6013386 | P75: =IFERROR((I14-J14)/ABS(J14),"-") -> 1.0581832
K76: Finansal Yatırımlar (UV) | L76: =IFERROR((B16-C16)/ABS(C16),"-") -> 0 | M76: =IFERROR((D16-E16)/ABS(E16),"-") -> 0.36764377 | N76: =IFERROR((F16-G16)/ABS(G16),"-") -> 0 | O76: =IFERROR((H16-I16)/ABS(I16),"-") -> 0 | P76: =IFERROR((I16-J16)/ABS(J16),"-") -> 0
K77: Diğer Alacaklar (UV) | L77: =IFERROR((B17-C17)/ABS(C17),"-") -> 0.00095743114 | M77: =IFERROR((D17-E17)/ABS(E17),"-") -> 0.12578685 | N77: =IFERROR((F17-G17)/ABS(G17),"-") -> -0.71140454 | O77: =IFERROR((H17-I17)/ABS(I17),"-") -> 0.10579221 | P77: =IFERROR((I17-J17)/ABS(J17),"-") -> 0.85865237
K78: Maddi Duran Varlıklar | L78: =IFERROR((B18-C18)/ABS(C18),"-") -> 0.26334451 | M78: =IFERROR((D18-E18)/ABS(E18),"-") -> 0.22223194 | N78: =IFERROR((F18-G18)/ABS(G18),"-") -> -0.0075621895 | O78: =IFERROR((H18-I18)/ABS(I18),"-") -> 0.63338371 | P78: =IFERROR((I18-J18)/ABS(J18),"-") -> 1.3054669
K79: Kullanım Hakkı Varlıkları | L79: =IFERROR((B19-C19)/ABS(C19),"-") -> 0.28496037 | M79: =IFERROR((D19-E19)/ABS(E19),"-") -> -0.39642436 | N79: =IFERROR((F19-G19)/ABS(G19),"-") -> 0.30104856 | O79: =IFERROR((H19-I19)/ABS(I19),"-") -> 0.52083785 | P79: =IFERROR((I19-J19)/ABS(J19),"-") -> -0.12145694
K80: Maddi Olmayan Duran Varlıklar | L80: =IFERROR((B20-C20)/ABS(C20),"-") -> 0.62866647 | M80: =IFERROR((D20-E20)/ABS(E20),"-") -> 0.014083502 | N80: =IFERROR((F20-G20)/ABS(G20),"-") -> 0.49384256 | O80: =IFERROR((H20-I20)/ABS(I20),"-") -> 0.55721606 | P80: =IFERROR((I20-J20)/ABS(J20),"-") -> 0.91645165
K81: Peşin Ödenmiş Giderler (UV) | L81: =IFERROR((B21-C21)/ABS(C21),"-") -> -0.34244317 | M81: =IFERROR((D21-E21)/ABS(E21),"-") -> 0.38751951 | N81: =IFERROR((F21-G21)/ABS(G21),"-") -> 52.685425 | O81: =IFERROR((H21-I21)/ABS(I21),"-") -> -0.862472 | P81: =IFERROR((I21-J21)/ABS(J21),"-") -> 65.905636
K82: Ertelenmiş Vergi Varlığı | L82: =IFERROR((B22-C22)/ABS(C22),"-") -> -0.57060495 | M82: =IFERROR((D22-E22)/ABS(E22),"-") -> -0.1209311 | N82: =IFERROR((F22-G22)/ABS(G22),"-") -> 3.8142596 | O82: =IFERROR((H22-I22)/ABS(I22),"-") -> 0.3804298 | P82: =IFERROR((I22-J22)/ABS(J22),"-") -> -0.83519058
K83: DURAN VARLIKLAR TOPLAM | L83: =IFERROR((B23-C23)/ABS(C23),"-") -> 0.23212351 | M83: =IFERROR((D23-E23)/ABS(E23),"-") -> 0.21577927 | N83: =IFERROR((F23-G23)/ABS(G23),"-") -> 0.063705522 | O83: =IFERROR((H23-I23)/ABS(I23),"-") -> 0.61358719 | P83: =IFERROR((I23-J23)/ABS(J23),"-") -> 1.2388866
K84: TOPLAM VARLIKLAR | L84: =IFERROR((B24-C24)/ABS(C24),"-") -> 0.19612045 | M84: =IFERROR((D24-E24)/ABS(E24),"-") -> 0.027309955 | N84: =IFERROR((F24-G24)/ABS(G24),"-") -> 0.010915536 | O84: =IFERROR((H24-I24)/ABS(I24),"-") -> 0.60935846 | P84: =IFERROR((I24-J24)/ABS(J24),"-") -> 1.1730193
K85: Kısa Vadeli Borçlanmalar | L85: =IFERROR((B28-C28)/ABS(C28),"-") -> -0.22272519 | M85: =IFERROR((D28-E28)/ABS(E28),"-") -> 0.5569328 | N85: =IFERROR((F28-G28)/ABS(G28),"-") -> -0.25018987 | O85: =IFERROR((H28-I28)/ABS(I28),"-") -> 0.24441067 | P85: =IFERROR((I28-J28)/ABS(J28),"-") -> 1.6409017
K86: UV Borçlanmaların KV Kısımları | L86: =IFERROR((B29-C29)/ABS(C29),"-") -> 0.47576712 | M86: =IFERROR((D29-E29)/ABS(E29),"-") -> -0.11602797 | N86: =IFERROR((F29-G29)/ABS(G29),"-") -> 0.35203739 | O86: =IFERROR((H29-I29)/ABS(I29),"-") -> 0.90947813 | P86: =IFERROR((I29-J29)/ABS(J29),"-") -> -0.051987155
K87: KV Kiralama İşl. Borçları | L87: =IFERROR((B30-C30)/ABS(C30),"-") -> 8.8332617 | M87: =IFERROR((D30-E30)/ABS(E30),"-") -> 0.0022552152 | N87: =IFERROR((F30-G30)/ABS(G30),"-") -> -0.18238296 | O87: =IFERROR((H30-I30)/ABS(I30),"-") -> -0.63909774 | P87: =IFERROR((I30-J30)/ABS(J30),"-") -> 8.1227437
K88: UV Kiralama İşl. KV Kısımları | L88: =IFERROR((B31-C31)/ABS(C31),"-") -> 1.1652967 | M88: =IFERROR((D31-E31)/ABS(E31),"-") -> -0.41754627 | N88: =IFERROR((F31-G31)/ABS(G31),"-") -> 2.1168259 | O88: =IFERROR((H31-I31)/ABS(I31),"-") -> 1.3152252 | P88: =IFERROR((I31-J31)/ABS(J31),"-") -> -0.17608952
K89: Ticari Borçlar | L89: =IFERROR((B32-C32)/ABS(C32),"-") -> -0.46486836 | M89: =IFERROR((D32-E32)/ABS(E32),"-") -> 0.29169748 | N89: =IFERROR((F32-G32)/ABS(G32),"-") -> -0.048628065 | O89: =IFERROR((H32-I32)/ABS(I32),"-") -> 0.052865883 | P89: =IFERROR((I32-J32)/ABS(J32),"-") -> 1.5898607
K90: Çalışanlara Sağlanan Faydalar | L90: =IFERROR((B33-C33)/ABS(C33),"-") -> -0.12228957 | M90: =IFERROR((D33-E33)/ABS(E33),"-") -> -0.16176067 | N90: =IFERROR((F33-G33)/ABS(G33),"-") -> 0.76040054 | O90: =IFERROR((H33-I33)/ABS(I33),"-") -> 0.29292429 | P90: =IFERROR((I33-J33)/ABS(J33),"-") -> 1.115738
K91: Diğer Borçlar | L91: =IFERROR((B34-C34)/ABS(C34),"-") -> 0.011205015 | M91: =IFERROR((D34-E34)/ABS(E34),"-") -> -0.63684765 | N91: =IFERROR((F34-G34)/ABS(G34),"-") -> -0.086188448 | O91: =IFERROR((H34-I34)/ABS(I34),"-") -> 0.34403653 | P91: =IFERROR((I34-J34)/ABS(J34),"-") -> 0.78329449
K92: Türev Araçlar (yükümlülük) | L92: =IFERROR((B35-C35)/ABS(C35),"-") -> 0.054306928 | M92: =IFERROR((D35-E35)/ABS(E35),"-") -> - | N92: =IFERROR((F35-G35)/ABS(G35),"-") -> - | O92: =IFERROR((H35-I35)/ABS(I35),"-") -> -1 | P92: =IFERROR((I35-J35)/ABS(J35),"-") -> 0.36823901
K93: Dönem Karı Vergi Yükümlülüğü | L93: =IFERROR((B36-C36)/ABS(C36),"-") -> -0.24702071 | M93: =IFERROR((D36-E36)/ABS(E36),"-") -> -0.47155971 | N93: =IFERROR((F36-G36)/ABS(G36),"-") -> 0.44438216 | O93: =IFERROR((H36-I36)/ABS(I36),"-") -> -0.086139465 | P93: =IFERROR((I36-J36)/ABS(J36),"-") -> 2.4212615
K94: KV Karşılıklar | L94: =IFERROR((B37-C37)/ABS(C37),"-") -> 0.24628692 | M94: =IFERROR((D37-E37)/ABS(E37),"-") -> 1.98782 | N94: =IFERROR((F37-G37)/ABS(G37),"-") -> 0.01751269 | O94: =IFERROR((H37-I37)/ABS(I37),"-") -> 1.1032633 | P94: =IFERROR((I37-J37)/ABS(J37),"-") -> -0.52343226
K95: Diğer KV Yükümlülükler | L95: =IFERROR((B38-C38)/ABS(C38),"-") -> -0.72189335 | M95: =IFERROR((D38-E38)/ABS(E38),"-") -> 7.9661233 | N95: =IFERROR((F38-G38)/ABS(G38),"-") -> 0.2188134 | O95: =IFERROR((H38-I38)/ABS(I38),"-") -> 12.067433 | P95: =IFERROR((I38-J38)/ABS(J38),"-") -> -0.92979342
K96: KISA VADELİ YÜKÜMLÜLÜKLER TOPLAM | L96: =IFERROR((B39-C39)/ABS(C39),"-") -> -0.076850607 | M96: =IFERROR((D39-E39)/ABS(E39),"-") -> 0.092528834 | N96: =IFERROR((F39-G39)/ABS(G39),"-") -> 0.046404466 | O96: =IFERROR((H39-I39)/ABS(I39),"-") -> 0.27234632 | P96: =IFERROR((I39-J39)/ABS(J39),"-") -> 0.90191329
K97: Uzun Vadeli Borçlanmalar | L97: =IFERROR((B41-C41)/ABS(C41),"-") -> 0.79597995 | M97: =IFERROR((D41-E41)/ABS(E41),"-") -> 0.99903971 | N97: =IFERROR((F41-G41)/ABS(G41),"-") -> -0.18590527 | O97: =IFERROR((H41-I41)/ABS(I41),"-") -> 0.55402295 | P97: =IFERROR((I41-J41)/ABS(J41),"-") -> 1.9182147
K98: UV Kiralama İşl. Borçları | L98: =IFERROR((B42-C42)/ABS(C42),"-") -> -0.10072852 | M98: =IFERROR((D42-E42)/ABS(E42),"-") -> -0.20621326 | N98: =IFERROR((F42-G42)/ABS(G42),"-") -> 0.17224997 | O98: =IFERROR((H42-I42)/ABS(I42),"-") -> 0.18578546 | P98: =IFERROR((I42-J42)/ABS(J42),"-") -> -0.10052684
K99: Uzun Vadeli Karşılıklar | L99: =IFERROR((B43-C43)/ABS(C43),"-") -> -0.14189165 | M99: =IFERROR((D43-E43)/ABS(E43),"-") -> -0.89380714 | N99: =IFERROR((F43-G43)/ABS(G43),"-") -> 0.024518662 | O99: =IFERROR((H43-I43)/ABS(I43),"-") -> 0.5758071 | P99: =IFERROR((I43-J43)/ABS(J43),"-") -> 4.2363304
K100: Ertelenmiş Vergi Yükümlülüğü | L100: =IFERROR((B44-C44)/ABS(C44),"-") -> 0.69100725 | M100: =IFERROR((D44-E44)/ABS(E44),"-") -> 0.016731737 | N100: =IFERROR((F44-G44)/ABS(G44),"-") -> -0.51936218 | O100: =IFERROR((H44-I44)/ABS(I44),"-") -> 1.0341351 | P100: =IFERROR((I44-J44)/ABS(J44),"-") -> 0.46667596
K101: UZUN VADELİ YÜKÜMLÜLÜKLER TOPLAM | L101: =IFERROR((B45-C45)/ABS(C45),"-") -> 0.76682925 | M101: =IFERROR((D45-E45)/ABS(E45),"-") -> 0.54598345 | N101: =IFERROR((F45-G45)/ABS(G45),"-") -> -0.23140648 | O101: =IFERROR((H45-I45)/ABS(I45),"-") -> 0.65915866 | P101: =IFERROR((I45-J45)/ABS(J45),"-") -> 1.4013998
K102: TOPLAM YÜKÜMLÜLÜKLER | L102: =IFERROR((B46-C46)/ABS(C46),"-") -> 0.28777196 | M102: =IFERROR((D46-E46)/ABS(E46),"-") -> 0.2511262 | N102: =IFERROR((F46-G46)/ABS(G46),"-") -> -0.071035019 | O102: =IFERROR((H46-I46)/ABS(I46),"-") -> 0.41812962 | P102: =IFERROR((I46-J46)/ABS(J46),"-") -> 1.0636881
K103: Ödenmiş Sermaye | L103: =IFERROR((B49-C49)/ABS(C49),"-") -> 0 | M103: =IFERROR((D49-E49)/ABS(E49),"-") -> 0 | N103: =IFERROR((F49-G49)/ABS(G49),"-") -> 0 | O103: =IFERROR((H49-I49)/ABS(I49),"-") -> 0 | P103: =IFERROR((I49-J49)/ABS(J49),"-") -> 1
K104: Sermaye Düzeltme Farkları | L104: =IFERROR((B50-C50)/ABS(C50),"-") -> 0 | M104: =IFERROR((D50-E50)/ABS(E50),"-") -> 0 | N104: =IFERROR((F50-G50)/ABS(G50),"-") -> 0 | O104: =IFERROR((H50-I50)/ABS(I50),"-") -> 0 | P104: =IFERROR((I50-J50)/ABS(J50),"-") -> -0.95664177
...

Sheet AKSEN_PLS
A1: AKSA ENERJİ ÜRETİM A.Ş. — KONSOLİDE GELİR TABLOSU (Bin TL) | L1: DİKEY ANALİZ (% HASILAT)
A2: KALEM (BİN TL) | B2: 2025 (2025 SAG) | C2: 2024 (2025 SAG) | D2: 2024 (2024 SAG) | E2: 2023 (2024 SAG) | F2: 2023 (2023 SAG) | G2: 2022 (2023 SAG) | H2: 2022 (Nominal) | I2: 2021 (Nominal) | J2: 2020 (Nominal) | L2: 2025 (2025 SAG) | M2: 2024 (2025 SAG) | N2: 2024 (2024 SAG) | O2: 2023 (2024 SAG) | P2: 2023 (2023 SAG) | Q2: 2022 (2023 SAG) | R2: 2022 (Nominal) | S2: 2021 (Nominal) | T2: 2020 (Nominal)
A3: KAR VEYA ZARAR KISMI
A4: Hasılat (Net) | B4: 42385314 | C4: 41412051 | D4: 31638820 | E4: 50781705 | F4: 35172257 | G4: 87101671 | H4: 45638094 | I4: 13887497 | J4: 7230547 | L4: =IFERROR(B4/B4,"") -> 1 | M4: =IFERROR(C4/C4,"") -> 1 | N4: =IFERROR(D4/D4,"") -> 1 | O4: =IFERROR(E4/E4,"") -> 1 | P4: =IFERROR(F4/F4,"") -> 1 | Q4: =IFERROR(G4/G4,"") -> 1 | R4: =IFERROR(H4/H4,"") -> 1 | S4: =IFERROR(I4/I4,"") -> 1 | T4: =IFERROR(J4/J4,"") -> 1
A5: Satışların Maliyeti (-) | B5: -31840584 | C5: -32657898 | D5: -24950644 | E5: -40364108 | F5: -27956855 | G5: -76510665 | H5: -40190386 | I5: -11808767 | J5: -6032956 | L5: =IFERROR(B5/B4,"") -> -0.75121737 | M5: =IFERROR(C5/C4,"") -> -0.78860856 | N5: =IFERROR(D5/D4,"") -> -0.78860855 | O5: =IFERROR(E5/E4,"") -> -0.79485531 | P5: =IFERROR(F5/F4,"") -> -0.7948553 | Q5: =IFERROR(G5/G4,"") -> -0.8784064 | R5: =IFERROR(H5/H4,"") -> -0.88063244 | S5: =IFERROR(I5/I4,"") -> -0.85031644 | T5: =IFERROR(J5/J4,"") -> -0.83437062
A6: BRÜT KAR / (ZARAR) | B6: =B4+B5 -> 10544730 | C6: =C4+C5 -> 8754153 | D6: =D4+D5 -> 6688176 | E6: =E4+E5 -> 10417597 | F6: =F4+F5 -> 7215402 | G6: =G4+G5 -> 10591006 | H6: =H4+H5 -> 5447708 | I6: =I4+I5 -> 2078730 | J6: =J4+J5 -> 1197591 | L6: =IFERROR(B6/B4,"") -> 0.24878263 | M6: =IFERROR(C6/C4,"") -> 0.21139144 | N6: =IFERROR(D6/D4,"") -> 0.21139145 | O6: =IFERROR(E6/E4,"") -> 0.20514469 | P6: =IFERROR(F6/F4,"") -> 0.2051447 | Q6: =IFERROR(G6/G4,"") -> 0.1215936 | R6: =IFERROR(H6/H4,"") -> 0.11936756 | S6: =IFERROR(I6/I4,"") -> 0.14968356 | T6: =IFERROR(J6/J4,"") -> 0.16562938
